Workbook

Sheet Overview
A1: Layer 1 frontend — complete project workbook
A2: Five products plus a shared HTTP kit, delivered in parallel with backend SP-00 … SP-04. Source of truth: docs/api/catalog/*.php — b (request body) / r (data shape) / e (error codes).
A4: Contents
A5: Products | B5: The six delivery units: repository, surface, guard, X-Client, backend dependency and volume.
A6: Epics | B6: The 20 epics with scope, sequencing constraints and the manual acceptance walkthrough.
A7: Backlog | B7: Every issue, one row, with full requirements and acceptance criteria readable in place.
A8: Delivery Plan | B8: Points and issue counts per week and team, and per backend gate. All figures are formulas over the Backlog sheet.
A9: Dependencies | B9: One row per blocking link, with cross-product links flagged.
A10: API Index | B10: Every endpoint and EP-ID the layer touches, and which issues consume it.
A11: Screens | B11: Every FE-* screen identifier and the issues that build it.
A12: Error Map | B12: The twelve envelope error codes and the required client behaviour.
A13: Header Policy | B13: Request headers, exemptions, forbidden paths, money and list rules.
A14: Risks | B14: Risk register with the issue that mitigates each risk.
A15: Jira Import | B15: Flat machine-readable sheet. Save this tab alone as CSV UTF-8 and import.
A17: Definition of done — applies to every issue in this workbook
A18: 1. | B18: Runs against real staging — no mock data in the merged branch.
A19: 2. | B19: HTTP 422 paints the named fields from error.details.{field}, never a generic banner.
A20: 3. | B20: Every write carries X-Idempotency-Key tied to the confirm tap; a network retry reuses the same key.
A21: 4. | B21: Permissions drive visibility: a control the user cannot use is absent or disabled.
A22: 5. | B22: Loading, empty, error and offline states are all implemented.
A23: 6. | B23: RTL layout is correct and every amount, limit and FX rate is an integer.
A24: 7. | B24: No request is made to any path outside the L1 allowlist (enforced by FE-CORE-10).
A25: 8. | B25: The PR contains a screenshot or GIF of the journey and names the EP-ID used.
A26: 9. | B26: Zero console errors and zero new lint warnings.
A28: Totals
A29: Products | B29: =COUNTA(Products!A2:A20) -> 6
A30: Epics | B30: =COUNTA(Epics!A2:A100) -> 20
A31: Issues | B31: =COUNTA(Backlog!A2:A120) -> 119
A32: Story points | B32: =SUM(Backlog!N2:N120) -> 318
A33: Blocking links | B33: =COUNTA(Dependencies!A2:A400) -> 191
A35: Exporting to Jira
A36: Step 1 | B36: Create the components first: api-client, ui-kit, ci, packages/b2b-auth-flow, apps/retailer, apps/rep, apps/channel-web, apps/warehouse-web, apps/platform-web.
A37: Step 2 | B37: Confirm Story Points and Epic Link are on the issue screens for both Story and Task types. This is the commonest cause of silently dropped values.
A38: Step 3 | B38: Open the Jira Import tab, then File > Save As > CSV UTF-8. Export that tab alone; do not reformat it and do not export the Backlog tab.
A39: Step 4 | B39: Import the whole file in a single run. Issue ID and Blocked By only resolve within one import.
A40: Step 5 | B40: Verify: 20 epics appear, and RT-18, RP-10, CH-10, WH-07 each show a long "is blocked by" list.
A41: Note | B41: Team-managed Jira projects do not expose Epic Link or Epic Name. Import into a company-managed project, or delete those two columns and set parents in bulk afterwards using the EP- prefix in each summary.

Sheet Products
A1: Product | B1: Team | C1: Repository | D1: Surface | E1: Guard | F1: X-Client | G1: Delivery window | H1: Backend dependency | I1: Source brief | J1: Issues | K1: Points
A2: Shared API client | B2: Platform Engineering | C2: packages/b2b-api-client (built first inside apps/platform-web, then extracted) | D2: Library consumed by all five products | E2: Not applicable — transport layer | F2: Set per consuming product | G2: A → C (tagged v0.1.0 by end of week C) | H2: SP-00 (GET /health, EP-CORE-001) · SP-01 (token guards) | I2: 00-shared-api-client.md | J2: 10 | K2: 36
A3: Retailer app | B3: Mobile | C3: apps/retailer | D3: Android / iOS | E3: app | F3: retailer-android · retailer-ios | G3: B (identity) → D (shop form, after SP-03) | H3: SP-01 (OTP + register) · SP-03 (/public/refs for the form) | I3: 01-retailer-app.md — DOC-12A | J3: 18 | K3: 44
A4: Field rep app | B4: Mobile | C4: apps/rep | D4: Android / iOS — a separate binary from the retailer app | E4: app | F4: rep-android · rep-ios | G4: B (identity) → E (registration, after SP-04) | H4: SP-01 · SP-03 (activity types / zones) · SP-04 (channel invite id) | I4: 02-rep-app.md — DOC-12B | J4: 10 | K4: 21
A5: Channel dashboard | B5: Ops Web | C5: apps/channel-web | D5: Web, RTL | E5: channel | F5: channel-web | G5: B → C | H5: SP-01 (/channel/auth/* only) | I5: 03-channel-dashboard.md — DOC-12C | J5: 10 | K5: 18
A6: Warehouse web | B6: Ops Web | C6: apps/warehouse-web | D6: Web or locked desktop browser, RTL, large hit targets | E6: warehouse | F6: warehouse-web | G6: B → C | H6: SP-01 (POST /warehouse/auth/device-login only) | I6: 04-warehouse-web.md — DOC-12D | J6: 7 | K6: 13
A7: Platform admin | B7: Platform Dashboard | C7: apps/platform-web | D7: Web, RTL | E7: platform | F7: platform-web | G7: A → E (spans the whole layer) | H7: SP-01 account · SP-02 IAM · SP-03 refs · SP-04 channels | I7: 05-platform-admin.md — DOC-12E + DOC-07 | J7: 64 | K7: 186

Sheet Epics
A1: Epic key | B1: Product | C1: Epic name | D1: Covers | E1: Issues | F1: Points | G1: In scope | H1: Out of scope | I1: Sequencing constraints | J1: Manual walkthrough | K1: Planning note
A2: EP-CORE-NET | B2: Shared API client | C2: Transport and errors | D2: Envelope client, error map, idempotency | E2: 2 | F2: 10 | G2: • Envelope client, error map, header policy, secure token storage. • Idempotency store keyed on user intent rather than on the network request. • can(code) permission layer and public refs cache. • Automated guardrails: path allowlist and catalog-generated contract tests. | H2: • Any screen logic or view state belonging to a single product. • Offline sync or a deferred request queue — not in L1. • Any handling of Layer 2+ paths even if the server answers them. | I2: • FE-CORE-01 → 02 → 03 in order; each builds on the previous one. • FE-CORE-10 (allowlist) must merge before the end of week B, otherwise Layer 2 calls leak into main undetected. • The v0.1.0 tag is a gate: no product screen branch opens in any repository before it. • Governance: changes to the error map or header policy go through a PR on the package. Copying the code into a product repo instead of upgrading the package is a review rejection. | J2: 1. Verified through the acceptance walkthroughs of the five consuming products. | K2: Create one project (L1-FE) and a component per product. Core issues are Task type because they produce no direct user value, and Highest priority because they block all five teams. FE-CORE-01 … 05 keep the IDs used by the product briefs; FE-CORE-10 and above are additional infrastructure introduced by this backlog.
A3: EP-CORE-SEC | B3: Shared API client | C3: Identity and permissions | D3: Headers, token store, can() | E3: 2 | F3: 8 | G3: • Envelope client, error map, header policy, secure token storage. • Idempotency store keyed on user intent rather than on the network request. • can(code) permission layer and public refs cache. • Automated guardrails: path allowlist and catalog-generated contract tests. | H3: • Any screen logic or view state belonging to a single product. • Offline sync or a deferred request queue — not in L1. • Any handling of Layer 2+ paths even if the server answers them. | I3: • FE-CORE-01 → 02 → 03 in order; each builds on the previous one. • FE-CORE-10 (allowlist) must merge before the end of week B, otherwise Layer 2 calls leak into main undetected. • The v0.1.0 tag is a gate: no product screen branch opens in any repository before it. • Governance: changes to the error map or header policy go through a PR on the package. Copying the code into a product repo instead of upgrading the package is a review rejection. | J3: 1. Verified through the acceptance walkthroughs of the five consuming products. | K3: Create one project (L1-FE) and a component per product. Core issues are Task type because they produce no direct user value, and Highest priority because they block all five teams. FE-CORE-01 … 05 keep the IDs used by the product briefs; FE-CORE-10 and above are additional infrastructure introduced by this backlog.
A4: EP-CORE-PLT | B4: Shared API client | C4: Platform and guardrails | D4: Refs cache, i18n, money, CI, allowlist, contract tests | E4: 6 | F4: 18 | G4: • Envelope client, error map, header policy, secure token storage. • Idempotency store keyed on user intent rather than on the network request. • can(code) permission layer and public refs cache. • Automated guardrails: path allowlist and catalog-generated contract tests. | H4: • Any screen logic or view state belonging to a single product. • Offline sync or a deferred request queue — not in L1. • Any handling of Layer 2+ paths even if the server answers them. | I4: • FE-CORE-01 → 02 → 03 in order; each builds on the previous one. • FE-CORE-10 (allowlist) must merge before the end of week B, otherwise Layer 2 calls leak into main undetected. • The v0.1.0 tag is a gate: no product screen branch opens in any repository before it. • Governance: changes to the error map or header policy go through a PR on the package. Copying the code into a product repo instead of upgrading the package is a review rejection. | J4: 1. Verified through the acceptance walkthroughs of the five consuming products. | K4: Create one project (L1-FE) and a component per product. Core issues are Task type because they produce no direct user value, and Highest priority because they block all five teams. FE-CORE-01 … 05 keep the IDs used by the product briefs; FE-CORE-10 and above are additional infrastructure introduced by this backlog.
A5: EP-RT-A | B5: Retailer app | C5: Identity and sign-in | D5: FE-RT-SPLASH, FE-RT-PHONE, FE-RT-OTP | E5: 6 | F5: 15 | G5: • Splash routing, phone screen and OTP screen. • The full shop registration form bound to GET /public/refs. • Waiting, rejected and empty-home screens. • Session router on cold start and logout with a full local wipe. | H5: • Retailer home feed, favourites, cart, orders, tracking, payments. • points and tier (SP-15) even when catalog examples include them. • Product tabs (Home / Orders / Account) — account in L1 is phone display plus logout. • Legal product screens, offline sync, GET /public/app-config. | I5: • RT-01 first: the routing graph determines everything built after it. • RT-02 → RT-06 land in week B as soon as SP-01 is available. • RT-07 → RT-10 are blocked until GET /public/refs ships in SP-03. The shop form cannot close without it. • RT-18 does not close until all four walkthrough scenarios have been run manually and recorded. | J5: 1. Invalid phone returns an Arabic 422 painted on the field. 2. A new number completes OTP, then the form, and lands on Waiting. 3. An existing approved shop completes OTP and lands on Empty home. 4. Logout returns to Phone, and the OS back gesture does not restore the register form with a live session. | K5: Component apps/retailer. Identity issues are Highest because they open the acceptance journey; the registration form is High because it is blocked on SP-03.
A6: EP-RT-B | B6: Retailer app | C6: Shop file | D6: FE-RT-REGISTER and /public/refs | E6: 4 | F6: 13 | G6: • Splash routing, phone screen and OTP screen. • The full shop registration form bound to GET /public/refs. • Waiting, rejected and empty-home screens. • Session router on cold start and logout with a full local wipe. | H6: • Retailer home feed, favourites, cart, orders, tracking, payments. • points and tier (SP-15) even when catalog examples include them. • Product tabs (Home / Orders / Account) — account in L1 is phone display plus logout. • Legal product screens, offline sync, GET /public/app-config. | I6: • RT-01 first: the routing graph determines everything built after it. • RT-02 → RT-06 land in week B as soon as SP-01 is available. • RT-07 → RT-10 are blocked until GET /public/refs ships in SP-03. The shop form cannot close without it. • RT-18 does not close until all four walkthrough scenarios have been run manually and recorded. | J6: 1. Invalid phone returns an Arabic 422 painted on the field. 2. A new number completes OTP, then the form, and lands on Waiting. 3. An existing approved shop completes OTP and lands on Empty home. 4. Logout returns to Phone, and the OS back gesture does not restore the register form with a live session. | K6: Component apps/retailer. Identity issues are Highest because they open the acceptance journey; the registration form is High because it is blocked on SP-03.
A7: EP-RT-C | B7: Retailer app | C7: Lifecycle | D7: FE-RT-WAIT, FE-RT-SESSION, FE-RT-HOME-EMPTY, FE-RT-LOGOUT | E7: 6 | F7: 11 | G7: • Splash routing, phone screen and OTP screen. • The full shop registration form bound to GET /public/refs. • Waiting, rejected and empty-home screens. • Session router on cold start and logout with a full local wipe. | H7: • Retailer home feed, favourites, cart, orders, tracking, payments. • points and tier (SP-15) even when catalog examples include them. • Product tabs (Home / Orders / Account) — account in L1 is phone display plus logout. • Legal product screens, offline sync, GET /public/app-config. | I7: • RT-01 first: the routing graph determines everything built after it. • RT-02 → RT-06 land in week B as soon as SP-01 is available. • RT-07 → RT-10 are blocked until GET /public/refs ships in SP-03. The shop form cannot close without it. • RT-18 does not close until all four walkthrough scenarios have been run manually and recorded. | J7: 1. Invalid phone returns an Arabic 422 painted on the field. 2. A new number completes OTP, then the form, and lands on Waiting. 3. An existing approved shop completes OTP and lands on Empty home. 4. Logout returns to Phone, and the OS back gesture does not restore the register form with a live session. | K7: Component apps/retailer. Identity issues are Highest because they open the acceptance journey; the registration form is High because it is blocked on SP-03.
A8: EP-RT-D | B8: Retailer app | C8: Packaging and acceptance | D8: Build, distribution, manual walkthrough | E8: 2 | F8: 5 | G8: • Splash routing, phone screen and OTP screen. • The full shop registration form bound to GET /public/refs. • Waiting, rejected and empty-home screens. • Session router on cold start and logout with a full local wipe. | H8: • Retailer home feed, favourites, cart, orders, tracking, payments. • points and tier (SP-15) even when catalog examples include them. • Product tabs (Home / Orders / Account) — account in L1 is phone display plus logout. • Legal product screens, offline sync, GET /public/app-config. | I8: • RT-01 first: the routing graph determines everything built after it. • RT-02 → RT-06 land in week B as soon as SP-01 is available. • RT-07 → RT-10 are blocked until GET /public/refs ships in SP-03. The shop form cannot close without it. • RT-18 does not close until all four walkthrough scenarios have been run manually and recorded. | J8: 1. Invalid phone returns an Arabic 422 painted on the field. 2. A new number completes OTP, then the form, and lands on Waiting. 3. An existing approved shop completes OTP and lands on Empty home. 4. Logout returns to Phone, and the OS back gesture does not restore the register form with a live session. | K8: Component apps/retailer. Identity issues are Highest because they open the acceptance journey; the registration form is High because it is blocked on SP-03.
A9: EP-RP-A | B9: Field rep app | C9: Shared package and setup | D9: Identity flow extraction, separate binary | E9: 3 | F9: 6 | G9: • Extraction of the identity flow into a shared package, then consumption of it. • Invite deep link capture of channel_id and a locked channel field. • Rep registration form with multi-zone selection. • Waiting, empty home, session and logout. | H9: • GET /app/rep/products, customers, zone shops, carts, assignments, handover, wallet, live location. • Any channel list or search — GET /public/refs does not list channels (REQ-IN-06). • Any in-app switch to the retailer product. | I9: • RP-01 comes first: extracting the shared identity package is an architectural issue, not an optimisation. • RP-04 → RP-07 are blocked until SP-04, because channel_id comes from an invite link issued after the platform creates the channel. • No issue may render a channel list. The only paths are the invite link and the guidance screen. | J9: 1. Submit is impossible without channel_id. 2. Zones outside the channel coverage keep the form and show the server field error. 3. Invite → OTP → Waiting completes without a platform token on the device. | K9: The low estimate for this product is conditional on RP-01. If it is dropped under schedule pressure the total rises to roughly 35 points and two divergent copies of the OTP error logic appear.
A10: EP-RP-B | B10: Field rep app | C10: Invite and registration | D10: Deep link, channel_id, zone_ids | E10: 4 | F10: 9 | G10: • Extraction of the identity flow into a shared package, then consumption of it. • Invite deep link capture of channel_id and a locked channel field. • Rep registration form with multi-zone selection. • Waiting, empty home, session and logout. | H10: • GET /app/rep/products, customers, zone shops, carts, assignments, handover, wallet, live location. • Any channel list or search — GET /public/refs does not list channels (REQ-IN-06). • Any in-app switch to the retailer product. | I10: • RP-01 comes first: extracting the shared identity package is an architectural issue, not an optimisation. • RP-04 → RP-07 are blocked until SP-04, because channel_id comes from an invite link issued after the platform creates the channel. • No issue may render a channel list. The only paths are the invite link and the guidance screen. | J10: 1. Submit is impossible without channel_id. 2. Zones outside the channel coverage keep the form and show the server field error. 3. Invite → OTP → Waiting completes without a platform token on the device. | K10: The low estimate for this product is conditional on RP-01. If it is dropped under schedule pressure the total rises to roughly 35 points and two divergent copies of the OTP error logic appear.
A11: EP-RP-C | B11: Field rep app | C11: Lifecycle and acceptance | D11: Waiting, empty home, session, walkthrough | E11: 3 | F11: 6 | G11: • Extraction of the identity flow into a shared package, then consumption of it. • Invite deep link capture of channel_id and a locked channel field. • Rep registration form with multi-zone selection. • Waiting, empty home, session and logout. | H11: • GET /app/rep/products, customers, zone shops, carts, assignments, handover, wallet, live location. • Any channel list or search — GET /public/refs does not list channels (REQ-IN-06). • Any in-app switch to the retailer product. | I11: • RP-01 comes first: extracting the shared identity package is an architectural issue, not an optimisation. • RP-04 → RP-07 are blocked until SP-04, because channel_id comes from an invite link issued after the platform creates the channel. • No issue may render a channel list. The only paths are the invite link and the guidance screen. | J11: 1. Submit is impossible without channel_id. 2. Zones outside the channel coverage keep the form and show the server field error. 3. Invite → OTP → Waiting completes without a platform token on the device. | K11: The low estimate for this product is conditional on RP-01. If it is dropped under schedule pressure the total rises to roughly 35 points and two divergent copies of the OTP error logic appear.
A12: EP-CH-A | B12: Channel dashboard | C12: Sign-in and channel selection | D12: FE-CH-PHONE, FE-CH-OTP, FE-CH-PICK | E12: 4 | F12: 9 | G12: • Phone and OTP sign-in on the channel auth contract. • Channel picker and X-Channel-Id pinning for multi-channel members. • Shell with a sidebar generated from permissions[]. • Empty office and local sign-out. | H12: • /channel/brands, /channel/products, orders, stock, finance, dashboard widgets. • /catalog, /orders and /reps routes — disabled nav labels only, with no page and no fetch. • Any chart or GMV figure on /home. | I12: • CH-01 sets the scope ceiling: four routes, everything else 404. • CH-02 depends on the contract test in FE-CORE-14 to prevent purpose from being sent. • CH-09 is a closing condition for the whole product. | J12: 1. A manager completes OTP, picks a channel when they have two, lands on an empty office and signs out. 2. DevTools shows zero calls to /channel/products or /channel/brands during the journey. | K12: The primary risk on this product is scope creep into "coming soon" pages that call Layer 2 APIs. CH-09 exists specifically to kill that risk automatically, and the epic does not close without it.
A13: EP-CH-B | B13: Channel dashboard | C13: Shell and office | D13: FE-CH-SHELL, /home, FE-CH-LOGOUT | E13: 4 | F13: 6 | G13: • Phone and OTP sign-in on the channel auth contract. • Channel picker and X-Channel-Id pinning for multi-channel members. • Shell with a sidebar generated from permissions[]. • Empty office and local sign-out. | H13: • /channel/brands, /channel/products, orders, stock, finance, dashboard widgets. • /catalog, /orders and /reps routes — disabled nav labels only, with no page and no fetch. • Any chart or GMV figure on /home. | I13: • CH-01 sets the scope ceiling: four routes, everything else 404. • CH-02 depends on the contract test in FE-CORE-14 to prevent purpose from being sent. • CH-09 is a closing condition for the whole product. | J13: 1. A manager completes OTP, picks a channel when they have two, lands on an empty office and signs out. 2. DevTools shows zero calls to /channel/products or /channel/brands during the journey. | K13: The primary risk on this product is scope creep into "coming soon" pages that call Layer 2 APIs. CH-09 exists specifically to kill that risk automatically, and the epic does not close without it.
... A21: EP-AD-CH | B21: Platform admin | C21: SP-04 channels | D21: List, create and provisioning, card tabs, join applications | E21: 21 | F21: 62 | G21: • Login, TOTP, boot, logout and the five tabs of /me. • Full IAM: permission catalog, roles with dual approval, assignments, simulation, temp grants, SoD, approval inbox, audit, access review. • Seven reference entities, FX rates and import with dry-run preview. • Channel lifecycle: list, create and provisioning, card tabs, join applications. | H21: • GET /platform/dashboard and any operations chart (SP-16). • Notification campaign builder (SP-14), plan SKU catalog and platform team CRUD (SP-17). • Impersonation, and any SoD rule editor — SoD is read-only in L1. | I21: • EP-AD-SHELL closes before any SP-02, SP-03 or SP-04 issue starts. Every later screen consumes the generic table, the reason modal, the password-confirm modal and the dual-approval handler. • AD-03 precedes every crit route: AD-15, AD-69, AD-76 and AD-77. • AD-40 (reference factory) precedes AD-41 … AD-47. Starting with a single entity before the factory creates immediate technical debt and roughly triples the SP-03 cost. • AD-65 is a closing condition for AD-64: creation is not done while the channel sits in provisioning. • Any issue that renders an operational figure prints the server value verbatim. Derivation, estimation or a decorative sparkline is a review rejection. | J21: 1. Login → 2FA → channel list, empty or seeded. 2. Create a governorate and a zone. 3. Create a channel: the UI shows provisioning then active, or offers retry. 4. Create a role that stays draft until a second user approves it. 5. Disable a zone: reason required and impact counts shown before the second confirm. 6. No dashboard-charts route exists anywhere in the app. | K21: This product consumes roughly 57% of the layer points. Order the epics exactly as listed, and do not allow an issue from EP-AD-REFS or EP-AD-CH to be pulled before EP-AD-SHELL closes.

Sheet Backlog
A1: Key | B1: Product | C1: Team | D1: Type | E1: Title | F1: Epic | G1: Component | H1: Screen ID | I1: API contract | J1: Requirements | K1: Error handling | L1: Acceptance criteria | M1: Out of scope | N1: Points | O1: Priority | P1: Sprint | Q1: Backend gate | R1: Blocked by | S1: Labels
A2: FE-CORE-01 | B2: Shared API client | C2: Platform Engineering | D2: Task | E2: Envelope client and error map | F2: EP-CORE-NET | G2: api-client | H2: Not screen-bound | I2: GET /api/v1/health (EP-CORE-001) · error contract e in the catalog | J2: 1. baseURL is fixed to /api/v1 with per-environment host configuration. 2. On success, expose data to the UI only; retain meta.server_time for clock-skew correction. 3. On failure, surface error.message. A raw Laravel validation JSON must never reach a component. 4. Implement one central map from error.code to client behaviour covering all twelve codes in the shared kit. 5. Timeouts, GET-only automatic retry, and request cancellation on screen exit. | K2: • validation_failed → inline field errors (422); rate_limited → disable submit, honour resend_after / Retry-After. • unauthenticated and token_revoked → drop token, route to login. • otp_invalid → clear the OTP boxes, never auto-request a new OTP. • insufficient_permission → toast and hide the action; requires_password_confirm → platform password modal then replay. • sod_violation → explain the conflict, do not resubmit blindly. • conflict / illegal_transition / idempotency_key_conflict → stop and show the server message. • idempotency_key_required → treat as a client bug: log it and fail the production build. • operation_in_progress → wait, then retry with the same key. | L2: ☐ GET /health returns data.status = ok through the client. ☐ No envelope field (meta, success) reaches a UI component. ☐ A unit test exists for each of the twelve error codes. ☐ Automatic retry never applies to POST, PUT, PATCH or DELETE. | M2: Toast and modal presentation components — those live in FE-CORE-12. | N2: 5 | O2: Highest | P2: Week A | Q2: SP-00 | R2: None | S2: L1, core, http, errors
A3: FE-CORE-02 | B3: Shared API client | C3: Platform Engineering | D3: Task | E3: Header injection and secure token store | F3: EP-CORE-SEC | G3: api-client | H3: Not screen-bound | I3: All authenticated paths | J3: 1. Inject Accept, Accept-Language, X-Client, X-App-Version on every request. 2. Inject X-Device-Id on mobile and warehouse surfaces: a stable UUID generated once per install. 3. Inject Authorization: Bearer {token} after login, and X-Channel-Id on the channel dashboard when the user belongs to more than one channel. 4. Store the token in Keychain / Keystore on mobile and in restricted storage on web. 5. Exempt from Bearer: GET /health and GET /public/refs. 6. Block the forbidden paths /api/v1/auth/* and /admin/channels at the client layer. | K3: No contract-specific codes. Use the shared error map in FE-CORE-01. | L3: ☐ After logout no Bearer appears on any subsequent request. ☐ X-Device-Id is stable across application restarts and reinstall where the platform allows it. ☐ A call to a forbidden path throws at development time rather than reaching the network. | M3: Nothing beyond the product scope on the parent epic. | N3: 5 | O3: Highest | P3: Week A | Q3: SP-00 | R3: FE-CORE-01 | S3: L1, core, auth, headers
A4: FE-CORE-03 | B4: Shared API client | C4: Platform Engineering | D4: Task | E4: Idempotency store tied to confirm buttons | F4: EP-CORE-NET | G4: api-client | H4: Not screen-bound | I4: X-Idempotency-Key on POST / PUT / PATCH / DELETE | J4: 1. One UUID per user intent (confirm tap), not per network request. 2. A retry after a dropped connection reuses the same key; a new confirm tap generates a new key. 3. Expose a small API, for example withIdempotency(intentId), that wraps the call. 4. Apply the shared-kit exemption list: public OTP request / verify / resend, platform login and 2FA, channel OTP, and warehouse device-login do not carry a key. 5. A write outside the exemption list must never leave the client without a key. | K4: No contract-specific codes. Use the shared error map in FE-CORE-01. | L4: ☐ A dropped connection followed by a retry does not create a duplicate write when the key is reused. ☐ A second confirm tap produces a different UUID, observable in the request log. ☐ operation_in_progress retries with the same key after a short backoff. ☐ A non-exempt write attempted without a key fails loudly in development. | M4: Nothing beyond the product scope on the parent epic. | N4: 5 | O4: Highest | P4: Week B | Q4: SP-00 | R4: FE-CORE-01 | S4: L1, core, idempotency
A5: FE-CORE-04 | B5: Shared API client | C5: Platform Engineering | D5: Task | E5: can(code) permission layer | F5: EP-CORE-SEC | G5: api-client | H5: Not screen-bound | I5: permissions[] from session and login responses | J5: 1. can(code) derived from the permissions[] persisted after sign-in. 2. Provide a <Can> wrapper component and a withPermission route guard. 3. Permissions refresh on session boot and on channel switch. | K5: No contract-specific codes. Use the shared error map in FE-CORE-01. | L5: ☐ A control the user lacks permission for is absent from the tree or rendered disabled with a tooltip. ☐ A guarded route does not build its network call before the check runs. | M5: Nothing beyond the product scope on the parent epic. | N5: 3 | O5: Highest | P5: Week B | Q5: SP-00 | R5: FE-CORE-02 | S5: L1, core, iam
A6: FE-CORE-05 | B6: Shared API client | C6: Platform Engineering | D6: Task | E6: Public refs cache keyed by sync_cursor | F6: EP-CORE-PLT | G6: api-client | H6: Not screen-bound | I6: GET /public/refs (EP-PB-001) | J6: 1. Cache the response under its sync_cursor and send since= when a cursor exists. 2. Expose selectors for activity_types, root_categories, equipments, governorates and zones. 3. Invalidate on logout and on language change. 4. This path carries neither Bearer nor an idempotency key. | K6: No contract-specific codes. Use the shared error map in FE-CORE-01. | L6: ☐ Changing the zone list on the server is reflected after a since= call. ☐ Refs are not fully re-downloaded on every cold start. ☐ Selecting a governorate filters zones by zone.governorate_id. | M6: Nothing beyond the product scope on the parent epic. | N6: 3 | O6: High | P6: Week B | Q6: SP-00 | R6: FE-CORE-01 | S6: L1, core, refs
A7: FE-CORE-10 | B7: Shared API client | C7: Platform Engineering | D7: Task | E7: Path allowlist guardrail | F7: EP-CORE-PLT | G7: ci | H7: Not screen-bound | I7: L1 allowlist derived from the catalog | J7: 1. Maintain an allowlist of the paths permitted in Layer 1. 2. Fail the test suite on any request outside it, including /api/v1/auth/*, /admin/channels and every path from SP-06 onward. 3. Print every path exercised during the run in the report. | K7: No contract-specific codes. Use the shared error map in FE-CORE-01. | L7: ☐ Calling GET /channel/products or GET /warehouse/queues fails the build. ☐ The report lists all paths touched by the journey tests. | M7: Nothing beyond the product scope on the parent epic. | N7: 3 | O7: Highest | P7: Week B | Q7: SP-00 | R7: FE-CORE-01 | S7: L1, core, guardrail, ci
A8: FE-CORE-11 | B8: Shared API client | C8: Platform Engineering | D8: Task | E8: i18n, RTL and integer money formatting | F8: EP-CORE-PLT | G8: api-client | H8: Not screen-bound | I8: decimals from the currency entity | J8: 1. Amounts, limits and FX rate are transported and stored as integers exactly as the server sends them. 2. Display uses the currency decimals value; SYP renders with zero decimal places. 3. RTL is the default layout with an en switch available. 4. Accept-Language follows the active locale. | K8: No contract-specific codes. Use the shared error map in FE-CORE-01. | L8: ☐ A value of 15000 in SYP renders as 15,000 with no fractional part. ☐ A type check proves no float exists on any money path. | M8: Nothing beyond the product scope on the parent epic. | N8: 3 | O8: High | P8: Week B | Q8: SP-00 | R8: None | S8: L1, core, i18n, money
A9: FE-CORE-12 | B9: Shared API client | C9: Platform Engineering | D9: Task | E9: Shared state templates and toast system | F9: EP-CORE-PLT | G9: ui-kit | H9: Not screen-bound | I9: — | J9: 1. Provide Loading, Empty, Error and Offline templates with approved Arabic copy. 2. Provide a toast system and a base modal consumed by all five products. 3. The Error template renders envelope errors, not raw exceptions. | K9: No contract-specific codes. Use the shared error map in FE-CORE-01. | L9: ☐ Every later screen consumes the template instead of writing its own state. ☐ The Offline state appears within two seconds of connection loss. | M9: Nothing beyond the product scope on the parent epic. | N9: 3 | O9: High | P9: Week B | Q9: SP-00 | R9: None | S9: L1, core, ui
A10: FE-CORE-13 | B10: Shared API client | C10: Platform Engineering | D10: Task | E10: Repository scaffold and CI pipeline | F10: EP-CORE-PLT | G10: ci | H10: Not screen-bound | I10: — | J10: 1. Strict types, lint, tests and a build target per product. 2. Publish the package internally under a semantic tag. 3. Block merges on a red pipeline. | K10: No contract-specific codes. Use the shared error map in FE-CORE-01. | L10: ☐ A failing PR cannot be merged. ☐ The package is published as v0.1.0 and consumed by at least two repositories. | M10: Nothing beyond the product scope on the parent epic. | N10: 3 | O10: Highest | P10: Week A | Q10: SP-00 | R10: None | S10: L1, core, ci
A11: FE-CORE-14 | B11: Shared API client | C11: Platform Engineering | D11: Task | E11: Contract tests generated from the catalog | F11: EP-CORE-PLT | G11: ci | H11: Not screen-bound | I11: docs/api/catalog/*.php — field b | J11: 1. Generate tests that compare the outgoing request body against field b in the catalog. 2. Cover extra keys, missing keys and wrong types. 3. Run the suite in CI on every PR. | K11: No contract-specific codes. Use the shared error map in FE-CORE-01. | L11: ☐ Sending purpose to /channel/auth/request-otp fails the test. ☐ Adding a key absent from b fails the test. | M11: Nothing beyond the product scope on the parent epic. | N11: 3 | O11: High | P11: Week B | Q11: SP-00 | R11: FE-CORE-13 | S11: L1, core, contract-tests
A12: RT-01 | B12: Retailer app | C12: Mobile | D12: Story | E12: App scaffold and splash routing | F12: EP-RT-A | G12: apps/retailer | H12: FE-RT-SPLASH | I12: GET /app/session (EP-CM-004) on cold start when a token exists | J12: 1. Router exposes exactly six screens: Splash, Phone, OTP, Register, Waiting/Rejected, Empty home. 2. On cold start with no token, route to Phone. 3. On cold start with a token, call the session router and branch per §3.6 of the brief. 4. Five splash branches: no token, registration-ability token, pending_review, rejected, full token with active status. | K12: No contract-specific codes. Use the shared error map in FE-CORE-01. | L12: ☐ Each of the five branches is covered by a routing test. ☐ No product, cart or catalog route exists in the router table. | M12: Nothing beyond the product scope on the parent epic. | N12: 3 | O12: Highest | P12: Week A | Q12: SP-01 | R12: FE-CORE-01, FE-CORE-02, FE-CORE-03, FE-CORE-04, FE-CORE-05 | S12: L1, retailer, routing
A13: RT-02 | B13: Retailer app | C13: Mobile | D13: Story | E13: Phone screen and Syrian number field | F13: EP-RT-A | G13: apps/retailer | H13: FE-RT-PHONE | I13: — | J13: 1. A single phone field accepting 09XXXXXXXX and +9639XXXXXXXX. 2. The value is sent exactly as typed; the server performs normalisation. 3. One primary action: send code. | K13: No contract-specific codes. Use the shared error map in FE-CORE-01. | L13: ☐ No client-side normalisation is applied to the number. ☐ The button stays disabled until the field reaches its minimum length. | M13: Nothing beyond the product scope on the parent epic. | N13: 2 | O13: Highest | P13: Week B | Q13: SP-01 | R13: RT-01 | S13: L1, retailer, auth
... A120: AD-78 | B120: Platform admin | C120: Platform Dashboard | D120: Story | E120: Channel join applications | F120: EP-AD-CH | G120: apps/platform-web | H120: FE-AD-CH-APPS | I120: GET /platform/channel-applications?filter[status]=under_review | J120: 1. List applications filtered on under_review. 2. Decide approve or reject with a reason; approval also carries plan_id and trial_days. 3. Approval produces a channel in provisioning. | K120: No contract-specific codes. Use the shared error map in FE-CORE-01. | L120: ☐ An approved application hands off to the AD-65 provisioning path. ☐ Rejection requires a written reason. | M120: Nothing beyond the product scope on the parent epic. | N120: 3 | O120: High | P120: Week E | Q120: SP-04 | R120: AD-02, AD-65 | S120: L1, platform, channels, applications

Sheet Delivery Plan
A1: Delivery plan — every figure is a live formula over the Backlog sheet
A2: Sprint assignment reflects the sequencing constraints on the Epics sheet, not team capacity. Rebalance after your first planning session; the constraints are the part that must not move.
A4: Story points by week and team
B5: Platform Engineering | C5: Mobile | D5: Ops Web | E5: Platform Dashboard | F5: Total
A6: Week A | B6: =SUMIFS(Backlog!$N$2:$N$120,Backlog!$P$2:$P$120,"Week A",Backlog!$C$2:$C$120,"Platform Engineering") -> 13 | C6: =SUMIFS(Backlog!$N$2:$N$120,Backlog!$P$2:$P$120,"Week A",Backlog!$C$2:$C$120,"Mobile") -> 3 | D6: =SUMIFS(Backlog!$N$2:$N$120,Backlog!$P$2:$P$120,"Week A",Backlog!$C$2:$C$120,"Ops Web") -> 5 | E6: =SUMIFS(Backlog!$N$2:$N$120,Backlog!$P$2:$P$120,"Week A",Backlog!$C$2:$C$120,"Platform Dashboard") -> 3 | F6: =SUM(B6:E6) -> 24
A7: Week B | B7: =SUMIFS(Backlog!$N$2:$N$120,Backlog!$P$2:$P$120,"Week B",Backlog!$C$2:$C$120,"Platform Engineering") -> 23 | C7: =SUMIFS(Backlog!$N$2:$N$120,Backlog!$P$2:$P$120,"Week B",Backlog!$C$2:$C$120,"Mobile") -> 15 | D7: =SUMIFS(Backlog!$N$2:$N$120,Backlog!$P$2:$P$120,"Week B",Backlog!$C$2:$C$120,"Ops Web") -> 16 | E7: =SUMIFS(Backlog!$N$2:$N$120,Backlog!$P$2:$P$120,"Week B",Backlog!$C$2:$C$120,"Platform Dashboard") -> 21 | F7: =SUM(B7:E7) -> 75
A8: Week C | B8: =SUMIFS(Backlog!$N$2:$N$120,Backlog!$P$2:$P$120,"Week C",Backlog!$C$2:$C$120,"Platform Engineering") -> 0 | C8: =SUMIFS(Backlog!$N$2:$N$120,Backlog!$P$2:$P$120,"Week C",Backlog!$C$2:$C$120,"Mobile") -> 20 | D8: =SUMIFS(Backlog!$N$2:$N$120,Backlog!$P$2:$P$120,"Week C",Backlog!$C$2:$C$120,"Ops Web") -> 10 | E8: =SUMIFS(Backlog!$N$2:$N$120,Backlog!$P$2:$P$120,"Week C",Backlog!$C$2:$C$120,"Platform Dashboard") -> 45 | F8: =SUM(B8:E8) -> 75
A9: Week D | B9: =SUMIFS(Backlog!$N$2:$N$120,Backlog!$P$2:$P$120,"Week D",Backlog!$C$2:$C$120,"Platform Engineering") -> 0 | C9: =SUMIFS(Backlog!$N$2:$N$120,Backlog!$P$2:$P$120,"Week D",Backlog!$C$2:$C$120,"Mobile") -> 15 | D9: =SUMIFS(Backlog!$N$2:$N$120,Backlog!$P$2:$P$120,"Week D",Backlog!$C$2:$C$120,"Ops Web") -> 0 | E9: =SUMIFS(Backlog!$N$2:$N$120,Backlog!$P$2:$P$120,"Week D",Backlog!$C$2:$C$120,"Platform Dashboard") -> 55 | F9: =SUM(B9:E9) -> 70
A10: Week E | B10: =SUMIFS(Backlog!$N$2:$N$120,Backlog!$P$2:$P$120,"Week E",Backlog!$C$2:$C$120,"Platform Engineering") -> 0 | C10: =SUMIFS(Backlog!$N$2:$N$120,Backlog!$P$2:$P$120,"Week E",Backlog!$C$2:$C$120,"Mobile") -> 12 | D10: =SUMIFS(Backlog!$N$2:$N$120,Backlog!$P$2:$P$120,"Week E",Backlog!$C$2:$C$120,"Ops Web") -> 0 | E10: =SUMIFS(Backlog!$N$2:$N$120,Backlog!$P$2:$P$120,"Week E",Backlog!$C$2:$C$120,"Platform Dashboard") -> 62 | F10: =SUM(B10:E10) -> 74
A11: Total | B11: =SUM(B6:B10) -> 36 | C11: =SUM(C6:C10) -> 65 | D11: =SUM(D6:D10) -> 31 | E11: =SUM(E6:E10) -> 186 | F11: =SUM(F6:F10) -> 318
A14: Issue count by week and team
B15: Platform Engineering | C15: Mobile | D15: Ops Web | E15: Platform Dashboard | F15: Total
A16: Week A | B16: =COUNTIFS(Backlog!$P$2:$P$120,"Week A",Backlog!$C$2:$C$120,"Platform Engineering") -> 3 | C16: =COUNTIFS(Backlog!$P$2:$P$120,"Week A",Backlog!$C$2:$C$120,"Mobile") -> 1 | D16: =COUNTIFS(Backlog!$P$2:$P$120,"Week A",Backlog!$C$2:$C$120,"Ops Web") -> 2 | E16: =COUNTIFS(Backlog!$P$2:$P$120,"Week A",Backlog!$C$2:$C$120,"Platform Dashboard") -> 1 | F16: =SUM(B16:E16) -> 7
A17: Week B | B17: =COUNTIFS(Backlog!$P$2:$P$120,"Week B",Backlog!$C$2:$C$120,"Platform Engineering") -> 7 | C17: =COUNTIFS(Backlog!$P$2:$P$120,"Week B",Backlog!$C$2:$C$120,"Mobile") -> 6 | D17: =COUNTIFS(Backlog!$P$2:$P$120,"Week B",Backlog!$C$2:$C$120,"Ops Web") -> 8 | E17: =COUNTIFS(Backlog!$P$2:$P$120,"Week B",Backlog!$C$2:$C$120,"Platform Dashboard") -> 7 | F17: =SUM(B17:E17) -> 28
A18: Week C | B18: =COUNTIFS(Backlog!$P$2:$P$120,"Week C",Backlog!$C$2:$C$120,"Platform Engineering") -> 0 | C18: =COUNTIFS(Backlog!$P$2:$P$120,"Week C",Backlog!$C$2:$C$120,"Mobile") -> 11 | D18: =COUNTIFS(Backlog!$P$2:$P$120,"Week C",Backlog!$C$2:$C$120,"Ops Web") -> 7 | E18: =COUNTIFS(Backlog!$P$2:$P$120,"Week C",Backlog!$C$2:$C$120,"Platform Dashboard") -> 17 | F18: =SUM(B18:E18) -> 35
A19: Week D | B19: =COUNTIFS(Backlog!$P$2:$P$120,"Week D",Backlog!$C$2:$C$120,"Platform Engineering") -> 0 | C19: =COUNTIFS(Backlog!$P$2:$P$120,"Week D",Backlog!$C$2:$C$120,"Mobile") -> 5 | D19: =COUNTIFS(Backlog!$P$2:$P$120,"Week D",Backlog!$C$2:$C$120,"Ops Web") -> 0 | E19: =COUNTIFS(Backlog!$P$2:$P$120,"Week D",Backlog!$C$2:$C$120,"Platform Dashboard") -> 18 | F19: =SUM(B19:E19) -> 23
A20: Week E | B20: =COUNTIFS(Backlog!$P$2:$P$120,"Week E",Backlog!$C$2:$C$120,"Platform Engineering") -> 0 | C20: =COUNTIFS(Backlog!$P$2:$P$120,"Week E",Backlog!$C$2:$C$120,"Mobile") -> 5 | D20: =COUNTIFS(Backlog!$P$2:$P$120,"Week E",Backlog!$C$2:$C$120,"Ops Web") -> 0 | E20: =COUNTIFS(Backlog!$P$2:$P$120,"Week E",Backlog!$C$2:$C$120,"Platform Dashboard") -> 21 | F20: =SUM(B20:E20) -> 26
A21: Total | B21: =SUM(B16:B20) -> 10 | C21: =SUM(C16:C20) -> 28 | D21: =SUM(D16:D20) -> 17 | E21: =SUM(E16:E20) -> 64 | F21: =SUM(F16:F20) -> 119
A24: Story points by backend gate and team
B25: Platform Engineering | C25: Mobile | D25: Ops Web | E25: Platform Dashboard | F25: Total
A26: SP-00 | B26: =SUMIFS(Backlog!$N$2:$N$120,Backlog!$Q$2:$Q$120,"SP-00",Backlog!$C$2:$C$120,"Platform Engineering") -> 36 | C26: =SUMIFS(Backlog!$N$2:$N$120,Backlog!$Q$2:$Q$120,"SP-00",Backlog!$C$2:$C$120,"Mobile") -> 0 | D26: =SUMIFS(Backlog!$N$2:$N$120,Backlog!$Q$2:$Q$120,"SP-00",Backlog!$C$2:$C$120,"Ops Web") -> 0 | E26: =SUMIFS(Backlog!$N$2:$N$120,Backlog!$Q$2:$Q$120,"SP-00",Backlog!$C$2:$C$120,"Platform Dashboard") -> 0 | F26: =SUM(B26:E26) -> 36
A27: SP-01 | B27: =SUMIFS(Backlog!$N$2:$N$120,Backlog!$Q$2:$Q$120,"SP-01",Backlog!$C$2:$C$120,"Platform Engineering") -> 0 | C27: =SUMIFS(Backlog!$N$2:$N$120,Backlog!$Q$2:$Q$120,"SP-01",Backlog!$C$2:$C$120,"Mobile") -> 43 | D27: =SUMIFS(Backlog!$N$2:$N$120,Backlog!$Q$2:$Q$120,"SP-01",Backlog!$C$2:$C$120,"Ops Web") -> 31 | E27: =SUMIFS(Backlog!$N$2:$N$120,Backlog!$Q$2:$Q$120,"SP-01",Backlog!$C$2:$C$120,"Platform Dashboard") -> 49 | F27: =SUM(B27:E27) -> 123
A28: SP-02 | B28: =SUMIFS(Backlog!$N$2:$N$120,Backlog!$Q$2:$Q$120,"SP-02",Backlog!$C$2:$C$120,"Platform Engineering") -> 0 | C28: =SUMIFS(Backlog!$N$2:$N$120,Backlog!$Q$2:$Q$120,"SP-02",Backlog!$C$2:$C$120,"Mobile") -> 0 | D28: =SUMIFS(Backlog!$N$2:$N$120,Backlog!$Q$2:$Q$120,"SP-02",Backlog!$C$2:$C$120,"Ops Web") -> 0 | E28: =SUMIFS(Backlog!$N$2:$N$120,Backlog!$Q$2:$Q$120,"SP-02",Backlog!$C$2:$C$120,"Platform Dashboard") -> 42 | F28: =SUM(B28:E28) -> 42
A29: SP-03 | B29: =SUMIFS(Backlog!$N$2:$N$120,Backlog!$Q$2:$Q$120,"SP-03",Backlog!$C$2:$C$120,"Platform Engineering") -> 0 | C29: =SUMIFS(Backlog!$N$2:$N$120,Backlog!$Q$2:$Q$120,"SP-03",Backlog!$C$2:$C$120,"Mobile") -> 13 | D29: =SUMIFS(Backlog!$N$2:$N$120,Backlog!$Q$2:$Q$120,"SP-03",Backlog!$C$2:$C$120,"Ops Web") -> 0 | E29: =SUMIFS(Backlog!$N$2:$N$120,Backlog!$Q$2:$Q$120,"SP-03",Backlog!$C$2:$C$120,"Platform Dashboard") -> 33 | F29: =SUM(B29:E29) -> 46
A30: SP-04 | B30: =SUMIFS(Backlog!$N$2:$N$120,Backlog!$Q$2:$Q$120,"SP-04",Backlog!$C$2:$C$120,"Platform Engineering") -> 0 | C30: =SUMIFS(Backlog!$N$2:$N$120,Backlog!$Q$2:$Q$120,"SP-04",Backlog!$C$2:$C$120,"Mobile") -> 9 | D30: =SUMIFS(Backlog!$N$2:$N$120,Backlog!$Q$2:$Q$120,"SP-04",Backlog!$C$2:$C$120,"Ops Web") -> 0 | E30: =SUMIFS(Backlog!$N$2:$N$120,Backlog!$Q$2:$Q$120,"SP-04",Backlog!$C$2:$C$120,"Platform Dashboard") -> 62 | F30: =SUM(B30:E30) -> 71
A31: Total | B31: =SUM(B26:B30) -> 36 | C31: =SUM(C26:C30) -> 65 | D31: =SUM(D26:D30) -> 31 | E31: =SUM(E26:E30) -> 186 | F31: =SUM(F26:F30) -> 318
A34: Reading the plan
A35: • | B35: Platform Dashboard carries roughly 57% of the layer. Moving an engineer off it to Mobile does not help: Mobile is constrained by backend availability (SP-01, SP-03, SP-04), not by headcount.
A36: • | B36: The backend-gate grid tells you what is buildable today. Anything gated on a sprint that has not shipped cannot be pulled, whatever the sprint column says.
A37: • | B37: Week C is the heaviest week by design: it absorbs the shared-kit hand-off plus the whole of IAM.

Sheet Dependencies
A1: Blocker key | B1: Blocker title | C1: Blocker product | D1: Blocker sprint | E1: Blocked key | F1: Blocked title | G1: Blocked product | H1: Blocked sprint | I1: Cross-product
A2: AD-00 | B2: Project scaffold and route guards | C2: Platform admin | D2: Week A | E2: AD-01 | F2: Shell and permission-gated navigation | G2: Platform admin | H2: Week B | I2: No
A3: AD-00 | B3: Project scaffold and route guards | C3: Platform admin | D3: Week A | E3: AD-10 | F3: Login screen | G3: Platform admin | H3: Week B | I3: No
A4: AD-02 | B4: Generic table component | C4: Platform admin | D4: Week B | E4: AD-06 | F4: Background job handler | G4: Platform admin | H4: Week C | I4: No
A5: AD-02 | B5: Generic table component | C5: Platform admin | D5: Week B | E5: AD-07 | F5: Export with active filters | G5: Platform admin | H5: Week C | I5: No
A6: AD-02 | B6: Generic table component | C6: Platform admin | D6: Week B | E6: AD-16 | F6: My account — active sessions | G6: Platform admin | H6: Week C | I6: No
A7: AD-02 | B7: Generic table component | C7: Platform admin | D7: Week B | E7: AD-18 | F7: My account — API tokens | G7: Platform admin | H7: Week C | I7: No
A8: AD-02 | B8: Generic table component | C8: Platform admin | D8: Week B | E8: AD-20 | F8: Permission catalog table | G8: Platform admin | H8: Week C | I8: No
A9: AD-02 | B9: Generic table component | C9: Platform admin | D9: Week B | E9: AD-22 | F9: Roles list | G9: Platform admin | H9: Week C | I9: No
A10: AD-02 | B10: Generic table component | C10: Platform admin | D10: Week B | E10: AD-30 | F10: Segregation of duties rules (read-only) | G10: Platform admin | H10: Week D | I10: No
A11: AD-02 | B11: Generic table component | C11: Platform admin | D11: Week B | E11: AD-32 | F11: Audit log screen | G11: Platform admin | H11: Week D | I11: No
A12: AD-02 | B12: Generic table component | C12: Platform admin | D12: Week B | E12: AD-34 | F12: Quarterly access review | G12: Platform admin | H12: Week D | I12: No
... A192: WH-06 | B192: Kiosk mode and connectivity behaviour | C192: Warehouse web | D192: Week B | E192: WH-07 | F192: Acceptance walkthrough and provisioning runbook | G192: Warehouse web | H192: Week C | I192: No

Sheet API Index
A1: EP-ID / contract | B1: Method and path | C1: Product | D1: Issues | E1: Count
A2: 403 and 401 envelope responses | B2: — | C2: Channel dashboard | D2: CH-08 | E2: 1
A3: Access review campaign routes | B3: — | C3: Platform admin | D3: AD-34 | E3: 1
A4: All authenticated paths | B4: — | C4: Shared API client | D4: FE-CORE-02 | E4: 1
A5: Catalog export routes | B5: — | C5: Platform admin | D5: AD-07 | E5: 1
A6: DELETE /platform/iam/assignments · { user_id, role_id, reason } | B6: DELETE /platform/iam/assignments | C6: Platform admin | D6: AD-27 | E6: 1
A7: EP-AD-001 | B7: POST /platform/auth/login | C7: Platform admin | D7: AD-10 | E7: 1
A8: EP-AD-002 | B8: POST /platform/auth/2fa/verify | C8: Platform admin | D8: AD-11 | E8: 1
A9: EP-AD-003 | B9: POST /platform/auth/logout | C9: Platform admin | D9: AD-13 | E9: 1
A10: EP-AD-004 · EP-AD-159A | B10: GET /platform/auth/me · GET /platform/me | C10: Platform admin | D10: AD-12 | E10: 1
A11: EP-AD-005 | B11: POST /platform/auth/confirm-password | C11: Platform admin | D11: AD-03 | E11: 1
A12: EP-AD-006 | B12: GET /platform/auth/sessions | C12: Platform admin | D12: AD-16 | E12: 1
A13: EP-AD-030 | B13: — | C13: Platform admin | D13: AD-41 | E13: 1
... A99: — | B99: — | C99: Warehouse web | D99: WH-02, WH-04, WH-05, WH-06, WH-07 | E99: 5

Sheet Screens
A1: Screen ID | B1: Product | C1: Epic | D1: Issues that build it | E1: Count | F1: Titles
A2: FE-AD-2FA | B2: Platform admin | C2: EP-AD-ACC | D2: AD-11 | E2: 1 | F2: • AD-11 — TOTP challenge
A3: FE-AD-AUDIT | B3: Platform admin | C3: EP-AD-IAM | D3: AD-32, AD-33 | E3: 2 | F3: • AD-32 — Audit log screen • AD-33 — Audit export
A4: FE-AD-BOOT | B4: Platform admin | C4: EP-AD-ACC | D4: AD-12, AD-13 | E4: 2 | F4: • AD-12 — Boot and admin identity fetch • AD-13 — Logout and storage clear
A5: FE-AD-CH-APPS | B5: Platform admin | C5: EP-AD-CH | D5: AD-78 | E5: 1 | F5: • AD-78 — Channel join applications
A6: FE-AD-CH-CARD | B6: Platform admin | C6: EP-AD-CH | D6: AD-66, AD-67, AD-68, AD-69, AD-70, AD-71, AD-72, AD-73, AD-74, AD-75, AD-76, AD-77 | E6: 12 | F6: • AD-66 — Channel card shell and tabs • AD-67 — Card — overview tab and edit • AD-68 — Card — users tab (read only) • AD-69 — Card — manager tab and invite reset (crit) • AD-70 — Card — coverage tab and overlap warning • AD-71 — Card — warehouses tab (read only) • AD-72 — Card — features tab and plan precedence • AD-73 — Card — usage tab • AD-74 — Card — limits tab and temporary override • AD-75 — Card — status tab driven by allowed_next • AD-76 — Card — export tab • AD-77 — Card — multi-barrier channel deletion
A7: FE-AD-CH-CREATE | B7: Platform admin | C7: EP-AD-CH | D7: AD-64a, AD-64b, AD-64c, AD-65 | E7: 4 | F7: • AD-64a — Create channel — legal identity and documents • AD-64b — Create channel — coverage, subscription and limits • AD-64c — Create channel — manager, invite and submit • AD-65 — Provisioning poll and retry
A8: FE-AD-CH-LIST | B8: Platform admin | C8: EP-AD-CH | D8: AD-60, AD-61, AD-62, AD-63 | E8: 4 | F8: • AD-60 — Channels list • AD-61 — Channels list export • AD-62 — Bulk notify channel managers • AD-63 — Plan change with preview
A9: FE-AD-IAM-ASSIGN | B9: Platform admin | C9: EP-AD-IAM | D9: AD-26, AD-27 | E9: 2 | F9: • AD-26 — Bulk role assignment • AD-27 — Revoke assignment
A10: FE-AD-IAM-INBOX | B10: Platform admin | C10: EP-AD-IAM | D10: AD-31 | E10: 1 | F10: • AD-31 — Dual-approval inbox and decisions
A11: FE-AD-IAM-PERMS | B11: Platform admin | C11: EP-AD-IAM | D11: AD-20, AD-21 | E11: 2 | F11: • AD-20 — Permission catalog table • AD-21 — Permission holders panel
A12: FE-AD-IAM-REVIEW | B12: Platform admin | C12: EP-AD-IAM | D12: AD-34 | E12: 1 | F12: • AD-34 — Quarterly access review
A13: FE-AD-IAM-ROLES | B13: Platform admin | C13: EP-AD-IAM | D13: AD-22, AD-23, AD-24, AD-25 | E13: 4 | F13: • AD-22 — Roles list • AD-23 — Create role with mandatory preview • AD-24 — Approve role by a second user • AD-25 — Replace role permissions
... A42: FE-WH-PIN | B42: Warehouse web | C42: EP-WH-B | D42: WH-06 | E42: 1 | F42: • WH-06 — Kiosk mode and connectivity behaviour

Sheet Error Map
A1: error.code | B1: Client behaviour | C1: Enforced in | D1: Most affected issues
A2: validation_failed | B2: Inline field errors (HTTP 422) mapped from error.details.{field}. | C2: FE-CORE-01 | D2: Every form issue: RT-03, RT-08, RT-10, RP-06, RP-07, AD-14, AD-67
A3: rate_limited | B3: Disable submit; honour resend_after / Retry-After and run the countdown. | C3: FE-CORE-01 | D3: RT-03, RT-04, RT-05, CH-02
A4: unauthenticated | B4: Drop the token and route to login. | C4: FE-CORE-01 | D4: RT-13, CH-08, AD-12
A5: token_revoked | B5: Same as unauthenticated. | C5: FE-CORE-01 | D5: RT-13, CH-08, AD-12
A6: otp_invalid | B6: Clear the OTP boxes. Do NOT auto-request a new OTP. | C6: FE-CORE-01 | D6: RT-06, RP-03, CH-03, AD-11
A7: insufficient_permission | B7: Toast, and hide the action so it cannot be retried. | C7: FE-CORE-01 | D7: AD-01, CH-05
A8: requires_password_confirm | B8: Platform only: open the password modal, then replay the original request with the same idempotency key. | C8: AD-03 | D8: AD-15, AD-69, AD-76, AD-77
A9: sod_violation | B9: Explain the conflict in plain language. Do not resubmit blindly. | C9: FE-CORE-01 | D9: AD-23, AD-26
A10: conflict | B10: Stop the operation and show the server message verbatim. | C10: FE-CORE-01 | D10: RP-07, AD-44, AD-45
A11: illegal_transition | B11: Stop the operation and show the server message verbatim. | C11: FE-CORE-01 | D11: AD-75
A12: idempotency_key_conflict | B12: Stop the operation and show the server message verbatim. | C12: FE-CORE-03 | D12: RT-10, RP-07, AD-64c
... A14: operation_in_progress | B14: Wait, then retry with the SAME key. | C14: FE-CORE-03 | D14: AD-65, RT-10

Sheet Header Policy
A1: Rule | B1: When | C1: Value or behaviour | D1: Owning issue
A2: Accept | B2: Always | C2: application/json | D2: FE-CORE-02
A3: Accept-Language | B3: Always | C3: ar by default, en when the user switches. | D3: FE-CORE-02
A4: X-Client | B4: Always | C4: retailer-android · retailer-ios · rep-android · rep-ios · channel-web · warehouse-web · platform-web | D4: FE-CORE-02
A5: X-App-Version | B5: Always | C5: Semver of the binary, taken from the build. | D5: FE-CORE-02
A6: X-Device-Id | B6: Mobile and warehouse | C6: Stable UUID generated once per install and never changed. | D6: FE-CORE-02
A7: Authorization | B7: After login | C7: Bearer {token} from the secure store. | D7: FE-CORE-02
A8: X-Channel-Id | B8: Channel dashboard | C8: Required when the user belongs to more than one channel; pinned by the picker. | D8: CH-04
A9: X-Idempotency-Key | B9: Every POST PUT PATCH DELETE | C9: UUID per user intent (confirm tap). Network retry reuses the SAME key; a new tap generates a new key. | D9: FE-CORE-03
A10: Exempt from Bearer | B10: Two paths | C10: GET /health and GET /public/refs. | D10: FE-CORE-02
A11: Exempt from idempotency | B11: Auth paths | C11: Public OTP request / verify / resend, platform login and 2FA, channel OTP, warehouse device-login. | D11: FE-CORE-03
A12: Forbidden paths | B12: Always | C12: /api/v1/auth/* and /admin/channels. Blocked at the client layer, not merely avoided. | D12: FE-CORE-02
... A16: baseURL | B16: Always | C16: /api/v1 | D16: FE-CORE-01

Sheet Risks
A1: # | B1: Risk | C1: Likelihood | D1: Impact | E1: Mitigation | F1: Owning issue
A2: 1 | B2: Scope creep: Layer 2 screens built with sales mock data "until the API is ready". | C2: High | D2: Rework, and fabricated figures reaching a demo. | E2: Automated path allowlist plus a network siege test on every product journey. | F2: FE-CORE-10, CH-09
A3: 2 | B3: The shared kit is copied into product repos instead of upgraded as a package. | C3: High | D3: Error handling diverges between the five products. | E3: Governance rule: kit changes only via a PR on the package. Contract tests run in CI. | F3: FE-CORE-13, FE-CORE-14
A4: 3 | B4: AD-40 is skipped and seven reference screens are built by hand. | C4: Medium | D4: Roughly +20 points and seven copies of the reason and impact logic. | E4: Hard sequencing rule: the factory precedes every reference entity. | F4: AD-40
A5: 4 | B5: Channel provisioning treated as a synchronous request. | C5: Medium | D5: Frozen UI and duplicate channel creation. | E5: Poll the card until a terminal state; retry endpoint is idempotent. | F5: AD-65, FE-CORE-03
A6: 5 | B6: "Deleted" shown before the second approver acts. | C6: Medium | D6: Operational trust lost and wrong follow-up decisions. | E6: Central dual-approval handler intercepts every pending response. | F6: AD-05, AD-77
A7: 6 | B7: Zone status route drifts from 034 to the 043 family. | C7: Medium | D7: Silent 404 or 405 in production. | E7: Contract test pinned to route 034 for zones. | F7: AD-42, FE-CORE-14
A8: 7 | B8: purpose sent to the channel OTP request. | C8: Medium | D8: Unexplained 422 in front of the user. | E8: Catalog-generated contract test on the request body. | F8: CH-02, FE-CORE-14
A9: 8 | B9: float used for a limit or an FX rate. | C9: Low | D9: Monetary discrepancies that cannot be reconciled. | E9: Integer-only money layer plus a type check in CI. | F9: FE-CORE-11, AD-48, AD-64b
A10: 9 | B10: Warehouse device_token exposed in the production UI. | C10: Low | D10: Physical access vulnerability on a shared terminal. | E10: Token read from installed config only, never rendered or logged. | F10: WH-01
A11: 10 | B11: challenge_token persisted in localStorage. | C11: Low | D11: 2FA bypass. | E11: Screen-memory-only storage; page reload returns to login. | F11: AD-11

Sheet Jira Import
A1: Issue ID | B1: Issue Key | C1: Issue Type | D1: Summary | E1: Description | F1: Component/s | G1: Priority | H1: Story Points | I1: Epic Name | J1: Epic Link | K1: Sprint | L1: Fix Version/s | M1: Backend Gate | N1: Labels | O1: Blocked By
A2: 1 | B2: EP-CORE-NET | C2: Epic | D2: EP-CORE-NET — Transport and errors | E2: *Product:* Shared API client *Covers:* Envelope client, error map, idempotency *Volume:* 2 issues / 10 points | F2: api-client | G2: High | I2: EP-CORE-NET | L2: Layer 1 | M2: SP-00 (GET /health, EP-CORE-001) · SP-01 (token guards) | N2: L1 epic
A3: 2 | B3: EP-CORE-SEC | C3: Epic | D3: EP-CORE-SEC — Identity and permissions | E3: *Product:* Shared API client *Covers:* Headers, token store, can() *Volume:* 2 issues / 8 points | F3: api-client | G3: High | I3: EP-CORE-SEC | L3: Layer 1 | M3: SP-00 (GET /health, EP-CORE-001) · SP-01 (token guards) | N3: L1 epic
A4: 3 | B4: EP-CORE-PLT | C4: Epic | D4: EP-CORE-PLT — Platform and guardrails | E4: *Product:* Shared API client *Covers:* Refs cache, i18n, money, CI, allowlist, contract tests *Volume:* 6 issues / 18 points | F4: api-client | G4: High | I4: EP-CORE-PLT | L4: Layer 1 | M4: SP-00 (GET /health, EP-CORE-001) · SP-01 (token guards) | N4: L1 epic
A5: 4 | B5: FE-CORE-01 | C5: Task | D5: FE-CORE-01 — Envelope client and error map | E5: *API contract:* GET /api/v1/health (EP-CORE-001) · error contract e in the catalog h3. Requirements # baseURL is fixed to /api/v1 with per-environment host configuration. # On success, expose data to the UI only; retain meta.server_time for clock-skew correction. # On failure, surface error.message. A raw Laravel validation JSON must never reach a component. # Implement one central map from error.code to client behaviour covering all twelve codes in the shared kit. # Timeouts, GET-only automatic retry, and request cancellation on screen exit. h3. Error handling * validation_failed → inline field errors (422); rate_limited → disable submit, honour resend_after / Retry-After. * unauthenticated and token_revoked → drop token, route to login. * otp_invalid → clear the OTP boxes, never auto-request a new OTP. * insufficient_permission → toast and hide the action; requires_password_confirm → platform password modal then replay. * sod_violation → explain the conflict, do not resubmit blindly. * conflict / illegal_transition / idempotency_key_conflict → stop and show the server message. * idempotency_key_required → treat as a client bug: log it and fail the production build. * operation_in_progress → wait, then retry with the same key. h3. Acceptance criteria * (/) GET /health returns data.status = ok through the client. * (/) No envelope field (meta, success) reaches a UI component. * (/) A unit test exists for each of the twelve error codes. * (/) Automatic retry never applies to POST, PUT, PATCH or DELETE. h3. Out of scope * Toast and modal presentation components — those live in FE-CORE-12. h3. Definition of done * (/) Runs against real staging — no mock data in the merged branch. * (/) HTTP 422 paints the named fields from error.details.{field}, never a generic banner. * (/) Every write carries X-Idempotency-Key tied to the confirm tap; a network retry reuses the same key. * (/) Permissions drive visibility: a control the user cannot use is absent or disabled. * (/) Loading, empty, error and offline states are all implemented. * (/) RTL layout is correct and every amount, limit and FX rate is an integer. * (/) No request is made to any path outside the L1 allowlist (enforced by FE-CORE-10). * (/) The PR contains a screenshot or GIF of the journey and names the EP-ID used. * (/) Zero console errors and zero new lint warnings. | F5: api-client | G5: Highest | H5: 5 | J5: EP-CORE-NET | K5: L1 — Week A | L5: Layer 1 | M5: SP-00 | N5: L1, core, http, errors
A6: 5 | B6: FE-CORE-02 | C6: Task | D6: FE-CORE-02 — Header injection and secure token store | E6: *API contract:* All authenticated paths h3. Requirements # Inject Accept, Accept-Language, X-Client, X-App-Version on every request. # Inject X-Device-Id on mobile and warehouse surfaces: a stable UUID generated once per install. # Inject Authorization: Bearer {token} after login, and X-Channel-Id on the channel dashboard when the user belongs to more than one channel. # Store the token in Keychain / Keystore on mobile and in restricted storage on web. # Exempt from Bearer: GET /health and GET /public/refs. # Block the forbidden paths /api/v1/auth/* and /admin/channels at the client layer. h3. Acceptance criteria * (/) After logout no Bearer appears on any subsequent request. * (/) X-Device-Id is stable across application restarts and reinstall where the platform allows it. * (/) A call to a forbidden path throws at development time rather than reaching the network. h3. Definition of done * (/) Runs against real staging — no mock data in the merged branch. * (/) HTTP 422 paints the named fields from error.details.{field}, never a generic banner. * (/) Every write carries X-Idempotency-Key tied to the confirm tap; a network retry reuses the same key. * (/) Permissions drive visibility: a control the user cannot use is absent or disabled. * (/) Loading, empty, error and offline states are all implemented. * (/) RTL layout is correct and every amount, limit and FX rate is an integer. * (/) No request is made to any path outside the L1 allowlist (enforced by FE-CORE-10). * (/) The PR contains a screenshot or GIF of the journey and names the EP-ID used. * (/) Zero console errors and zero new lint warnings. | F6: api-client | G6: Highest | H6: 5 | J6: EP-CORE-SEC | K6: L1 — Week A | L6: Layer 1 | M6: SP-00 | N6: L1, core, auth, headers | O6: FE-CORE-01
A7: 6 | B7: FE-CORE-03 | C7: Task | D7: FE-CORE-03 — Idempotency store tied to confirm buttons | E7: *API contract:* X-Idempotency-Key on POST / PUT / PATCH / DELETE h3. Requirements # One UUID per user intent (confirm tap), not per network request. # A retry after a dropped connection reuses the same key; a new confirm tap generates a new key. # Expose a small API, for example withIdempotency(intentId), that wraps the call. # Apply the shared-kit exemption list: public OTP request / verify / resend, platform login and 2FA, channel OTP, and warehouse device-login do not carry a key. # A write outside the exemption list must never leave the client without a key. h3. Acceptance criteria * (/) A dropped connection followed by a retry does not create a duplicate write when the key is reused. * (/) A second confirm tap produces a different UUID, observable in the request log. * (/) operation_in_progress retries with the same key after a short backoff. * (/) A non-exempt write attempted without a key fails loudly in development. h3. Definition of done * (/) Runs against real staging — no mock data in the merged branch. * (/) HTTP 422 paints the named fields from error.details.{field}, never a generic banner. * (/) Every write carries X-Idempotency-Key tied to the confirm tap; a network retry reuses the same key. * (/) Permissions drive visibility: a control the user cannot use is absent or disabled. * (/) Loading, empty, error and offline states are all implemented. * (/) RTL layout is correct and every amount, limit and FX rate is an integer. * (/) No request is made to any path outside the L1 allowlist (enforced by FE-CORE-10). * (/) The PR contains a screenshot or GIF of the journey and names the EP-ID used. * (/) Zero console errors and zero new lint warnings. | F7: api-client | G7: Highest | H7: 5 | J7: EP-CORE-NET | K7: L1 — Week B | L7: Layer 1 | M7: SP-00 | N7: L1, core, idempotency | O7: FE-CORE-01
A8: 7 | B8: FE-CORE-04 | C8: Task | D8: FE-CORE-04 — can(code) permission layer | E8: *API contract:* permissions[] from session and login responses h3. Requirements # can(code) derived from the permissions[] persisted after sign-in. # Provide a <Can> wrapper component and a withPermission route guard. # Permissions refresh on session boot and on channel switch. h3. Acceptance criteria * (/) A control the user lacks permission for is absent from the tree or rendered disabled with a tooltip. * (/) A guarded route does not build its network call before the check runs. h3. Definition of done * (/) Runs against real staging — no mock data in the merged branch. * (/) HTTP 422 paints the named fields from error.details.{field}, never a generic banner. * (/) Every write carries X-Idempotency-Key tied to the confirm tap; a network retry reuses the same key. * (/) Permissions drive visibility: a control the user cannot use is absent or disabled. * (/) Loading, empty, error and offline states are all implemented. * (/) RTL layout is correct and every amount, limit and FX rate is an integer. * (/) No request is made to any path outside the L1 allowlist (enforced by FE-CORE-10). * (/) The PR contains a screenshot or GIF of the journey and names the EP-ID used. * (/) Zero console errors and zero new lint warnings. | F8: api-client | G8: Highest | H8: 3 | J8: EP-CORE-SEC | K8: L1 — Week B | L8: Layer 1 | M8: SP-00 | N8: L1, core, iam | O8: FE-CORE-02
A9: 8 | B9: FE-CORE-05 | C9: Task | D9: FE-CORE-05 — Public refs cache keyed by sync_cursor | E9: *API contract:* GET /public/refs (EP-PB-001) h3. Requirements # Cache the response under its sync_cursor and send since= when a cursor exists. # Expose selectors for activity_types, root_categories, equipments, governorates and zones. # Invalidate on logout and on language change. # This path carries neither Bearer nor an idempotency key. h3. Acceptance criteria * (/) Changing the zone list on the server is reflected after a since= call. * (/) Refs are not fully re-downloaded on every cold start. * (/) Selecting a governorate filters zones by zone.governorate_id. h3. Definition of done * (/) Runs against real staging — no mock data in the merged branch. * (/) HTTP 422 paints the named fields from error.details.{field}, never a generic banner. * (/) Every write carries X-Idempotency-Key tied to the confirm tap; a network retry reuses the same key. * (/) Permissions drive visibility: a control the user cannot use is absent or disabled. * (/) Loading, empty, error and offline states are all implemented. * (/) RTL layout is correct and every amount, limit and FX rate is an integer. * (/) No request is made to any path outside the L1 allowlist (enforced by FE-CORE-10). * (/) The PR contains a screenshot or GIF of the journey and names the EP-ID used. * (/) Zero console errors and zero new lint warnings. | F9: api-client | G9: High | H9: 3 | J9: EP-CORE-PLT | K9: L1 — Week B | L9: Layer 1 | M9: SP-00 | N9: L1, core, refs | O9: FE-CORE-01
A10: 9 | B10: FE-CORE-10 | C10: Task | D10: FE-CORE-10 — Path allowlist guardrail | E10: *API contract:* L1 allowlist derived from the catalog h3. Requirements # Maintain an allowlist of the paths permitted in Layer 1. # Fail the test suite on any request outside it, including /api/v1/auth/*, /admin/channels and every path from SP-06 onward. # Print every path exercised during the run in the report. h3. Acceptance criteria * (/) Calling GET /channel/products or GET /warehouse/queues fails the build. * (/) The report lists all paths touched by the journey tests. h3. Definition of done * (/) Runs against real staging — no mock data in the merged branch. * (/) HTTP 422 paints the named fields from error.details.{field}, never a generic banner. * (/) Every write carries X-Idempotency-Key tied to the confirm tap; a network retry reuses the same key. * (/) Permissions drive visibility: a control the user cannot use is absent or disabled. * (/) Loading, empty, error and offline states are all implemented. * (/) RTL layout is correct and every amount, limit and FX rate is an integer. * (/) No request is made to any path outside the L1 allowlist (enforced by FE-CORE-10). * (/) The PR contains a screenshot or GIF of the journey and names the EP-ID used. * (/) Zero console errors and zero new lint warnings. | F10: ci | G10: Highest | H10: 3 | J10: EP-CORE-PLT | K10: L1 — Week B | L10: Layer 1 | M10: SP-00 | N10: L1, core, guardrail, ci | O10: FE-CORE-01
A11: 10 | B11: FE-CORE-11 | C11: Task | D11: FE-CORE-11 — i18n, RTL and integer money formatting | E11: *API contract:* decimals from the currency entity h3. Requirements # Amounts, limits and FX rate are transported and stored as integers exactly as the server sends them. # Display uses the currency decimals value; SYP renders with zero decimal places. # RTL is the default layout with an en switch available. # Accept-Language follows the active locale. h3. Acceptance criteria * (/) A value of 15000 in SYP renders as 15,000 with no fractional part. * (/) A type check proves no float exists on any money path. h3. Definition of done * (/) Runs against real staging — no mock data in the merged branch. * (/) HTTP 422 paints the named fields from error.details.{field}, never a generic banner. * (/) Every write carries X-Idempotency-Key tied to the confirm tap; a network retry reuses the same key. * (/) Permissions drive visibility: a control the user cannot use is absent or disabled. * (/) Loading, empty, error and offline states are all implemented. * (/) RTL layout is correct and every amount, limit and FX rate is an integer. * (/) No request is made to any path outside the L1 allowlist (enforced by FE-CORE-10). * (/) The PR contains a screenshot or GIF of the journey and names the EP-ID used. * (/) Zero console errors and zero new lint warnings. | F11: api-client | G11: High | H11: 3 | J11: EP-CORE-PLT | K11: L1 — Week B | L11: Layer 1 | M11: SP-00 | N11: L1, core, i18n, money
A12: 11 | B12: FE-CORE-12 | C12: Task | D12: FE-CORE-12 — Shared state templates and toast system | E12: *API contract:* — h3. Requirements # Provide Loading, Empty, Error and Offline templates with approved Arabic copy. # Provide a toast system and a base modal consumed by all five products. # The Error template renders envelope errors, not raw exceptions. h3. Acceptance criteria * (/) Every later screen consumes the template instead of writing its own state. * (/) The Offline state appears within two seconds of connection loss. h3. Definition of done * (/) Runs against real staging — no mock data in the merged branch. * (/) HTTP 422 paints the named fields from error.details.{field}, never a generic banner. * (/) Every write carries X-Idempotency-Key tied to the confirm tap; a network retry reuses the same key. * (/) Permissions drive visibility: a control the user cannot use is absent or disabled. * (/) Loading, empty, error and offline states are all implemented. * (/) RTL layout is correct and every amount, limit and FX rate is an integer. * (/) No request is made to any path outside the L1 allowlist (enforced by FE-CORE-10). * (/) The PR contains a screenshot or GIF of the journey and names the EP-ID used. * (/) Zero console errors and zero new lint warnings. | F12: ui-kit | G12: High | H12: 3 | J12: EP-CORE-PLT | K12: L1 — Week B | L12: Layer 1 | M12: SP-00 | N12: L1, core, ui
A13: 12 | B13: FE-CORE-13 | C13: Task | D13: FE-CORE-13 — Repository scaffold and CI pipeline | E13: *API contract:* — h3. Requirements # Strict types, lint, tests and a build target per product. # Publish the package internally under a semantic tag. # Block merges on a red pipeline. h3. Acceptance criteria * (/) A failing PR cannot be merged. * (/) The package is published as v0.1.0 and consumed by at least two repositories. h3. Definition of done * (/) Runs against real staging — no mock data in the merged branch. * (/) HTTP 422 paints the named fields from error.details.{field}, never a generic banner. * (/) Every write carries X-Idempotency-Key tied to the confirm tap; a network retry reuses the same key. * (/) Permissions drive visibility: a control the user cannot use is absent or disabled. * (/) Loading, empty, error and offline states are all implemented. * (/) RTL layout is correct and every amount, limit and FX rate is an integer. * (/) No request is made to any path outside the L1 allowlist (enforced by FE-CORE-10). * (/) The PR contains a screenshot or GIF of the journey and names the EP-ID used. * (/) Zero console errors and zero new lint warnings. | F13: ci | G13: Highest | H13: 3 | J13: EP-CORE-PLT | K13: L1 — Week A | L13: Layer 1 | M13: SP-00 | N13: L1, core, ci
A14: 13 | B14: FE-CORE-14 | C14: Task | D14: FE-CORE-14 — Contract tests generated from the catalog | E14: *API contract:* docs/api/catalog/*.php — field b h3. Requirements # Generate tests that compare the outgoing request body against field b in the catalog. # Cover extra keys, missing keys and wrong types. # Run the suite in CI on every PR. h3. Acceptance criteria * (/) Sending purpose to /channel/auth/request-otp fails the test. * (/) Adding a key absent from b fails the test. h3. Definition of done * (/) Runs against real staging — no mock data in the merged branch. * (/) HTTP 422 paints the named fields from error.details.{field}, never a generic banner. * (/) Every write carries X-Idempotency-Key tied to the confirm tap; a network retry reuses the same key. * (/) Permissions drive visibility: a control the user cannot use is absent or disabled. * (/) Loading, empty, error and offline states are all implemented. * (/) RTL layout is correct and every amount, limit and FX rate is an integer. * (/) No request is made to any path outside the L1 allowlist (enforced by FE-CORE-10). * (/) The PR contains a screenshot or GIF of the journey and names the EP-ID used. * (/) Zero console errors and zero new lint warnings. | F14: ci | G14: High | H14: 3 | J14: EP-CORE-PLT | K14: L1 — Week B | L14: Layer 1 | M14: SP-00 | N14: L1, core, contract-tests | O14: FE-CORE-13
A15: 14 | B15: EP-RT-A | C15: Epic | D15: EP-RT-A — Identity and sign-in | E15: *Product:* Retailer app *Covers:* FE-RT-SPLASH, FE-RT-PHONE, FE-RT-OTP *Volume:* 6 issues / 15 points | F15: apps/retailer | G15: High | I15: EP-RT-A | L15: Layer 1 | M15: SP-01 (OTP + register) · SP-03 (/public/refs for the form) | N15: L1 epic
A16: 15 | B16: EP-RT-B | C16: Epic | D16: EP-RT-B — Shop file | E16: *Product:* Retailer app *Covers:* FE-RT-REGISTER and /public/refs *Volume:* 4 issues / 13 points | F16: apps/retailer | G16: High | I16: EP-RT-B | L16: Layer 1 | M16: SP-01 (OTP + register) · SP-03 (/public/refs for the form) | N16: L1 epic
A17: 16 | B17: EP-RT-C | C17: Epic | D17: EP-RT-C — Lifecycle | E17: *Product:* Retailer app *Covers:* FE-RT-WAIT, FE-RT-SESSION, FE-RT-HOME-EMPTY, FE-RT-LOGOUT *Volume:* 6 issues / 11 points | F17: apps/retailer | G17: High | I17: EP-RT-C | L17: Layer 1 | M17: SP-01 (OTP + register) · SP-03 (/public/refs for the form) | N17: L1 epic
A18: 17 | B18: EP-RT-D | C18: Epic | D18: EP-RT-D — Packaging and acceptance | E18: *Product:* Retailer app *Covers:* Build, distribution, manual walkthrough *Volume:* 2 issues / 5 points | F18: apps/retailer | G18: High | I18: EP-RT-D | L18: Layer 1 | M18: SP-01 (OTP + register) · SP-03 (/public/refs for the form) | N18: L1 epic
A19: 18 | B19: RT-01 | C19: Story | D19: RT-01 — App scaffold and splash routing | E19: *Screen:* FE-RT-SPLASH *API contract:* GET /app/session (EP-CM-004) on cold start when a token exists h3. Requirements # Router exposes exactly six screens: Splash, Phone, OTP, Register, Waiting/Rejected, Empty home. # On cold start with no token, route to Phone. # On cold start with a token, call the session router and branch per §3.6 of the brief. # Five splash branches: no token, registration-ability token, pending_review, rejected, full token with active status. h3. Acceptance criteria * (/) Each of the five branches is covered by a routing test. * (/) No product, cart or catalog route exists in the router table. h3. Definition of done * (/) Runs against real staging — no mock data in the merged branch. * (/) HTTP 422 paints the named fields from error.details.{field}, never a generic banner. * (/) Every write carries X-Idempotency-Key tied to the confirm tap; a network retry reuses the same key. * (/) Permissions drive visibility: a control the user cannot use is absent or disabled. * (/) Loading, empty, error and offline states are all implemented. * (/) RTL layout is correct and every amount, limit and FX rate is an integer. * (/) No request is made to any path outside the L1 allowlist (enforced by FE-CORE-10). * (/) The PR contains a screenshot or GIF of the journey and names the EP-ID used. * (/) Zero console errors and zero new lint warnings. | F19: apps/retailer | G19: Highest | H19: 3 | J19: EP-RT-A | K19: L1 — Week A | L19: Layer 1 | M19: SP-01 | N19: L1, retailer, routing | O19: FE-CORE-01 FE-CORE-02 FE-CORE-03 FE-CORE-04 FE-CORE-05
A20: 19 | B20: RT-02 | C20: Story | D20: RT-02 — Phone screen and Syrian number field | E20: *Screen:* FE-RT-PHONE *API contract:* — h3. Requirements # A single phone field accepting 09XXXXXXXX and +9639XXXXXXXX. # The value is sent exactly as typed; the server performs normalisation. # One primary action: send code. h3. Acceptance criteria * (/) No client-side normalisation is applied to the number. * (/) The button stays disabled until the field reaches its minimum length. h3. Definition of done * (/) Runs against real staging — no mock data in the merged branch. * (/) HTTP 422 paints the named fields from error.details.{field}, never a generic banner. * (/) Every write carries X-Idempotency-Key tied to the confirm tap; a network retry reuses the same key. * (/) Permissions drive visibility: a control the user cannot use is absent or disabled. * (/) Loading, empty, error and offline states are all implemented. * (/) RTL layout is correct and every amount, limit and FX rate is an integer. * (/) No request is made to any path outside the L1 allowlist (enforced by FE-CORE-10). * (/) The PR contains a screenshot or GIF of the journey and names the EP-ID used. * (/) Zero console errors and zero new lint warnings. | F20: apps/retailer | G20: Highest | H20: 2 | J20: EP-RT-A | K20: L1 — Week B | L20: Layer 1 | M20: SP-01 | N20: L1, retailer, auth | O20: RT-01
A21: 20 | B21: RT-03 | C21: Story | D21: RT-03 — Request OTP integration | E21: *Screen:* FE-RT-PHONE *API contract:* POST /public/auth/request-otp · EP-CM-001 h3. Requirements # Body: { phone, purpose, client } with client set to retailer-android or retailer-ios. # purpose is register from a sign-up entry and login from a sign-in entry; a single-screen app sends login and relies on is_new_user. # On 200 store otp_id, expires_in (300), resend_after (60) and channel_used, then route to OTP. # This path is exempt from the idempotency key per the shared kit. h3. Error handling * 422 → errors under the phone field, in Arabic when Accept-Language is ar. * 429 rate_limited → disable the button and start the countdown. h3. Acceptance criteria * (/) A non-Syrian number produces a 422 on the field in Arabic. * (/) A 429 disables the submit button and honours resend_after. h3. Definition of done * (/) Runs against real staging — no mock data in the merged branch. * (/) HTTP 422 paints the named fields from error.details.{field}, never a generic banner. * (/) Every write carries X-Idempotency-Key tied to the confirm tap; a network retry reuses the same key. * (/) Permissions drive visibility: a control the user cannot use is absent or disabled. * (/) Loading, empty, error and offline states are all implemented. * (/) RTL layout is correct and every amount, limit and FX rate is an integer. * (/) No request is made to any path outside the L1 allowlist (enforced by FE-CORE-10). * (/) The PR contains a screenshot or GIF of the journey and names the EP-ID used. * (/) Zero console errors and zero new lint warnings. | F21: apps/retailer | G21: Highest | H21: 2 | J21: EP-RT-A | K21: L1 — Week B | L21: Layer 1 | M21: SP-01 | N21: L1, retailer, otp | O21: RT-02
A22: 21 | B22: RT-04 | C22: Story | D22: RT-04 — OTP screen and resend countdown | E22: *Screen:* FE-RT-OTP *API contract:* — h3. Requirements # Six numeric boxes; a paste longer than six characters is ignored. # Countdown starts from resend_after and reveals the resend action at zero. # The countdown survives backgrounding and does not reset on re-render. h3. Acceptance criteria * (/) Backgrounding and returning resumes the countdown at the correct value. * (/) The resend action is unavailable until the countdown reaches zero. h3. Definition of done * (/) Runs against real staging — no mock data in the merged branch. * (/) HTTP 422 paints the named fields from error.details.{field}, never a generic banner. * (/) Every write carries X-Idempotency-Key tied to the confirm tap; a network retry reuses the same key. * (/) Permissions drive visibility: a control the user cannot use is absent or disabled. * (/) Loading, empty, error and offline states are all implemented. * (/) RTL layout is correct and every amount, limit and FX rate is an integer. * (/) No request is made to any path outside the L1 allowlist (enforced by FE-CORE-10). * (/) The PR contains a screenshot or GIF of the journey and names the EP-ID used. * (/) Zero console errors and zero new lint warnings. | F22: apps/retailer | G22: Highest | H22: 3 | J22: EP-RT-A | K22: L1 — Week B | L22: Layer 1 | M22: SP-01 | N22: L1, retailer, otp | O22: RT-03
A23: 22 | B23: RT-05 | C23: Story | D23: RT-05 — Resend OTP and channel preference | E23: *Screen:* FE-RT-OTP *API contract:* POST /public/auth/resend-otp · EP-CM-003 h3. Requirements # Body: { otp_id, prefer_channel } with whatsapp as the default. # The user may switch to sms; the choice is explicit, never automatic. h3. Acceptance criteria * (/) No automatic resend occurs under any condition. * (/) Switching to sms is reflected in the request body. h3. Definition of done * (/) Runs against real staging — no mock data in the merged branch. * (/) HTTP 422 paints the named fields from error.details.{field}, never a generic banner. * (/) Every write carries X-Idempotency-Key tied to the confirm tap; a network retry reuses the same key. * (/) Permissions drive visibility: a control the user cannot use is absent or disabled. * (/) Loading, empty, error and offline states are all implemented. * (/) RTL layout is correct and every amount, limit and FX rate is an integer. * (/) No request is made to any path outside the L1 allowlist (enforced by FE-CORE-10). * (/) The PR contains a screenshot or GIF of the journey and names the EP-ID used. * (/) Zero console errors and zero new lint warnings. | F23: apps/retailer | G23: High | H23: 2 | J23: EP-RT-A | K23: L1 — Week B | L23: Layer 1 | M23: SP-01 | N23: L1, retailer, otp | O23: RT-04
A24: 23 | B24: RT-06 | C24: Story | D24: RT-06 — Verify OTP and new-user branch | E24: *Screen:* FE-RT-OTP *API contract:* POST /public/auth/verify-otp · EP-CM-002 h3. Requirements # Body: { otp_id, code, device_id, device_name, platform } where device_id is X-Device-Id. # On 200 persist token in the secure store. # If is_new_user is true or profile_completed is false, route to Register; otherwise hand control to the session router. h3. Error handling * 401 otp_invalid → clear the boxes and do not request a new OTP automatically. h3. Acceptance criteria * (/) otp_invalid clears the boxes and triggers no follow-up request. * (/) The token is written to the secure store, not to volatile memory. h3. Definition of done * (/) Runs against real staging — no mock data in the merged branch. * (/) HTTP 422 paints the named fields from error.details.{field}, never a generic banner. * (/) Every write carries X-Idempotency-Key tied to the confirm tap; a network retry reuses the same key. * (/) Permissions drive visibility: a control the user cannot use is absent or disabled. * (/) Loading, empty, error and offline states are all implemented. * (/) RTL layout is correct and every amount, limit and FX rate is an integer. * (/) No request is made to any path outside the L1 allowlist (enforced by FE-CORE-10). * (/) The PR contains a screenshot or GIF of the journey and names the EP-ID used. * (/) Zero console errors and zero new lint warnings. | F24: apps/retailer | G24: Highest | H24: 3 | J24: EP-RT-A | K24: L1 — Week B | L24: Layer 1 | M24: SP-01 | N24: L1, retailer, otp | O24: RT-04
A25: 24 | B25: RT-07 | C25: Story | D25: RT-07 — Load public refs and derive zones | E25: *Screen:* FE-RT-REGISTER *API contract:* GET /public/refs · EP-PB-001 h3. Requirements # Fetch refs before painting the register form. # Bind active activity_types, root_categories, equipments and governorates. # Derive zones by matching zone.governorate_id against the selected governorate. h3. Acceptance criteria * (/) Changing the governorate clears the selected zone immediately. * (/) The form renders from cache on a second visit without a network call. h3. Definition of done * (/) Runs against real staging — no mock data in the merged branch. * (/) HTTP 422 paints the named fields from error.details.{field}, never a generic banner. * (/) Every write carries X-Idempotency-Key tied to the confirm tap; a network retry reuses the same key. * (/) Permissions drive visibility: a control the user cannot use is absent or disabled. * (/) Loading, empty, error and offline states are all implemented. * (/) RTL layout is correct and every amount, limit and FX rate is an integer. * (/) No request is made to any path outside the L1 allowlist (enforced by FE-CORE-10). * (/) The PR contains a screenshot or GIF of the journey and names the EP-ID used. * (/) Zero console errors and zero new lint warnings. | F25: apps/retailer | G25: High | H25: 3 | J25: EP-RT-B | K25: L1 — Week D | L25: Layer 1 | M25: SP-03 | N25: L1, retailer, refs | O25: FE-CORE-05
A26: 25 | B26: RT-08 | C26: Story | D26: RT-08 — Shop registration form | E26: *Screen:* FE-RT-REGISTER *API contract:* Field set of EP-RT-001 h3. Requirements # Required: owner_name, shop_name, activity_type_id, category_ids (at least one), governorate_id, zone_id. # Optional: equipment_ids, address. # Categories are multi-select; where the activity type carries suggestions, show them first. # The screen opens only with an app token carrying the registration ability; without a token, route back to Phone. # No email field and no password field. h3. Acceptance criteria * (/) Submit is impossible with zero categories selected. * (/) The zone list only ever contains zones of the selected governorate. * (/) Opening the screen without a registration token redirects to Phone. h3. Out of scope * Shop photo or document upload — not part of L1. h3. Definition of done * (/) Runs against real staging — no mock data in the merged branch. * (/) HTTP 422 paints the named fields from error.details.{field}, never a generic banner. * (/) Every write carries X-Idempotency-Key tied to the confirm tap; a network retry reuses the same key. * (/) Permissions drive visibility: a control the user cannot use is absent or disabled. * (/) Loading, empty, error and offline states are all implemented. * (/) RTL layout is correct and every amount, limit and FX rate is an integer. * (/) No request is made to any path outside the L1 allowlist (enforced by FE-CORE-10). * (/) The PR contains a screenshot or GIF of the journey and names the EP-ID used. * (/) Zero console errors and zero new lint warnings. | F26: apps/retailer | G26: High | H26: 5 | J26: EP-RT-B | K26: L1 — Week D | L26: Layer 1 | M26: SP-03 | N26: L1, retailer, register | O26: RT-07
A27: 26 | B27: RT-09 | C27: Story | D27: RT-09 — Optional map pin and GPS permission | E27: *Screen:* FE-RT-REGISTER *API contract:* lat and lng in EP-RT-001 h3. Requirements # Request location permission with a clear rationale and fill lat / lng when granted. # Denial must never block submission. h3. Acceptance criteria * (/) Denying the permission still allows the form to be submitted. * (/) lat and lng are omitted rather than sent as zeros when no fix exists. h3. Definition of done * (/) Runs against real staging — no mock data in the merged branch. * (/) HTTP 422 paints the named fields from error.details.{field}, never a generic banner. * (/) Every write carries X-Idempotency-Key tied to the confirm tap; a network retry reuses the same key. * (/) Permissions drive visibility: a control the user cannot use is absent or disabled. * (/) Loading, empty, error and offline states are all implemented. * (/) RTL layout is correct and every amount, limit and FX rate is an integer. * (/) No request is made to any path outside the L1 allowlist (enforced by FE-CORE-10). * (/) The PR contains a screenshot or GIF of the journey and names the EP-ID used. * (/) Zero console errors and zero new lint warnings. | F27: apps/retailer | G27: Medium | H27: 2 | J27: EP-RT-B | K27: L1 — Week D | L27: Layer 1 | M27: SP-03 | N27: L1, retailer, gps | O27: RT-08
A28: 27 | B28: RT-10 | C28: Story | D28: RT-10 — Submit registration and swap the token | E28: *Screen:* FE-RT-REGISTER *API contract:* POST /app/retailer/register · EP-RT-001 · Bearer + idempotency h3. Requirements # Send with Bearer and one idempotency key per confirm tap. # On 200 replace the stored token with data.token and route to Waiting with status pending_review. h3. Error handling * 422 (for example zone not in governorate) → keep the form populated and render details on the offending fields. h3. Acceptance criteria * (/) A 422 keeps the form state intact and paints details. * (/) A retry after a dropped connection does not create two shop profiles. h3. Definition of done * (/) Runs against real staging — no mock data in the merged branch. * (/) HTTP 422 paints the named fields from error.details.{field}, never a generic banner. * (/) Every write carries X-Idempotency-Key tied to the confirm tap; a network retry reuses the same key. * (/) Permissions drive visibility: a control the user cannot use is absent or disabled. * (/) Loading, empty, error and offline states are all implemented. * (/) RTL layout is correct and every amount, limit and FX rate is an integer. * (/) No request is made to any path outside the L1 allowlist (enforced by FE-CORE-10). * (/) The PR contains a screenshot or GIF of the journey and names the EP-ID used. * (/) Zero console errors and zero new lint warnings. | F28: apps/retailer | G28: High | H28: 3 | J28: EP-RT-B | K28: L1 — Week D | L28: Layer 1 | M28: SP-03 | N28: L1, retailer, register | O28: RT-08 FE-CORE-03
A29: 28 | B29: RT-11 | C29: Story | D29: RT-11 — Waiting screen and status refresh | E29: *Screen:* FE-RT-WAIT *API contract:* GET /app/session · EP-CM-004 h3. Requirements # Static copy for pending_review, the phone number, a refresh action and logout. # Refresh calls the session router; it never re-submits registration. h3. Acceptance criteria * (/) Refresh triggers a session call and nothing else. * (/) No operational widget or fabricated counter appears on the screen. h3. Definition of done * (/) Runs against real staging — no mock data in the merged branch. * (/) HTTP 422 paints the named fields from error.details.{field}, never a generic banner. * (/) Every write carries X-Idempotency-Key tied to the confirm tap; a network retry reuses the same key. * (/) Permissions drive visibility: a control the user cannot use is absent or disabled. * (/) Loading, empty, error and offline states are all implemented. * (/) RTL layout is correct and every amount, limit and FX rate is an integer. * (/) No request is made to any path outside the L1 allowlist (enforced by FE-CORE-10). * (/) The PR contains a screenshot or GIF of the journey and names the EP-ID used. * (/) Zero console errors and zero new lint warnings. | F29: apps/retailer | G29: High | H29: 2 | J29: EP-RT-C | K29: L1 — Week C | L29: Layer 1 | M29: SP-01 | N29: L1, retailer, lifecycle | O29: RT-13
A30: 29 | B30: RT-12 | C30: Story | D30: RT-12 — Rejected screen | E30: *Screen:* FE-RT-WAIT *API contract:* rejected status from the session h3. Requirements # Show rejection copy when the session provides it. # Static WhatsApp support text is allowed as an operational contact route. h3. Acceptance criteria * (/) No edit form and no silent re-registration on the same token. h3. Definition of done * (/) Runs against real staging — no mock data in the merged branch. * (/) HTTP 422 paints the named fields from error.details.{field}, never a generic banner. * (/) Every write carries X-Idempotency-Key tied to the confirm tap; a network retry reuses the same key. * (/) Permissions drive visibility: a control the user cannot use is absent or disabled. * (/) Loading, empty, error and offline states are all implemented. * (/) RTL layout is correct and every amount, limit and FX rate is an integer. * (/) No request is made to any path outside the L1 allowlist (enforced by FE-CORE-10). * (/) The PR contains a screenshot or GIF of the journey and names the EP-ID used. * (/) Zero console errors and zero new lint warnings. | F30: apps/retailer | G30: Medium | H30: 1 | J30: EP-RT-C | K30: L1 — Week C | L30: Layer 1 | M30: SP-01 | N30: L1, retailer, lifecycle | O30: RT-13
... A36: 35 | B36: RT-18 | C36: Task | D36: RT-18 — Recorded acceptance walkthrough | E36: *API contract:* — h3. Requirements # Execute the four scenarios in the product definition of done. # Record each one and note the EP-ID used and the observed response. h3. Acceptance criteria * (/) A screen recording or signed manual checklist is attached to the issue. * (/) All four scenarios pass without a workaround. h3. Definition of done * (/) Runs against real staging — no mock data in the merged branch. * (/) HTTP 422 paints the named fields from error.details.{field}, never a generic banner. * (/) Every write carries X-Idempotency-Key tied to the confirm tap; a network retry reuses the same key. * (/) Permissions drive visibility: a control the user cannot use is absent or disabled. * (/) Loading, empty, error and offline states are all implemented. * (/) RTL layout is correct and every amount, limit and FX rate is an integer. * (/) No request is made to any path outside the L1 allowlist (enforced by FE-CORE-10). * (/) The PR contains a screenshot or GIF of the journey and names the EP-ID used. * (/) Zero console errors and zero new lint warnings. | F36: apps/retailer | G36: High | H36: 2 | J36: EP-RT-D | K36: L1 — Week D | L36: Layer 1 | M36: SP-01 | N36: L1, retailer, qa | O36: RT-01 RT-02 RT-03 RT-04 RT-05 RT-06 RT-07 RT-08 RT-09 RT-10 RT-11 RT-12 RT-13 RT-14 RT-15 RT-16 RT-17
A37: 36 | B37: EP-RP-A | C37: Epic | D37: EP-RP-A — Shared package and setup | E37: *Product:* Field rep app *Covers:* Identity flow extraction, separate binary *Volume:* 3 issues / 6 points | F37: packages/b2b-auth-flow | G37: High | I37: EP-RP-A | L37: Layer 1 | M37: SP-01 · SP-03 (activity types / zones) · SP-04 (channel invite id) | N37: L1 epic
A38: 37 | B38: EP-RP-B | C38: Epic | D38: EP-RP-B — Invite and registration | E38: *Product:* Field rep app *Covers:* Deep link, channel_id, zone_ids *Volume:* 4 issues / 9 points | F38: packages/b2b-auth-flow | G38: High | I38: EP-RP-B | L38: Layer 1 | M38: SP-01 · SP-03 (activity types / zones) · SP-04 (channel invite id) | N38: L1 epic
A39: 38 | B39: EP-RP-C | C39: Epic | D39: EP-RP-C — Lifecycle and acceptance | E39: *Product:* Field rep app *Covers:* Waiting, empty home, session, walkthrough *Volume:* 3 issues / 6 points | F39: packages/b2b-auth-flow | G39: High | I39: EP-RP-C | L39: Layer 1 | M39: SP-01 · SP-03 (activity types / zones) · SP-04 (channel invite id) | N39: L1 epic
A40: 39 | B40: RP-01 | C40: Task | D40: RP-01 — Extract the shared identity flow package | E40: *Screen:* FE-RP-PHONE · FE-RP-OTP *API contract:* EP-CM-001 / EP-CM-002 / EP-CM-003 h3. Requirements # Move the phone screen, OTP screen, countdown and error handling out of the retailer app into a configurable package. # Configuration points: client value, purpose, post-verify destination, copy. # The retailer app consumes the package rather than keeping a private copy. h3. Acceptance criteria * (/) The retailer app passes its four walkthrough scenarios after extraction with no regression. * (/) Test coverage is preserved or improved. * (/) No duplicate OTP logic exists in either repository. h3. Definition of done * (/) Runs against real staging — no mock data in the merged branch. * (/) HTTP 422 paints the named fields from error.details.{field}, never a generic banner. * (/) Every write carries X-Idempotency-Key tied to the confirm tap; a network retry reuses the same key. * (/) Permissions drive visibility: a control the user cannot use is absent or disabled. * (/) Loading, empty, error and offline states are all implemented. * (/) RTL layout is correct and every amount, limit and FX rate is an integer. * (/) No request is made to any path outside the L1 allowlist (enforced by FE-CORE-10). * (/) The PR contains a screenshot or GIF of the journey and names the EP-ID used. * (/) Zero console errors and zero new lint warnings. | F40: packages/b2b-auth-flow | G40: Highest | H40: 3 | J40: EP-RP-A | K40: L1 — Week C | L40: Layer 1 | M40: SP-01 | N40: L1, rep, refactor, shared | O40: RT-06
A41: 40 | B41: RP-02 | C41: Task | D41: RP-02 — Stand up the separate rep binary | E41: *API contract:* — h3. Requirements # Separate icon, bundle identifier and visual identity. # X-Client set to rep-android or rep-ios. # No in-session switch between retailer and rep. h3. Acceptance criteria * (/) Both builds send the rep client value. * (/) No route exists for switching product roles. h3. Definition of done * (/) Runs against real staging — no mock data in the merged branch. * (/) HTTP 422 paints the named fields from error.details.{field}, never a generic banner. * (/) Every write carries X-Idempotency-Key tied to the confirm tap; a network retry reuses the same key. * (/) Permissions drive visibility: a control the user cannot use is absent or disabled. * (/) Loading, empty, error and offline states are all implemented. * (/) RTL layout is correct and every amount, limit and FX rate is an integer. * (/) No request is made to any path outside the L1 allowlist (enforced by FE-CORE-10). * (/) The PR contains a screenshot or GIF of the journey and names the EP-ID used. * (/) Zero console errors and zero new lint warnings. | F41: apps/rep | G41: Highest | H41: 2 | J41: EP-RP-A | K41: L1 — Week C | L41: Layer 1 | M41: SP-01 | N41: L1, rep, setup | O41: RP-01
A42: 41 | B42: RP-03 | C42: Story | D42: RP-03 — Compose the phone and OTP flow | E42: *Screen:* FE-RP-PHONE · FE-RP-OTP *API contract:* EP-CM-001 · EP-CM-002 · EP-CM-003 h3. Requirements # Compose the shared flow with rep configuration and no new logic. # Verify sends device_id, device_name and platform as in the retailer app. h3. Acceptance criteria * (/) Registering the same phone under a second kind surfaces the server rejection message verbatim. h3. Definition of done * (/) Runs against real staging — no mock data in the merged branch. * (/) HTTP 422 paints the named fields from error.details.{field}, never a generic banner. * (/) Every write carries X-Idempotency-Key tied to the confirm tap; a network retry reuses the same key. * (/) Permissions drive visibility: a control the user cannot use is absent or disabled. * (/) Loading, empty, error and offline states are all implemented. * (/) RTL layout is correct and every amount, limit and FX rate is an integer. * (/) No request is made to any path outside the L1 allowlist (enforced by FE-CORE-10). * (/) The PR contains a screenshot or GIF of the journey and names the EP-ID used. * (/) Zero console errors and zero new lint warnings. | F42: apps/rep | G42: High | H42: 1 | J42: EP-RP-A | K42: L1 — Week C | L42: Layer 1 | M42: SP-01 | N42: L1, rep, otp | O42: RP-01
A43: 42 | B43: RP-04 | C43: Story | D43: RP-04 — Invite deep link and channel_id capture | E43: *Screen:* FE-RP-REGISTER *API contract:* b2b-rep://register?channel_id={id} (optional channel_name) h3. Requirements # Handle the b2b-rep:// scheme and capture channel_id, plus channel_name for display when present. # The channel field is locked and cannot be changed by the user. # The link works when the app is closed and when it is backgrounded. h3. Acceptance criteria * (/) The channel field is non-editable in every state. * (/) Cold start and warm start from the link both reach the register form with the id applied. h3. Definition of done * (/) Runs against real staging — no mock data in the merged branch. * (/) HTTP 422 paints the named fields from error.details.{field}, never a generic banner. * (/) Every write carries X-Idempotency-Key tied to the confirm tap; a network retry reuses the same key. * (/) Permissions drive visibility: a control the user cannot use is absent or disabled. * (/) Loading, empty, error and offline states are all implemented. * (/) RTL layout is correct and every amount, limit and FX rate is an integer. * (/) No request is made to any path outside the L1 allowlist (enforced by FE-CORE-10). * (/) The PR contains a screenshot or GIF of the journey and names the EP-ID used. * (/) Zero console errors and zero new lint warnings. | F43: apps/rep | G43: High | H43: 3 | J43: EP-RP-B | K43: L1 — Week E | L43: Layer 1 | M43: SP-04 | N43: L1, rep, deeplink | O43: RP-02
A44: 43 | B44: RP-05 | C44: Story | D44: RP-05 — No-invite guidance screen | E44: *Screen:* FE-RP-REGISTER *API contract:* — h3. Requirements # When the register screen is opened without channel_id, show copy only: use the invite link from your company. # No channel search, no channel list, no fetch. h3. Acceptance criteria * (/) Zero calls to /platform/channels or any channel lookup, enforced by FE-CORE-10. h3. Definition of done * (/) Runs against real staging — no mock data in the merged branch. * (/) HTTP 422 paints the named fields from error.details.{field}, never a generic banner. * (/) Every write carries X-Idempotency-Key tied to the confirm tap; a network retry reuses the same key. * (/) Permissions drive visibility: a control the user cannot use is absent or disabled. * (/) Loading, empty, error and offline states are all implemented. * (/) RTL layout is correct and every amount, limit and FX rate is an integer. * (/) No request is made to any path outside the L1 allowlist (enforced by FE-CORE-10). * (/) The PR contains a screenshot or GIF of the journey and names the EP-ID used. * (/) Zero console errors and zero new lint warnings. | F44: apps/rep | G44: High | H44: 1 | J44: EP-RP-B | K44: L1 — Week E | L44: Layer 1 | M44: SP-04 | N44: L1, rep, guardrail | O44: RP-04
A45: 44 | B45: RP-06 | C45: Story | D45: RP-06 — Rep registration form | E45: *Screen:* FE-RP-REGISTER *API contract:* GET /public/refs · EP-PB-001 h3. Requirements # Required: name, supply_channel_id (locked, from the invite), activity_type_id, zone_ids with at least one entry. # Optional: note. # Activity types and zones come from public refs only. h3. Acceptance criteria * (/) Submit is impossible with an empty zone selection. * (/) No source other than /public/refs populates the zone list. h3. Definition of done * (/) Runs against real staging — no mock data in the merged branch. * (/) HTTP 422 paints the named fields from error.details.{field}, never a generic banner. * (/) Every write carries X-Idempotency-Key tied to the confirm tap; a network retry reuses the same key. * (/) Permissions drive visibility: a control the user cannot use is absent or disabled. * (/) Loading, empty, error and offline states are all implemented. * (/) RTL layout is correct and every amount, limit and FX rate is an integer. * (/) No request is made to any path outside the L1 allowlist (enforced by FE-CORE-10). * (/) The PR contains a screenshot or GIF of the journey and names the EP-ID used. * (/) Zero console errors and zero new lint warnings. | F45: apps/rep | G45: High | H45: 3 | J45: EP-RP-B | K45: L1 — Week E | L45: Layer 1 | M45: SP-04 | N45: L1, rep, register | O45: RP-04 FE-CORE-05
A46: 45 | B46: RP-07 | C46: Story | D46: RP-07 — Submit registration and handle coverage rejection | E46: *Screen:* FE-RP-REGISTER *API contract:* POST /app/rep/register · EP-RP-001 · Bearer + idempotency h3. Requirements # Send with Bearer and one idempotency key per confirm tap. # On 200 store data.token; rep.status is pending_review and the app routes to Waiting. h3. Error handling * 422 when a zone falls outside the channel coverage → keep the form and paint the field error. * 409 when the channel is not active → show error.message exactly as sent. h3. Acceptance criteria * (/) error.message is rendered verbatim with no invented wording. * (/) The form retains its values after either error. h3. Definition of done * (/) Runs against real staging — no mock data in the merged branch. * (/) HTTP 422 paints the named fields from error.details.{field}, never a generic banner. * (/) Every write carries X-Idempotency-Key tied to the confirm tap; a network retry reuses the same key. * (/) Permissions drive visibility: a control the user cannot use is absent or disabled. * (/) Loading, empty, error and offline states are all implemented. * (/) RTL layout is correct and every amount, limit and FX rate is an integer. * (/) No request is made to any path outside the L1 allowlist (enforced by FE-CORE-10). * (/) The PR contains a screenshot or GIF of the journey and names the EP-ID used. * (/) Zero console errors and zero new lint warnings. | F46: apps/rep | G46: High | H46: 2 | J46: EP-RP-B | K46: L1 — Week E | L46: Layer 1 | M46: SP-04 | N46: L1, rep, register | O46: RP-06 FE-CORE-03
A47: 46 | B47: RP-08 | C47: Story | D47: RP-08 — Waiting and empty home | E47: *Screen:* FE-RP-WAIT · FE-RP-HOME-EMPTY *API contract:* GET /app/session · EP-CM-004 h3. Requirements # Waiting mirrors the retailer logic. # Empty home shows the rep name, the channel name from the register payload, and copy stating that tasks unlock after approval. h3. Acceptance criteria * (/) No product list, no task list, no map, no counters. h3. Definition of done * (/) Runs against real staging — no mock data in the merged branch. * (/) HTTP 422 paints the named fields from error.details.{field}, never a generic banner. * (/) Every write carries X-Idempotency-Key tied to the confirm tap; a network retry reuses the same key. * (/) Permissions drive visibility: a control the user cannot use is absent or disabled. * (/) Loading, empty, error and offline states are all implemented. * (/) RTL layout is correct and every amount, limit and FX rate is an integer. * (/) No request is made to any path outside the L1 allowlist (enforced by FE-CORE-10). * (/) The PR contains a screenshot or GIF of the journey and names the EP-ID used. * (/) Zero console errors and zero new lint warnings. | F47: apps/rep | G47: Medium | H47: 2 | J47: EP-RP-C | K47: L1 — Week C | L47: Layer 1 | M47: SP-01 | N47: L1, rep, lifecycle | O47: RP-07
A48: 47 | B48: RP-09 | C48: Story | D48: RP-09 — Session and logout | E48: *Screen:* FE-RP-WAIT *API contract:* EP-CM-004 · EP-CM-005 h3. Requirements # Reuse the session router and logout behaviour from the shared package. # Local wipe follows REQ-CM-056. h3. Acceptance criteria * (/) Behaviour is identical to the retailer app including the local wipe. h3. Definition of done * (/) Runs against real staging — no mock data in the merged branch. * (/) HTTP 422 paints the named fields from error.details.{field}, never a generic banner. * (/) Every write carries X-Idempotency-Key tied to the confirm tap; a network retry reuses the same key. * (/) Permissions drive visibility: a control the user cannot use is absent or disabled. * (/) Loading, empty, error and offline states are all implemented. * (/) RTL layout is correct and every amount, limit and FX rate is an integer. * (/) No request is made to any path outside the L1 allowlist (enforced by FE-CORE-10). * (/) The PR contains a screenshot or GIF of the journey and names the EP-ID used. * (/) Zero console errors and zero new lint warnings. | F48: apps/rep | G48: Medium | H48: 1 | J48: EP-RP-C | K48: L1 — Week C | L48: Layer 1 | M48: SP-01 | N48: L1, rep, session | O48: RP-01
A49: 48 | B49: RP-10 | C49: Task | D49: RP-10 — Packaging and recorded acceptance walkthrough | E49: *API contract:* — h3. Requirements # Ship internal builds for both platforms. # Execute the three scenarios in the product definition of done and record them. h3. Acceptance criteria * (/) The invite journey is captured on video. * (/) The network monitor report shows zero channel-lookup calls. h3. Definition of done * (/) Runs against real staging — no mock data in the merged branch. * (/) HTTP 422 paints the named fields from error.details.{field}, never a generic banner. * (/) Every write carries X-Idempotency-Key tied to the confirm tap; a network retry reuses the same key. * (/) Permissions drive visibility: a control the user cannot use is absent or disabled. * (/) Loading, empty, error and offline states are all implemented. * (/) RTL layout is correct and every amount, limit and FX rate is an integer. * (/) No request is made to any path outside the L1 allowlist (enforced by FE-CORE-10). * (/) The PR contains a screenshot or GIF of the journey and names the EP-ID used. * (/) Zero console errors and zero new lint warnings. | F49: apps/rep | G49: High | H49: 3 | J49: EP-RP-C | K49: L1 — Week E | L49: Layer 1 | M49: SP-01 | N49: L1, rep, qa, release | O49: RP-01 RP-02 RP-03 RP-04 RP-05 RP-06 RP-07 RP-08 RP-09
A50: 49 | B50: EP-CH-A | C50: Epic | D50: EP-CH-A — Sign-in and channel selection | E50: *Product:* Channel dashboard *Covers:* FE-CH-PHONE, FE-CH-OTP, FE-CH-PICK *Volume:* 4 issues / 9 points | F50: apps/channel-web | G50: High | I50: EP-CH-A | L50: Layer 1 | M50: SP-01 (/channel/auth/* only) | N50: L1 epic
A51: 50 | B51: EP-CH-B | C51: Epic | D51: EP-CH-B — Shell and office | E51: *Product:* Channel dashboard *Covers:* FE-CH-SHELL, /home, FE-CH-LOGOUT *Volume:* 4 issues / 6 points | F51: apps/channel-web | G51: High | I51: EP-CH-B | L51: Layer 1 | M51: SP-01 (/channel/auth/* only) | N51: L1 epic
A52: 51 | B52: EP-CH-C | C52: Epic | D52: EP-CH-C — Guardrails and acceptance | E52: *Product:* Channel dashboard *Covers:* Network siege test, walkthrough *Volume:* 2 issues / 3 points | F52: apps/channel-web | G52: High | I52: EP-CH-C | L52: Layer 1 | M52: SP-01 (/channel/auth/* only) | N52: L1 epic
A53: 52 | B53: CH-01 | C53: Task | D53: CH-01 — Project scaffold and four-route router | E53: *API contract:* — h3. Requirements # Register exactly four paths: /login/phone, /login/otp, /select-channel, /home. # Everything else resolves to an internal 404. # No deferred page components are committed to the repository. h3. Acceptance criteria * (/) /catalog, /orders and /reps do not exist in the router table. * (/) A code review confirms no placeholder page components exist. h3. Definition of done * (/) Runs against real staging — no mock data in the merged branch. * (/) HTTP 422 paints the named fields from error.details.{field}, never a generic banner. * (/) Every write carries X-Idempotency-Key tied to the confirm tap; a network retry reuses the same key. * (/) Permissions drive visibility: a control the user cannot use is absent or disabled. * (/) Loading, empty, error and offline states are all implemented. * (/) RTL layout is correct and every amount, limit and FX rate is an integer. * (/) No request is made to any path outside the L1 allowlist (enforced by FE-CORE-10). * (/) The PR contains a screenshot or GIF of the journey and names the EP-ID used. * (/) Zero console errors and zero new lint warnings. | F53: apps/channel-web | G53: Highest | H53: 2 | J53: EP-CH-A | K53: L1 — Week A | L53: Layer 1 | M53: SP-01 | N53: L1, channel, setup, routing | O53: FE-CORE-01 FE-CORE-02 FE-CORE-03 FE-CORE-04 FE-CORE-05
A54: 53 | B54: CH-02 | C54: Story | D54: CH-02 — Phone screen and channel OTP request | E54: *Screen:* FE-CH-PHONE *API contract:* POST /channel/auth/request-otp · EP-CH-001 h3. Requirements # Body contains phone only. purpose is not part of this catalog row and must not be sent. # Store otp_id and route to the OTP screen. # This path is exempt from the idempotency key per the shared kit. h3. Error handling * 429 rate_limited → disable submit and show the countdown. h3. Acceptance criteria * (/) The contract test fails if purpose is included in the body. * (/) A 429 disables the button. h3. Definition of done * (/) Runs against real staging — no mock data in the merged branch. * (/) HTTP 422 paints the named fields from error.details.{field}, never a generic banner. * (/) Every write carries X-Idempotency-Key tied to the confirm tap; a network retry reuses the same key. * (/) Permissions drive visibility: a control the user cannot use is absent or disabled. * (/) Loading, empty, error and offline states are all implemented. * (/) RTL layout is correct and every amount, limit and FX rate is an integer. * (/) No request is made to any path outside the L1 allowlist (enforced by FE-CORE-10). * (/) The PR contains a screenshot or GIF of the journey and names the EP-ID used. * (/) Zero console errors and zero new lint warnings. | F54: apps/channel-web | G54: Highest | H54: 2 | J54: EP-CH-A | K54: L1 — Week B | L54: Layer 1 | M54: SP-01 | N54: L1, channel, otp | O54: CH-01
A55: 54 | B55: CH-03 | C55: Story | D55: CH-03 — OTP verification and session persistence | E55: *Screen:* FE-CH-OTP *API contract:* POST /channel/auth/verify-otp · EP-CH-002 h3. Requirements # Body: { otp_id, code }. # On 200 persist token and permissions[] — permissions drive the sidebar in CH-05. # Read the channels collection from the response and hand it to the picker logic. h3. Error handling * 401 otp_invalid → clear the boxes, no automatic re-request. * Empty channels or 403 → show the server message; never invent a channel. h3. Acceptance criteria * (/) permissions[] is persisted alongside the token. * (/) The token is written only to the store defined in FE-CORE-02. h3. Definition of done * (/) Runs against real staging — no mock data in the merged branch. * (/) HTTP 422 paints the named fields from error.details.{field}, never a generic banner. * (/) Every write carries X-Idempotency-Key tied to the confirm tap; a network retry reuses the same key. * (/) Permissions drive visibility: a control the user cannot use is absent or disabled. * (/) Loading, empty, error and offline states are all implemented. * (/) RTL layout is correct and every amount, limit and FX rate is an integer. * (/) No request is made to any path outside the L1 allowlist (enforced by FE-CORE-10). * (/) The PR contains a screenshot or GIF of the journey and names the EP-ID used. * (/) Zero console errors and zero new lint warnings. | F55: apps/channel-web | G55: Highest | H55: 2 | J55: EP-CH-A | K55: L1 — Week B | L55: Layer 1 | M55: SP-01 | N55: L1, channel, otp | O55: CH-02
A56: 55 | B56: CH-04 | C56: Story | D56: CH-04 — Channel picker and X-Channel-Id pinning | E56: *Screen:* FE-CH-PICK *API contract:* data.channels from the verify response h3. Requirements # When channels.length is 1, set X-Channel-Id and go straight to /home with no interstitial. # When channels.length is greater than 1, render cards at /select-channel. # The selection pins X-Channel-Id on every later request until the user switches from the header or menu. h3. Acceptance criteria * (/) Switching channel rebuilds permissions and clears cache bound to the previous channel. * (/) X-Channel-Id is present on every request after selection. h3. Definition of done * (/) Runs against real staging — no mock data in the merged branch. * (/) HTTP 422 paints the named fields from error.details.{field}, never a generic banner. * (/) Every write carries X-Idempotency-Key tied to the confirm tap; a network retry reuses the same key. * (/) Permissions drive visibility: a control the user cannot use is absent or disabled. * (/) Loading, empty, error and offline states are all implemented. * (/) RTL layout is correct and every amount, limit and FX rate is an integer. * (/) No request is made to any path outside the L1 allowlist (enforced by FE-CORE-10). * (/) The PR contains a screenshot or GIF of the journey and names the EP-ID used. * (/) Zero console errors and zero new lint warnings. | F56: apps/channel-web | G56: High | H56: 3 | J56: EP-CH-A | K56: L1 — Week B | L56: Layer 1 | M56: SP-01 | N56: L1, channel, context | O56: CH-03
A57: 56 | B57: CH-05 | C57: Story | D57: CH-05 — Shell and permission-driven sidebar | E57: *Screen:* FE-CH-SHELL *API contract:* permissions[] h3. Requirements # The sidebar is generated from permissions[] and never from a hard-coded constant. # Layer 2+ items (sc.catalog.*, sc.orders.*, numeric sc.dashboard.view) are either omitted or shown disabled with "Available after operations go live". # A disabled item has no page and issues no fetch. h3. Acceptance criteria * (/) A disabled item is not clickable and owns no route. * (/) Removing a permission on the server hides the item after re-login. h3. Definition of done * (/) Runs against real staging — no mock data in the merged branch. * (/) HTTP 422 paints the named fields from error.details.{field}, never a generic banner. * (/) Every write carries X-Idempotency-Key tied to the confirm tap; a network retry reuses the same key. * (/) Permissions drive visibility: a control the user cannot use is absent or disabled. * (/) Loading, empty, error and offline states are all implemented. * (/) RTL layout is correct and every amount, limit and FX rate is an integer. * (/) No request is made to any path outside the L1 allowlist (enforced by FE-CORE-10). * (/) The PR contains a screenshot or GIF of the journey and names the EP-ID used. * (/) Zero console errors and zero new lint warnings. | F57: apps/channel-web | G57: High | H57: 3 | J57: EP-CH-B | K57: L1 — Week C | L57: Layer 1 | M57: SP-01 | N57: L1, channel, shell | O57: FE-CORE-04 CH-04
A58: 57 | B58: CH-06 | C58: Story | D58: CH-06 — Empty office at /home | E58: *Screen:* FE-CH-SHELL *API contract:* — h3. Requirements # Show the selected channel name and the signed-in user identity. h3. Acceptance criteria * (/) No charts, no GMV, no metric tiles anywhere on the page. h3. Definition of done * (/) Runs against real staging — no mock data in the merged branch. * (/) HTTP 422 paints the named fields from error.details.{field}, never a generic banner. * (/) Every write carries X-Idempotency-Key tied to the confirm tap; a network retry reuses the same key. * (/) Permissions drive visibility: a control the user cannot use is absent or disabled. * (/) Loading, empty, error and offline states are all implemented. * (/) RTL layout is correct and every amount, limit and FX rate is an integer. * (/) No request is made to any path outside the L1 allowlist (enforced by FE-CORE-10). * (/) The PR contains a screenshot or GIF of the journey and names the EP-ID used. * (/) Zero console errors and zero new lint warnings. | F58: apps/channel-web | G58: Medium | H58: 1 | J58: EP-CH-B | K58: L1 — Week C | L58: Layer 1 | M58: SP-01 | N58: L1, channel, home | O58: CH-05
A59: 58 | B59: CH-07 | C59: Story | D59: CH-07 — Local sign-out | E59: *Screen:* FE-CH-LOGOUT *API contract:* No channel logout endpoint exists in the L1 catalog h3. Requirements # Clear the token and X-Channel-Id locally and redirect to /login/phone. h3. Acceptance criteria * (/) No attempt is made to call /channel/auth/logout. * (/) No channel id remains in storage after sign-out. h3. Definition of done * (/) Runs against real staging — no mock data in the merged branch. * (/) HTTP 422 paints the named fields from error.details.{field}, never a generic banner. * (/) Every write carries X-Idempotency-Key tied to the confirm tap; a network retry reuses the same key. * (/) Permissions drive visibility: a control the user cannot use is absent or disabled. * (/) Loading, empty, error and offline states are all implemented. * (/) RTL layout is correct and every amount, limit and FX rate is an integer. * (/) No request is made to any path outside the L1 allowlist (enforced by FE-CORE-10). * (/) The PR contains a screenshot or GIF of the journey and names the EP-ID used. * (/) Zero console errors and zero new lint warnings. | F59: apps/channel-web | G59: Medium | H59: 1 | J59: EP-CH-B | K59: L1 — Week C | L59: Layer 1 | M59: SP-01 | N59: L1, channel, auth | O59: CH-03
A60: 59 | B60: CH-08 | C60: Story | D60: CH-08 — No-membership and token expiry handling | E60: *Screen:* FE-CH-SHELL *API contract:* 403 and 401 envelope responses h3. Requirements # Render the server message on a 403 with no channel membership. # Handle unauthenticated by dropping the token and returning to sign-in. h3. Acceptance criteria * (/) No default channel is invented and no redirect to /home occurs on 403. h3. Definition of done * (/) Runs against real staging — no mock data in the merged branch. * (/) HTTP 422 paints the named fields from error.details.{field}, never a generic banner. * (/) Every write carries X-Idempotency-Key tied to the confirm tap; a network retry reuses the same key. * (/) Permissions drive visibility: a control the user cannot use is absent or disabled. * (/) Loading, empty, error and offline states are all implemented. * (/) RTL layout is correct and every amount, limit and FX rate is an integer. * (/) No request is made to any path outside the L1 allowlist (enforced by FE-CORE-10). * (/) The PR contains a screenshot or GIF of the journey and names the EP-ID used. * (/) Zero console errors and zero new lint warnings. | F60: apps/channel-web | G60: Medium | H60: 1 | J60: EP-CH-B | K60: L1 — Week C | L60: Layer 1 | M60: SP-01 | N60: L1, channel, errors | O60: FE-CORE-01
A61: 60 | B61: CH-09 | C61: Task | D61: CH-09 — Network siege test | E61: *API contract:* L1 allowlist h3. Requirements # Run the full journey with a request monitor comparing every path against the L1 allowlist. # Attach the monitor report to the issue. h3. Acceptance criteria * (/) The build fails on a request to /channel/brands or /channel/products. * (/) The report enumerates every path the journey touched. h3. Definition of done * (/) Runs against real staging — no mock data in the merged branch. * (/) HTTP 422 paints the named fields from error.details.{field}, never a generic banner. * (/) Every write carries X-Idempotency-Key tied to the confirm tap; a network retry reuses the same key. * (/) Permissions drive visibility: a control the user cannot use is absent or disabled. * (/) Loading, empty, error and offline states are all implemented. * (/) RTL layout is correct and every amount, limit and FX rate is an integer. * (/) No request is made to any path outside the L1 allowlist (enforced by FE-CORE-10). * (/) The PR contains a screenshot or GIF of the journey and names the EP-ID used. * (/) Zero console errors and zero new lint warnings. | F61: apps/channel-web | G61: Highest | H61: 2 | J61: EP-CH-C | K61: L1 — Week C | L61: Layer 1 | M61: SP-01 | N61: L1, channel, guardrail, qa | O61: FE-CORE-10
A62: 61 | B62: CH-10 | C62: Task | D62: CH-10 — Recorded acceptance walkthrough | E62: *API contract:* — h3. Requirements # Run the walkthrough with an account that belongs to two channels and record it. h3. Acceptance criteria * (/) The recording shows sign-in, channel selection, empty office and sign-out. * (/) Zero Layer 2 network calls occur during the recording. h3. Definition of done * (/) Runs against real staging — no mock data in the merged branch. * (/) HTTP 422 paints the named fields from error.details.{field}, never a generic banner. * (/) Every write carries X-Idempotency-Key tied to the confirm tap; a network retry reuses the same key. * (/) Permissions drive visibility: a control the user cannot use is absent or disabled. * (/) Loading, empty, error and offline states are all implemented. * (/) RTL layout is correct and every amount, limit and FX rate is an integer. * (/) No request is made to any path outside the L1 allowlist (enforced by FE-CORE-10). * (/) The PR contains a screenshot or GIF of the journey and names the EP-ID used. * (/) Zero console errors and zero new lint warnings. | F62: apps/channel-web | G62: High | H62: 1 | J62: EP-CH-C | K62: L1 — Week C | L62: Layer 1 | M62: SP-01 | N62: L1, channel, qa | O62: CH-01 CH-02 CH-03 CH-04 CH-05 CH-06 CH-07 CH-08 CH-09
A63: 62 | B63: EP-WH-A | C63: Epic | D63: EP-WH-A — Device provisioning and lock | E63: *Product:* Warehouse web *Covers:* device_token, FE-WH-PIN, device login *Volume:* 3 issues / 8 points | F63: apps/warehouse-web | G63: High | I63: EP-WH-A | L63: Layer 1 | M63: SP-01 (POST /warehouse/auth/device-login only) | N63: L1 epic
A64: 63 | B64: EP-WH-B | C64: Epic | D64: EP-WH-B — Floor and acceptance | E64: *Product:* Warehouse web *Covers:* FE-WH-HOME, sign-out, kiosk mode, walkthrough *Volume:* 4 issues / 5 points | F64: apps/warehouse-web | G64: High | I64: EP-WH-B | L64: Layer 1 | M64: SP-01 (POST /warehouse/auth/device-login only) | N64: L1 epic
A65: 64 | B65: WH-01 | C65: Task | D65: WH-01 — Read device_token from installed configuration | E65: *API contract:* device_token issued by backend warehouse:register-device h3. Requirements # Read the token from environment or local config placed by ops after backend provisioning. # Render a "device not provisioned" state addressed to the operator, not to the floor user. # The token must never be displayed in production. h3. Acceptance criteria * (/) The token does not appear in the UI, in browser logs or in any error message. * (/) The unprovisioned state gives the operator a clear next step. h3. Out of scope * Any in-product device registration or token entry screen. h3. Definition of done * (/) Runs against real staging — no mock data in the merged branch. * (/) HTTP 422 paints the named fields from error.details.{field}, never a generic banner. * (/) Every write carries X-Idempotency-Key tied to the confirm tap; a network retry reuses the same key. * (/) Permissions drive visibility: a control the user cannot use is absent or disabled. * (/) Loading, empty, error and offline states are all implemented. * (/) RTL layout is correct and every amount, limit and FX rate is an integer. * (/) No request is made to any path outside the L1 allowlist (enforced by FE-CORE-10). * (/) The PR contains a screenshot or GIF of the journey and names the EP-ID used. * (/) Zero console errors and zero new lint warnings. | F65: apps/warehouse-web | G65: Highest | H65: 3 | J65: EP-WH-A | K65: L1 — Week A | L65: Layer 1 | M65: SP-01 | N65: L1, warehouse, security, setup | O65: FE-CORE-01
A66: 65 | B66: WH-02 | C66: Story | D66: WH-02 — PIN pad screen | E66: *Screen:* FE-WH-PIN *API contract:* — h3. Requirements # Exactly four digits, validated against /^\d{4}$/. # A large on-screen numeric pad usable with gloves. # The OS keyboard must never appear. h3. Acceptance criteria * (/) Hit targets are at least 64 pixels. * (/) No system keyboard is triggered on any interaction. h3. Definition of done * (/) Runs against real staging — no mock data in the merged branch. * (/) HTTP 422 paints the named fields from error.details.{field}, never a generic banner. * (/) Every write carries X-Idempotency-Key tied to the confirm tap; a network retry reuses the same key. * (/) Permissions drive visibility: a control the user cannot use is absent or disabled. * (/) Loading, empty, error and offline states are all implemented. * (/) RTL layout is correct and every amount, limit and FX rate is an integer. * (/) No request is made to any path outside the L1 allowlist (enforced by FE-CORE-10). * (/) The PR contains a screenshot or GIF of the journey and names the EP-ID used. * (/) Zero console errors and zero new lint warnings. | F66: apps/warehouse-web | G66: Highest | H66: 3 | J66: EP-WH-A | K66: L1 — Week B | L66: Layer 1 | M66: SP-01 | N66: L1, warehouse, ui | O66: WH-01
A67: 66 | B67: WH-03 | C67: Story | D67: WH-03 — Device login and rejection handling | E67: *Screen:* FE-WH-PIN *API contract:* POST /warehouse/auth/device-login · EP-WH-001 h3. Requirements # Body: { device_token, pin }. # On 200 store the Bearer, persist permissions[] for later layers, show warehouse.name and route to /home. # This path is exempt from the idempotency key per the shared kit. h3. Error handling * 401 → shake the pad and clear the PIN. Never reveal whether the token or the PIN failed. h3. Acceptance criteria * (/) The 401 message is identical regardless of which factor was wrong. * (/) permissions[] is stored even though no screen consumes it in L1. h3. Definition of done * (/) Runs against real staging — no mock data in the merged branch. * (/) HTTP 422 paints the named fields from error.details.{field}, never a generic banner. * (/) Every write carries X-Idempotency-Key tied to the confirm tap; a network retry reuses the same key. * (/) Permissions drive visibility: a control the user cannot use is absent or disabled. * (/) Loading, empty, error and offline states are all implemented. * (/) RTL layout is correct and every amount, limit and FX rate is an integer. * (/) No request is made to any path outside the L1 allowlist (enforced by FE-CORE-10). * (/) The PR contains a screenshot or GIF of the journey and names the EP-ID used. * (/) Zero console errors and zero new lint warnings. | F67: apps/warehouse-web | G67: Highest | H67: 2 | J67: EP-WH-A | K67: L1 — Week B | L67: Layer 1 | M67: SP-01 | N67: L1, warehouse, auth | O67: WH-02
A68: 67 | B68: WH-04 | C68: Story | D68: WH-04 — Empty floor home | E68: *Screen:* FE-WH-HOME *API contract:* — h3. Requirements # Show the warehouse name and copy stating that queues unlock in Layer 3. h3. Acceptance criteria * (/) Zero calls to GET /warehouse/queues. * (/) No to_pick count and no operational figure of any kind. h3. Definition of done * (/) Runs against real staging — no mock data in the merged branch. * (/) HTTP 422 paints the named fields from error.details.{field}, never a generic banner. * (/) Every write carries X-Idempotency-Key tied to the confirm tap; a network retry reuses the same key. * (/) Permissions drive visibility: a control the user cannot use is absent or disabled. * (/) Loading, empty, error and offline states are all implemented. * (/) RTL layout is correct and every amount, limit and FX rate is an integer. * (/) No request is made to any path outside the L1 allowlist (enforced by FE-CORE-10). * (/) The PR contains a screenshot or GIF of the journey and names the EP-ID used. * (/) Zero console errors and zero new lint warnings. | F68: apps/warehouse-web | G68: Medium | H68: 1 | J68: EP-WH-B | K68: L1 — Week B | L68: Layer 1 | M68: SP-01 | N68: L1, warehouse, home | O68: WH-03
A69: 68 | B69: WH-05 | C69: Story | D69: WH-05 — Sign out while keeping the device token | E69: *Screen:* FE-WH-HOME *API contract:* — h3. Requirements # Clear the Bearer only; device_token stays on the machine. h3. Acceptance criteria * (/) Signing back in requires the PIN alone, with no re-provisioning. h3. Definition of done * (/) Runs against real staging — no mock data in the merged branch. * (/) HTTP 422 paints the named fields from error.details.{field}, never a generic banner. * (/) Every write carries X-Idempotency-Key tied to the confirm tap; a network retry reuses the same key. * (/) Permissions drive visibility: a control the user cannot use is absent or disabled. * (/) Loading, empty, error and offline states are all implemented. * (/) RTL layout is correct and every amount, limit and FX rate is an integer. * (/) No request is made to any path outside the L1 allowlist (enforced by FE-CORE-10). * (/) The PR contains a screenshot or GIF of the journey and names the EP-ID used. * (/) Zero console errors and zero new lint warnings. | F69: apps/warehouse-web | G69: High | H69: 1 | J69: EP-WH-B | K69: L1 — Week B | L69: Layer 1 | M69: SP-01 | N69: L1, warehouse, auth | O69: WH-03
A70: 69 | B70: WH-06 | C70: Task | D70: WH-06 — Kiosk mode and connectivity behaviour | E70: *Screen:* FE-WH-PIN *API contract:* — h3. Requirements # Prevent screen sleep, run full screen, enlarge typography for floor distance. # Define explicit behaviour for a long connectivity loss. h3. Acceptance criteria * (/) The terminal stays on the PIN pad without crashing after an extended outage. * (/) Recovery does not require a manual page reload. h3. Definition of done * (/) Runs against real staging — no mock data in the merged branch. * (/) HTTP 422 paints the named fields from error.details.{field}, never a generic banner. * (/) Every write carries X-Idempotency-Key tied to the confirm tap; a network retry reuses the same key. * (/) Permissions drive visibility: a control the user cannot use is absent or disabled. * (/) Loading, empty, error and offline states are all implemented. * (/) RTL layout is correct and every amount, limit and FX rate is an integer. * (/) No request is made to any path outside the L1 allowlist (enforced by FE-CORE-10). * (/) The PR contains a screenshot or GIF of the journey and names the EP-ID used. * (/) Zero console errors and zero new lint warnings. | F70: apps/warehouse-web | G70: Medium | H70: 2 | J70: EP-WH-B | K70: L1 — Week B | L70: Layer 1 | M70: SP-01 | N70: L1, warehouse, kiosk | O70: WH-02
A71: 70 | B71: WH-07 | C71: Task | D71: WH-07 — Acceptance walkthrough and provisioning runbook | E71: *API contract:* — h3. Requirements # Run the walkthrough on a real terminal. # Write a one-page runbook describing how ops plants device_token on a new machine. h3. Acceptance criteria * (/) No queue route exists in the router, verified manually and by the allowlist test. * (/) The runbook is reviewed by the operations team. h3. Definition of done * (/) Runs against real staging — no mock data in the merged branch. * (/) HTTP 422 paints the named fields from error.details.{field}, never a generic banner. * (/) Every write carries X-Idempotency-Key tied to the confirm tap; a network retry reuses the same key. * (/) Permissions drive visibility: a control the user cannot use is absent or disabled. * (/) Loading, empty, error and offline states are all implemented. * (/) RTL layout is correct and every amount, limit and FX rate is an integer. * (/) No request is made to any path outside the L1 allowlist (enforced by FE-CORE-10). * (/) The PR contains a screenshot or GIF of the journey and names the EP-ID used. * (/) Zero console errors and zero new lint warnings. | F71: apps/warehouse-web | G71: High | H71: 1 | J71: EP-WH-B | K71: L1 — Week C | L71: Layer 1 | M71: SP-01 | N71: L1, warehouse, qa, docs | O71: WH-01 WH-02 WH-03 WH-04 WH-05 WH-06
A72: 71 | B72: EP-AD-SHELL | C72: Epic | D72: EP-AD-SHELL — Shell and governing components | E72: *Product:* Platform admin *Covers:* Router, generic table, password confirm, reason modal, dual approval, background jobs *Volume:* 8 issues / 26 points | F72: apps/platform-web | G72: High | I72: EP-AD-SHELL | L72: Layer 1 | M72: SP-01 account · SP-02 IAM · SP-03 refs · SP-04 channels | N72: L1 epic
A73: 72 | B73: EP-AD-ACC | C73: Epic | D73: EP-AD-ACC — SP-01 auth and my account | E73: *Product:* Platform admin *Covers:* Login, 2FA, boot, logout, /me tabs *Volume:* 9 issues / 23 points | F73: apps/platform-web | G73: High | I73: EP-AD-ACC | L73: Layer 1 | M73: SP-01 account · SP-02 IAM · SP-03 refs · SP-04 channels | N73: L1 epic
A74: 73 | B74: EP-AD-IAM | C74: Epic | D74: EP-AD-IAM — SP-02 access and audit | E74: *Product:* Platform admin *Covers:* Permissions, roles, assignments, simulate, inbox, audit, review *Volume:* 15 issues / 42 points | F74: apps/platform-web | G74: High | I74: EP-AD-IAM | L74: Layer 1 | M74: SP-01 account · SP-02 IAM · SP-03 refs · SP-04 channels | N74: L1 epic
A75: 74 | B75: EP-AD-REFS | C75: Epic | D75: EP-AD-REFS — SP-03 references | E75: *Product:* Platform admin *Covers:* Reference factory, seven entities, FX, import *Volume:* 11 issues / 33 points | F75: apps/platform-web | G75: High | I75: EP-AD-REFS | L75: Layer 1 | M75: SP-01 account · SP-02 IAM · SP-03 refs · SP-04 channels | N75: L1 epic
A76: 75 | B76: EP-AD-CH | C76: Epic | D76: EP-AD-CH — SP-04 channels | E76: *Product:* Platform admin *Covers:* List, create and provisioning, card tabs, join applications *Volume:* 21 issues / 62 points | F76: apps/platform-web | G76: High | I76: EP-AD-CH | L76: Layer 1 | M76: SP-01 account · SP-02 IAM · SP-03 refs · SP-04 channels | N76: L1 epic
A77: 76 | B77: AD-00 | C77: Task | D77: AD-00 — Project scaffold and route guards | E77: *API contract:* — h3. Requirements # Register only the routes in the information architecture: /, /channels, /channels/applications, /refs/*, /iam/*, /audit, /me. # Guard every route with can(permission) using the minimum permission from the brief. # Provide one shared internal 403 page. h3. Acceptance criteria * (/) A guarded route shows no content flash before the check resolves. * (/) No /dashboard route exists in the table. h3. Definition of done * (/) Runs against real staging — no mock data in the merged branch. * (/) HTTP 422 paints the named fields from error.details.{field}, never a generic banner. * (/) Every write carries X-Idempotency-Key tied to the confirm tap; a network retry reuses the same key. * (/) Permissions drive visibility: a control the user cannot use is absent or disabled. * (/) Loading, empty, error and offline states are all implemented. * (/) RTL layout is correct and every amount, limit and FX rate is an integer. * (/) No request is made to any path outside the L1 allowlist (enforced by FE-CORE-10). * (/) The PR contains a screenshot or GIF of the journey and names the EP-ID used. * (/) Zero console errors and zero new lint warnings. | F77: apps/platform-web | G77: Highest | H77: 3 | J77: EP-AD-SHELL | K77: L1 — Week A | L77: Layer 1 | M77: SP-01 | N77: L1, platform, setup, routing | O77: FE-CORE-04
A78: 77 | B78: AD-01 | C78: Story | D78: AD-01 — Shell and permission-gated navigation | E78: *API contract:* permissions[] from boot h3. Requirements # Render a nav group only when can(permission) is true: ad.channels.view, ad.refs.view (ad.refs.currency for currencies), ad.iam.view_catalog, ad.audit.view. # Overview at / is available to any signed-in admin and contains no charts. # My account is available to every admin. h3. Acceptance criteria * (/) A group is hidden rather than disabled when the permission is missing. * (/) No operations dashboard item exists and GET /platform/dashboard is never called. h3. Definition of done * (/) Runs against real staging — no mock data in the merged branch. * (/) HTTP 422 paints the named fields from error.details.{field}, never a generic banner. * (/) Every write carries X-Idempotency-Key tied to the confirm tap; a network retry reuses the same key. * (/) Permissions drive visibility: a control the user cannot use is absent or disabled. * (/) Loading, empty, error and offline states are all implemented. * (/) RTL layout is correct and every amount, limit and FX rate is an integer. * (/) No request is made to any path outside the L1 allowlist (enforced by FE-CORE-10). * (/) The PR contains a screenshot or GIF of the journey and names the EP-ID used. * (/) Zero console errors and zero new lint warnings. | F78: apps/platform-web | G78: Highest | H78: 3 | J78: EP-AD-SHELL | K78: L1 — Week B | L78: Layer 1 | M78: SP-01 | N78: L1, platform, shell | O78: AD-00
A79: 78 | B79: AD-02 | C79: Story | D79: AD-02 — Generic table component | E79: *API contract:* page, per_page, sort, search, filter[*] h3. Requirements # Pagination with per_page defaulting to 25 and capped at 100, plus search, sort and filters. # Full table state is reflected in the URL. # Loading, empty and envelope-error states on every list. h3. Acceptance criteria * (/) Changing a filter updates the URL and a reload restores the same view. * (/) Every later list in the product consumes this component. h3. Definition of done * (/) Runs against real staging — no mock data in the merged branch. * (/) HTTP 422 paints the named fields from error.details.{field}, never a generic banner. * (/) Every write carries X-Idempotency-Key tied to the confirm tap; a network retry reuses the same key. * (/) Permissions drive visibility: a control the user cannot use is absent or disabled. * (/) Loading, empty, error and offline states are all implemented. * (/) RTL layout is correct and every amount, limit and FX rate is an integer. * (/) No request is made to any path outside the L1 allowlist (enforced by FE-CORE-10). * (/) The PR contains a screenshot or GIF of the journey and names the EP-ID used. * (/) Zero console errors and zero new lint warnings. | F79: apps/platform-web | G79: Highest | H79: 5 | J79: EP-AD-SHELL | K79: L1 — Week B | L79: Layer 1 | M79: SP-01 | N79: L1, platform, table, shared | O79: FE-CORE-12
A80: 79 | B80: AD-03 | C80: Story | D80: AD-03 — Password confirm modal and request replay | E80: *API contract:* POST /platform/auth/confirm-password · EP-AD-005 h3. Requirements # Trigger on HTTP 403 requires_password_confirm or on a route marked crit. # After confirmation, replay the original request verbatim with the same idempotency key. # The confirmation is valid for fifteen minutes. # This path is exempt from the idempotency key itself. h3. Acceptance criteria * (/) The replay does not create a duplicate operation on the server. * (/) Dismissing the modal does not lose the originating form context. * (/) Expiry after fifteen minutes reopens the modal instead of failing silently. h3. Definition of done * (/) Runs against real staging — no mock data in the merged branch. * (/) HTTP 422 paints the named fields from error.details.{field}, never a generic banner. * (/) Every write carries X-Idempotency-Key tied to the confirm tap; a network retry reuses the same key. * (/) Permissions drive visibility: a control the user cannot use is absent or disabled. * (/) Loading, empty, error and offline states are all implemented. * (/) RTL layout is correct and every amount, limit and FX rate is an integer. * (/) No request is made to any path outside the L1 allowlist (enforced by FE-CORE-10). * (/) The PR contains a screenshot or GIF of the journey and names the EP-ID used. * (/) Zero console errors and zero new lint warnings. | F80: apps/platform-web | G80: Highest | H80: 5 | J80: EP-AD-SHELL | K80: L1 — Week B | L80: Layer 1 | M80: SP-01 | N80: L1, platform, security, shared | O80: FE-CORE-01 FE-CORE-03
A81: 80 | B81: AD-04 | C81: Story | D81: AD-04 — Mandatory reason modal | E81: *API contract:* reason field on ref and channel mutations h3. Requirements # reason is a required field on every mutation where the catalog carries it — not an optional note. # Support a minimum length where the catalog enforces one, for example twenty characters on temp grants. # reason travels in the request body, never as a header. h3. Acceptance criteria * (/) Submitting with an empty reason is impossible from the UI. * (/) The minimum length is enforced before the request is built. h3. Definition of done * (/) Runs against real staging — no mock data in the merged branch. * (/) HTTP 422 paints the named fields from error.details.{field}, never a generic banner. * (/) Every write carries X-Idempotency-Key tied to the confirm tap; a network retry reuses the same key. * (/) Permissions drive visibility: a control the user cannot use is absent or disabled. * (/) Loading, empty, error and offline states are all implemented. * (/) RTL layout is correct and every amount, limit and FX rate is an integer. * (/) No request is made to any path outside the L1 allowlist (enforced by FE-CORE-10). * (/) The PR contains a screenshot or GIF of the journey and names the EP-ID used. * (/) Zero console errors and zero new lint warnings. | F81: apps/platform-web | G81: Highest | H81: 2 | J81: EP-AD-SHELL | K81: L1 — Week C | L81: Layer 1 | M81: SP-01 | N81: L1, platform, shared | O81: AD-03
A82: 81 | B82: AD-05 | C82: Story | D82: AD-05 — Dual-approval and pending-state handler | E82: *API contract:* draft / pending / deletion_request_id responses h3. Requirements # Any response carrying draft, pending or deletion_request_id renders a "Sent for approval" toast with a link to the approval inbox. # The link opens the inbox filtered on the originating request. h3. Acceptance criteria * (/) The UI never shows "Deleted" or "Activated" before the server executes. * (/) The inbox link lands on the correct filtered view. h3. Definition of done * (/) Runs against real staging — no mock data in the merged branch. * (/) HTTP 422 paints the named fields from error.details.{field}, never a generic banner. * (/) Every write carries X-Idempotency-Key tied to the confirm tap; a network retry reuses the same key. * (/) Permissions drive visibility: a control the user cannot use is absent or disabled. * (/) Loading, empty, error and offline states are all implemented. * (/) RTL layout is correct and every amount, limit and FX rate is an integer. * (/) No request is made to any path outside the L1 allowlist (enforced by FE-CORE-10). * (/) The PR contains a screenshot or GIF of the journey and names the EP-ID used. * (/) Zero console errors and zero new lint warnings. | F82: apps/platform-web | G82: Highest | H82: 3 | J82: EP-AD-SHELL | K82: L1 — Week C | L82: Layer 1 | M82: SP-01 | N82: L1, platform, dual-approval, shared | O82: AD-03
A83: 82 | B83: AD-06 | C83: Story | D83: AD-06 — Background job handler | E83: *API contract:* job_id from export and provisioning routes h3. Requirements # Any response carrying job_id renders "Running in the background" and registers the job in a notification or downloads centre. # Never spin on the originating HTTP call. h3. Acceptance criteria * (/) No indefinite spinner is attached to the original request. * (/) Job completion reaches the user without a manual page refresh. h3. Definition of done * (/) Runs against real staging — no mock data in the merged branch. * (/) HTTP 422 paints the named fields from error.details.{field}, never a generic banner. * (/) Every write carries X-Idempotency-Key tied to the confirm tap; a network retry reuses the same key. * (/) Permissions drive visibility: a control the user cannot use is absent or disabled. * (/) Loading, empty, error and offline states are all implemented. * (/) RTL layout is correct and every amount, limit and FX rate is an integer. * (/) No request is made to any path outside the L1 allowlist (enforced by FE-CORE-10). * (/) The PR contains a screenshot or GIF of the journey and names the EP-ID used. * (/) Zero console errors and zero new lint warnings. | F83: apps/platform-web | G83: High | H83: 3 | J83: EP-AD-SHELL | K83: L1 — Week C | L83: Layer 1 | M83: SP-01 | N83: L1, platform, jobs, shared | O83: AD-02
A84: 83 | B84: AD-07 | C84: Story | D84: AD-07 — Export with active filters | E84: *API contract:* Catalog export routes h3. Requirements # Every export sends the active filter set, not the visible page. # page and per_page are never included in an export body. h3. Acceptance criteria * (/) Exporting from page 3 of 40 produces the full filtered result set. h3. Definition of done * (/) Runs against real staging — no mock data in the merged branch. * (/) HTTP 422 paints the named fields from error.details.{field}, never a generic banner. * (/) Every write carries X-Idempotency-Key tied to the confirm tap; a network retry reuses the same key. * (/) Permissions drive visibility: a control the user cannot use is absent or disabled. * (/) Loading, empty, error and offline states are all implemented. * (/) RTL layout is correct and every amount, limit and FX rate is an integer. * (/) No request is made to any path outside the L1 allowlist (enforced by FE-CORE-10). * (/) The PR contains a screenshot or GIF of the journey and names the EP-ID used. * (/) Zero console errors and zero new lint warnings. | F84: apps/platform-web | G84: High | H84: 2 | J84: EP-AD-SHELL | K84: L1 — Week C | L84: Layer 1 | M84: SP-01 | N84: L1, platform, export, shared | O84: AD-02 AD-06
A85: 84 | B85: AD-10 | C85: Story | D85: AD-10 — Login screen | E85: *Screen:* FE-AD-LOGIN *API contract:* POST /platform/auth/login · EP-AD-001 h3. Requirements # Body: { email, password }. # When requires_2fa is returned, route to /login/2fa. # This path is exempt from the idempotency key per the shared kit. h3. Error handling * 401 → generic failure copy. Never reveal whether the email exists. h3. Acceptance criteria * (/) Error copy is identical for unknown email and wrong password. h3. Definition of done * (/) Runs against real staging — no mock data in the merged branch. * (/) HTTP 422 paints the named fields from error.details.{field}, never a generic banner. * (/) Every write carries X-Idempotency-Key tied to the confirm tap; a network retry reuses the same key. * (/) Permissions drive visibility: a control the user cannot use is absent or disabled. * (/) Loading, empty, error and offline states are all implemented. * (/) RTL layout is correct and every amount, limit and FX rate is an integer. * (/) No request is made to any path outside the L1 allowlist (enforced by FE-CORE-10). * (/) The PR contains a screenshot or GIF of the journey and names the EP-ID used. * (/) Zero console errors and zero new lint warnings. | F85: apps/platform-web | G85: Highest | H85: 2 | J85: EP-AD-ACC | K85: L1 — Week B | L85: Layer 1 | M85: SP-01 | N85: L1, platform, auth | O85: AD-00
A86: 85 | B86: AD-11 | C86: Story | D86: AD-11 — TOTP challenge | E86: *Screen:* FE-AD-2FA *API contract:* POST /platform/auth/2fa/verify · EP-AD-002 h3. Requirements # Body: { challenge_token, code }; challenge_token is held in screen memory only, never in long-lived storage. # On 200 store token, user.roles, user.permissions and expires_at, then route to /. h3. Error handling * 401 otp_invalid → error on the code field, no automatic retry. h3. Acceptance criteria * (/) challenge_token is absent from localStorage and from any persistent store. * (/) Reloading the page mid-challenge returns to the login screen. h3. Definition of done * (/) Runs against real staging — no mock data in the merged branch. * (/) HTTP 422 paints the named fields from error.details.{field}, never a generic banner. * (/) Every write carries X-Idempotency-Key tied to the confirm tap; a network retry reuses the same key. * (/) Permissions drive visibility: a control the user cannot use is absent or disabled. * (/) Loading, empty, error and offline states are all implemented. * (/) RTL layout is correct and every amount, limit and FX rate is an integer. * (/) No request is made to any path outside the L1 allowlist (enforced by FE-CORE-10). * (/) The PR contains a screenshot or GIF of the journey and names the EP-ID used. * (/) Zero console errors and zero new lint warnings. | F86: apps/platform-web | G86: Highest | H86: 3 | J86: EP-AD-ACC | K86: L1 — Week B | L86: Layer 1 | M86: SP-01 | N86: L1, platform, auth, 2fa | O86: AD-10
A87: 86 | B87: AD-12 | C87: Story | D87: AD-12 — Boot and admin identity fetch | E87: *Screen:* FE-AD-BOOT *API contract:* GET /platform/auth/me (EP-AD-004) and/or GET /platform/me (EP-AD-159A) h3. Requirements # Fetch identity and permissions on every boot before the navigation is built. # Handle expiry by routing to login without a redirect loop. h3. Acceptance criteria * (/) The navigation does not render before permissions[] arrives. * (/) An expired session produces exactly one redirect. h3. Definition of done * (/) Runs against real staging — no mock data in the merged branch. * (/) HTTP 422 paints the named fields from error.details.{field}, never a generic banner. * (/) Every write carries X-Idempotency-Key tied to the confirm tap; a network retry reuses the same key. * (/) Permissions drive visibility: a control the user cannot use is absent or disabled. * (/) Loading, empty, error and offline states are all implemented. * (/) RTL layout is correct and every amount, limit and FX rate is an integer. * (/) No request is made to any path outside the L1 allowlist (enforced by FE-CORE-10). * (/) The PR contains a screenshot or GIF of the journey and names the EP-ID used. * (/) Zero console errors and zero new lint warnings. | F87: apps/platform-web | G87: Highest | H87: 2 | J87: EP-AD-ACC | K87: L1 — Week B | L87: Layer 1 | M87: SP-01 | N87: L1, platform, session | O87: AD-11
A88: 87 | B88: AD-13 | C88: Story | D88: AD-13 — Logout and storage clear | E88: *Screen:* FE-AD-BOOT *API contract:* POST /platform/auth/logout · EP-AD-003 h3. Requirements # Call logout, then clear all session-bound storage. h3. Acceptance criteria * (/) No token or permission data survives logout. h3. Definition of done * (/) Runs against real staging — no mock data in the merged branch. * (/) HTTP 422 paints the named fields from error.details.{field}, never a generic banner. * (/) Every write carries X-Idempotency-Key tied to the confirm tap; a network retry reuses the same key. * (/) Permissions drive visibility: a control the user cannot use is absent or disabled. * (/) Loading, empty, error and offline states are all implemented. * (/) RTL layout is correct and every amount, limit and FX rate is an integer. * (/) No request is made to any path outside the L1 allowlist (enforced by FE-CORE-10). * (/) The PR contains a screenshot or GIF of the journey and names the EP-ID used. * (/) Zero console errors and zero new lint warnings. | F88: apps/platform-web | G88: High | H88: 1 | J88: EP-AD-ACC | K88: L1 — Week B | L88: Layer 1 | M88: SP-01 | N88: L1, platform, auth | O88: AD-12
... A140: 139 | B140: AD-78 | C140: Story | D140: AD-78 — Channel join applications | E140: *Screen:* FE-AD-CH-APPS *API contract:* GET /platform/channel-applications?filter[status]=under_review h3. Requirements # List applications filtered on under_review. # Decide approve or reject with a reason; approval also carries plan_id and trial_days. # Approval produces a channel in provisioning. h3. Acceptance criteria * (/) An approved application hands off to the AD-65 provisioning path. * (/) Rejection requires a written reason. h3. Definition of done * (/) Runs against real staging — no mock data in the merged branch. * (/) HTTP 422 paints the named fields from error.details.{field}, never a generic banner. * (/) Every write carries X-Idempotency-Key tied to the confirm tap; a network retry reuses the same key. * (/) Permissions drive visibility: a control the user cannot use is absent or disabled. * (/) Loading, empty, error and offline states are all implemented. * (/) RTL layout is correct and every amount, limit and FX rate is an integer. * (/) No request is made to any path outside the L1 allowlist (enforced by FE-CORE-10). * (/) The PR contains a screenshot or GIF of the journey and names the EP-ID used. * (/) Zero console errors and zero new lint warnings. | F140: apps/platform-web | G140: High | H140: 3 | J140: EP-AD-CH | K140: L1 — Week E | L140: Layer 1 | M140: SP-04 | N140: L1, platform, channels, applications | O140: AD-02 AD-65
