Workbook

Sheet Overview
A1: Layer 4 — growth, reporting and launch
A2: Sprints 14 to 18 in DOC-02. Content, notifications, loyalty, reporting, support, platform billing, hardening, the pilot and the general release.
A4: This layer in one line
A5: Deliverable | B5: A pilot with real users in a real zone, then a stable general release.
A6: Sprints | B6: SP-14, SP-15, SP-16, SP-17, SP-18 (DOC-02 §23)
A7: Depends on | B7: Layer 3 (L3-field-operations-backlog.xlsx) — the operational cycle this layer measures and grows.
A8: Followed by | B8: None. This layer ends at the general release.
A9: Read this first | B9: Hardening here is not polish. AC-01 to AC-10 are measured with real users in the street, and a failure on any one of them blocks the pilot rather than being logged for later.
A11: Contents
A12: Epics | B12: The epics of this layer with their volume and sprints.
A13: Backlog | B13: Every issue in this layer, backend and frontend, with full requirements and acceptance criteria readable in place.
A14: Roadmap | B14: Points by sprint and side, and by unit. All figures are live formulas over the Backlog sheet.
A15: Dependencies | B15: One row per blocking link, including links reaching back into earlier layers.
A16: Business Rules | B16: BR-01…BR-20 and REQ-IN-01…08 with the enforcing issue. Rules delivered in this layer are highlighted.
A17: Acceptance Criteria | B17: AC-01…AC-10 from DOC-06 §9.1 with the issues that satisfy each, flagged for this layer.
A18: Data Model | B18: The tables this layer creates.
A19: Events | B19: Inter-module events, with the ones this layer delivers highlighted.
A20: Risks | B20: The risks that bite in this layer, with the mitigating issue.
A21: Jira Import | B21: Flat machine-readable sheet. Save this tab alone as CSV UTF-8 and import.
A23: Contract status — read before importing
A24: The gap | B24: Layer 1 issues carried real EP-IDs because the five frontend briefs named them. The API catalog itself was never provided, so no issue in this workbook carries an endpoint identifier.
A25: What this means | B25: Every issue states behaviour, requirements and acceptance criteria, all traceable to a source document. None states a path. The path must come from the catalog before the issue is pulled.
A26: The rule to keep | B26: No ticket without a contract. Importing is fine; starting an issue while its Contract column reads Proposed is not.
A28: Definition of done — applies to every issue
A29: 1. | B29: Merged after peer review; Larastan level 6, Pint and Rector pass; Deptrac and the architecture suite pass.
A30: 2. | B30: Unit and feature tests green: 90%+ on engines and money paths, 75%+ on endpoints, permissions and isolation.
A31: 3. | B31: Every write carries X-Idempotency-Key unless it is on the documented exemption list.
A32: 4. | B32: Every channel endpoint has an isolation test proving another channel receives 404.
A33: 5. | B33: All amounts, limits and rates are integers; no float exists on any money path.
A34: 6. | B34: Every state transition goes through the lifecycle service and is logged with actor and reason.
A35: 7. | B35: Errors follow the unified envelope and the HTTP status map.
A36: 8. | B36: Mobile work functions correctly with the network disconnected and syncs without loss or duplication.
A37: 9. | B37: The OpenAPI document is regenerated and the typed client still builds.
A38: 10. | B38: Deployed to the test environment and accepted by the product owner.
A40: Totals
A41: Issues in this layer | B41: =COUNTA(Backlog!A2:A37) -> 36
A42: Points in this layer | B42: =SUM(Backlog!L2:L37) -> 206
A43: Backend issues | B43: =COUNTIF(Backlog!B2:B37,"Backend") -> 24
A44: Frontend issues | B44: =COUNTIF(Backlog!B2:B37,"Frontend") -> 12
A45: Epics | B45: =COUNTA(Epics!A2:A60) -> 8
A46: Blocking links | B46: 48
A47: Tables created | B47: 25

Sheet Epics
A1: Epic key | B1: Epic name | C1: Covers | D1: Issues | E1: Points | F1: Sprints
A2: EP-L4-CNT | B2: Content and marketing | C2: Intro, banners, dynamic sliders, algorithms, legal pages | D2: 4 | E2: 19 | F2: SP-14
A3: EP-L4-NTF | B3: Notifications and campaigns | C3: Templates, targeting, scheduling, three channels, delivery log | D3: 3 | E3: 15 | F3: SP-14
A4: EP-L4-LOY | B4: Loyalty | C4: Point rules, tiers, rewards, redemption | D4: 2 | E4: 10 | F4: SP-15
A5: EP-L4-RPT | B5: Reporting | C5: Daily snapshots, dashboards, the nine report families, background export | D5: 4 | E5: 26 | F5: SP-15, SP-16
A6: EP-L4-SUP | B6: Support and platform ops | C6: Tickets, unified search, 360 view, impersonation, system health | D6: 3 | E6: 13 | F6: SP-16
A7: EP-L4-BIL | B7: Platform billing | C7: Plans, subscriptions, platform invoices, dunning | D7: 3 | E7: 18 | F7: SP-17
A8: EP-L4-HRD | B8: Hardening and launch | C8: Performance, security, load, pilot, general release | D8: 6 | E8: 45 | F8: SP-16, SP-17, SP-18
A9: EP-L4-FE | B9: Layer 4 frontend | C9: Growth screens across the five products | D9: 11 | E9: 60 | F9: SP-14, SP-15, SP-16, SP-17

Sheet Backlog
A1: Key | B1: Side | C1: Unit | D1: Title | E1: Epic | F1: Sprint | G1: Tables | H1: Events | I1: Requirements | J1: Acceptance criteria | K1: Out of scope | L1: Points | M1: Priority | N1: Blocked by | O1: Contract
A2: BE4-CNT01 | B2: Backend | C2: Content | D2: Intro and legal pages | E2: EP-L4-CNT | F2: SP-14 | G2: intros, legal_pages | H2: — | I2: 1. Control the opening screen of both apps: enable, welcome text, logo, image or video, display duration. 2. Target a different intro per activity type or per zone. 3. Versioned terms and privacy policy with an acceptance record per user, required for store approval (NEED-C-08). | J2: ☐ A terms change requires re-acceptance and the acceptance is recorded per version. ☐ Disabling the intro takes effect without an app release. | K2: Nothing beyond the epic scope. | L2: 3 | M2: Medium | N2: BE-T04 | O2: Proposed
A3: BE4-CNT02 | B3: Backend | C3: Content | D3: Banners | E3: EP-L4-CNT | F3: SP-14 | G3: banners | H3: — | I3: 1. Media type image, video or GIF; link internal, external or none. 2. Placements: home, root and sub categories, brand pages, offers page, product page. 3. Targeting by activity, zone, retailer group and app; a scheduled date window; order and random weight. 4. Measurement: impressions, clicks and click-through rate. | J3: ☐ A banner outside its window is never served. ☐ Impression and click counts are server side and auditable. | K3: Nothing beyond the epic scope. | L3: 5 | M3: High | N3: BE4-CNT01 | O3: Proposed
A4: BE4-CNT03 | B4: Backend | C4: Content | D4: Dynamic sliders and algorithms | E4: EP-L4-CNT | F4: SP-14 | G4: sliders, slider_items | H4: — | I4: 1. Unlimited sliders with a name, order and placement. 2. Sources: manual selection, brand, category, offer set, or an algorithm. 3. Algorithms: newly arrived, best selling, most ordered by this retailer, suggested for you, similar products, same brand, also bought. 4. The same engine serves the rep app with its own sliders. | J4: ☐ An algorithm slider is personalised per retailer and returns within the list budget. ☐ A slider with no eligible items is omitted rather than rendered empty. | K4: Nothing beyond the epic scope. | L4: 8 | M4: High | N4: BE4-CNT02, BE2-CAT07 | O4: Proposed
A5: BE4-CNT04 | B5: Backend | C5: Content | D5: App version gating | E5: EP-L4-CNT | F5: SP-14 | G5: app_versions | H5: — | I5: 1. A minimum supported version per client; older builds receive 426 upgrade_required. 2. A soft-update notice above the minimum. | J5: ☐ A build below the minimum cannot call any write endpoint. | K5: Nothing beyond the epic scope. | L5: 3 | M5: Medium | N5: BE-C02 | O5: Proposed
A6: BE4-NTF01 | B6: Backend | C6: Notification | D6: Notification model and targeting | E6: EP-L4-NTF | F6: SP-14 | G6: notifications, notification_targets | H6: — | I6: 1. Title, body, icon, optional image and a tap action opening a screen, product, offer or link. 2. Targeting: one user, several users, a retailer group, a zone, a city, an activity type, or everyone (REQ-CM-022). 3. Read notifications are hidden from the counter but never deleted from the log (BR-17). | J6: ☐ A targeted notification reaches exactly the intended audience, verified by count. ☐ Marking as read changes the counter and preserves the record. | K6: Nothing beyond the epic scope. | L6: 5 | M6: High | N6: BE-T02 | O6: Proposed
A7: BE4-NTF02 | B7: Backend | C7: Notification | D7: Automatic event templates | E7: EP-L4-NTF | F7: SP-14 | G7: notification_templates | H7: — | I7: 1. Templates bound to system events: order confirmed, rep on the way, delivered, postponed, an awaited product back in stock, a return decision, a payment falling due, a new offer matching the activity. 2. Send only on a change that matters to the user, without flooding (REQ-CM-023). | J7: ☐ Every state transition that concerns a user produces exactly one notification. ☐ No event produces a notification that requires no action and carries no information. | K7: Nothing beyond the epic scope. | L7: 5 | M7: High | N7: BE4-NTF01, BE2-ORD04 | O7: Proposed
A8: BE4-NTF03 | B8: Backend | C8: Notification | D8: Channels, scheduling and delivery log | E8: EP-L4-NTF | F8: SP-14 | G8: delivery_log | H8: — | I8: 1. Three channels: in-app, push, and optionally WhatsApp for critical events. 2. Immediate or scheduled sending with quiet hours respected. 3. A delivery log per message: sent, delivered, read, failed. | J8: ☐ A failed push is visible in the log and retried within policy. ☐ Quiet hours are honoured for non-critical messages. | K8: Nothing beyond the epic scope. | L8: 5 | M8: Medium | N8: BE4-NTF02, BE-X01 | O8: Proposed
A9: BE4-LOY01 | B9: Backend | C9: Loyalty | D9: Point rules | E9: EP-L4-LOY | F9: SP-15 | G9: loyalty_rules, loyalty_points | H9: — | I9: 1. Retailer earning: purchase value, monthly continuity, on-time payment, rating a rep, trying a new product. 2. Rep earning: order count, on-time delivery rate, collection, new customers, retailer ratings. 3. Points carry an expiry date and every award is a ledger entry. | J9: ☐ The points balance is recomputable from its ledger and always matches. ☐ A reversed order reverses its points. | K9: Nothing beyond the epic scope. | L9: 5 | M9: Medium | N9: BE3-FIN02 | O9: Proposed
A10: BE4-LOY02 | B10: Backend | C10: Loyalty | D10: Tiers and rewards | E10: EP-L4-LOY | F10: SP-15 | G10: loyalty_tiers, rewards, redemptions | H10: — | I10: 1. Bronze, silver and gold tiers with bound privileges: extra discount, delivery priority, exclusive offers. 2. A reward catalog with redemption and a complete history. | J10: ☐ A tier change applies its privileges automatically. ☐ A redemption cannot exceed the available balance under concurrency. | K10: Nothing beyond the epic scope. | L10: 5 | M10: Medium | N10: BE4-LOY01 | O10: Proposed
A11: BE4-RPT01 | B11: Backend | C11: Reporting | D11: Daily snapshots | E11: EP-L4-RPT | F11: SP-15 | G11: daily_snapshots | H11: — | I11: 1. A nightly job materialising the figures the dashboards read, so interactive screens never aggregate live. 2. Snapshots run on the reports queue and never contend with operational work. | J11: ☐ A dashboard screen responds within the interactive budget at production volume. ☐ A snapshot failure is alerted and the previous snapshot is clearly dated. | K11: Nothing beyond the epic scope. | L11: 5 | M11: High | N11: BE3-FIN01 | O11: Proposed
A12: BE4-RPT02 | B12: Backend | C12: Reporting | D12: Channel dashboard figures | E12: EP-L4-RPT | F12: SP-15 | G12: — | H12: — | I12: 1. The indicator set from DOC-01 §4.1 with a selectable period and comparison to the previous period. 2. Actionable alerts: overdue pending orders, items at reorder point, returns awaiting decision, reps over their cash cap, retailers over their credit limit, offers expiring within 48 hours, unassigned scheduled orders. 3. Every card and chart column is drillable to its filtered list. | J12: ☐ No figure exists without a route to its underlying documents. ☐ The alert list is actionable, with a bulk action attached to each type. | K12: Nothing beyond the epic scope. | L12: 8 | M12: High | N12: BE4-RPT01 | O12: Proposed
A13: BE4-RPT03 | B13: Backend | C13: Reporting | D13: The nine report families | E13: EP-L4-RPT | F13: SP-15 | G13: — | H13: — | I13: 1. Sales, products, retailers, reps, zones, inventory, finance, offers and operations. 2. Every report filters, sorts, exports to Excel and PDF, and prints. 3. Heavy reports are generated in the background and delivered by notification. | J13: ☐ Any figure in any report traces back to its originating document (DOC-01 §7). ☐ No report blocks an HTTP request. | K13: Nothing beyond the epic scope. | L13: 8 | M13: Medium | N13: BE4-RPT01 | O13: Proposed
... A37: FE4-QA01 | B37: Frontend | C37: — | D37: Field testing programme | E37: EP-L4-HRD | F37: SP-17 | G37: — | H37: — | I37: 1. Test in the street, in sunlight, while moving, one handed — desk testing does not surface these failures (DOC-06 §9.2). 2. Deliberate connectivity cuts in the middle of financial operations. 3. At least three devices including one low specification; a full working day with a real rep and an observer. 4. A retailer who has never used a similar app, with no prior explanation. 5. Battery and data consumption measured across a full working day. | J37: ☐ Every one of the ten acceptance criteria is measured in the field, not in the office. ☐ The observation log names an owner for every stumble recorded. | K37: Nothing beyond the epic scope. | L37: 8 | M37: Highest | N37: FE3-RT07 | O37: Proposed

Sheet Roadmap
A1: Roadmap — every figure is a live formula over the Backlog sheet
A2: Hardening here is not polish. AC-01 to AC-10 are measured with real users in the street, and a failure on any one of them blocks the pilot rather than being logged for later.
A4: Points by sprint and side
B5: Backend | C5: Frontend | D5: Total
A6: SP-14 | B6: =SUMIFS(Backlog!$L$2:$L$37,Backlog!$F$2:$F$37,"SP-14",Backlog!$B$2:$B$37,"Backend") -> 34 | C6: =SUMIFS(Backlog!$L$2:$L$37,Backlog!$F$2:$F$37,"SP-14",Backlog!$B$2:$B$37,"Frontend") -> 23 | D6: =SUM(B6:C6) -> 57
A7: SP-15 | B7: =SUMIFS(Backlog!$L$2:$L$37,Backlog!$F$2:$F$37,"SP-15",Backlog!$B$2:$B$37,"Backend") -> 31 | C7: =SUMIFS(Backlog!$L$2:$L$37,Backlog!$F$2:$F$37,"SP-15",Backlog!$B$2:$B$37,"Frontend") -> 19 | D7: =SUM(B7:C7) -> 50
A8: SP-16 | B8: =SUMIFS(Backlog!$L$2:$L$37,Backlog!$F$2:$F$37,"SP-16",Backlog!$B$2:$B$37,"Backend") -> 34 | C8: =SUMIFS(Backlog!$L$2:$L$37,Backlog!$F$2:$F$37,"SP-16",Backlog!$B$2:$B$37,"Frontend") -> 13 | D8: =SUM(B8:C8) -> 47
A9: SP-17 | B9: =SUMIFS(Backlog!$L$2:$L$37,Backlog!$F$2:$F$37,"SP-17",Backlog!$B$2:$B$37,"Backend") -> 34 | C9: =SUMIFS(Backlog!$L$2:$L$37,Backlog!$F$2:$F$37,"SP-17",Backlog!$B$2:$B$37,"Frontend") -> 13 | D9: =SUM(B9:C9) -> 47
A10: SP-18 | B10: =SUMIFS(Backlog!$L$2:$L$37,Backlog!$F$2:$F$37,"SP-18",Backlog!$B$2:$B$37,"Backend") -> 5 | C10: =SUMIFS(Backlog!$L$2:$L$37,Backlog!$F$2:$F$37,"SP-18",Backlog!$B$2:$B$37,"Frontend") -> 0 | D10: =SUM(B10:C10) -> 5
A11: Total | B11: =SUM(B6:B10) -> 138 | C11: =SUM(C6:C10) -> 68 | D11: =SUM(D6:D10) -> 206
A14: Issue count by sprint and side
B15: Backend | C15: Frontend | D15: Total
A16: SP-14 | B16: =COUNTIFS(Backlog!$F$2:$F$37,"SP-14",Backlog!$B$2:$B$37,"Backend") -> 7 | C16: =COUNTIFS(Backlog!$F$2:$F$37,"SP-14",Backlog!$B$2:$B$37,"Frontend") -> 4 | D16: =SUM(B16:C16) -> 11
A17: SP-15 | B17: =COUNTIFS(Backlog!$F$2:$F$37,"SP-15",Backlog!$B$2:$B$37,"Backend") -> 5 | C17: =COUNTIFS(Backlog!$F$2:$F$37,"SP-15",Backlog!$B$2:$B$37,"Frontend") -> 4 | D17: =SUM(B17:C17) -> 9
A18: SP-16 | B18: =COUNTIFS(Backlog!$F$2:$F$37,"SP-16",Backlog!$B$2:$B$37,"Backend") -> 6 | C18: =COUNTIFS(Backlog!$F$2:$F$37,"SP-16",Backlog!$B$2:$B$37,"Frontend") -> 2 | D18: =SUM(B18:C18) -> 8
A19: SP-17 | B19: =COUNTIFS(Backlog!$F$2:$F$37,"SP-17",Backlog!$B$2:$B$37,"Backend") -> 5 | C19: =COUNTIFS(Backlog!$F$2:$F$37,"SP-17",Backlog!$B$2:$B$37,"Frontend") -> 2 | D19: =SUM(B19:C19) -> 7
A20: SP-18 | B20: =COUNTIFS(Backlog!$F$2:$F$37,"SP-18",Backlog!$B$2:$B$37,"Backend") -> 1 | C20: =COUNTIFS(Backlog!$F$2:$F$37,"SP-18",Backlog!$B$2:$B$37,"Frontend") -> 0 | D20: =SUM(B20:C20) -> 1
A21: Total | B21: =SUM(B16:B20) -> 24 | C21: =SUM(C16:C20) -> 12 | D21: =SUM(D16:D20) -> 36
A24: Points by sprint and unit
B25: Channel dashboard | C25: Content | D25: Loyalty | E25: Notification | F25: Platform admin | G25: PlatformBilling | H25: Rep app | I25: Reporting | J25: Retailer app | K25: Support | L25: Total
A26: SP-14 | B26: =SUMIFS(Backlog!$L$2:$L$37,Backlog!$F$2:$F$37,"SP-14",Backlog!$C$2:$C$37,"Channel dashboard") -> 13 | C26: =SUMIFS(Backlog!$L$2:$L$37,Backlog!$F$2:$F$37,"SP-14",Backlog!$C$2:$C$37,"Content") -> 19 | D26: =SUMIFS(Backlog!$L$2:$L$37,Backlog!$F$2:$F$37,"SP-14",Backlog!$C$2:$C$37,"Loyalty") -> 0 | E26: =SUMIFS(Backlog!$L$2:$L$37,Backlog!$F$2:$F$37,"SP-14",Backlog!$C$2:$C$37,"Notification") -> 15 | F26: =SUMIFS(Backlog!$L$2:$L$37,Backlog!$F$2:$F$37,"SP-14",Backlog!$C$2:$C$37,"Platform admin") -> 0 | G26: =SUMIFS(Backlog!$L$2:$L$37,Backlog!$F$2:$F$37,"SP-14",Backlog!$C$2:$C$37,"PlatformBilling") -> 0 | H26: =SUMIFS(Backlog!$L$2:$L$37,Backlog!$F$2:$F$37,"SP-14",Backlog!$C$2:$C$37,"Rep app") -> 5 | I26: =SUMIFS(Backlog!$L$2:$L$37,Backlog!$F$2:$F$37,"SP-14",Backlog!$C$2:$C$37,"Reporting") -> 0 | J26: =SUMIFS(Backlog!$L$2:$L$37,Backlog!$F$2:$F$37,"SP-14",Backlog!$C$2:$C$37,"Retailer app") -> 5 | K26: =SUMIFS(Backlog!$L$2:$L$37,Backlog!$F$2:$F$37,"SP-14",Backlog!$C$2:$C$37,"Support") -> 0 | L26: =SUM(B26:K26) -> 57
A27: SP-15 | B27: =SUMIFS(Backlog!$L$2:$L$37,Backlog!$F$2:$F$37,"SP-15",Backlog!$C$2:$C$37,"Channel dashboard") -> 11 | C27: =SUMIFS(Backlog!$L$2:$L$37,Backlog!$F$2:$F$37,"SP-15",Backlog!$C$2:$C$37,"Content") -> 0 | D27: =SUMIFS(Backlog!$L$2:$L$37,Backlog!$F$2:$F$37,"SP-15",Backlog!$C$2:$C$37,"Loyalty") -> 10 | E27: =SUMIFS(Backlog!$L$2:$L$37,Backlog!$F$2:$F$37,"SP-15",Backlog!$C$2:$C$37,"Notification") -> 0 | F27: =SUMIFS(Backlog!$L$2:$L$37,Backlog!$F$2:$F$37,"SP-15",Backlog!$C$2:$C$37,"Platform admin") -> 0 | G27: =SUMIFS(Backlog!$L$2:$L$37,Backlog!$F$2:$F$37,"SP-15",Backlog!$C$2:$C$37,"PlatformBilling") -> 0 | H27: =SUMIFS(Backlog!$L$2:$L$37,Backlog!$F$2:$F$37,"SP-15",Backlog!$C$2:$C$37,"Rep app") -> 3 | I27: =SUMIFS(Backlog!$L$2:$L$37,Backlog!$F$2:$F$37,"SP-15",Backlog!$C$2:$C$37,"Reporting") -> 21 | J27: =SUMIFS(Backlog!$L$2:$L$37,Backlog!$F$2:$F$37,"SP-15",Backlog!$C$2:$C$37,"Retailer app") -> 5 | K27: =SUMIFS(Backlog!$L$2:$L$37,Backlog!$F$2:$F$37,"SP-15",Backlog!$C$2:$C$37,"Support") -> 0 | L27: =SUM(B27:K27) -> 50
A28: SP-16 | B28: =SUMIFS(Backlog!$L$2:$L$37,Backlog!$F$2:$F$37,"SP-16",Backlog!$C$2:$C$37,"Channel dashboard") -> 0 | C28: =SUMIFS(Backlog!$L$2:$L$37,Backlog!$F$2:$F$37,"SP-16",Backlog!$C$2:$C$37,"Content") -> 0 | D28: =SUMIFS(Backlog!$L$2:$L$37,Backlog!$F$2:$F$37,"SP-16",Backlog!$C$2:$C$37,"Loyalty") -> 0 | E28: =SUMIFS(Backlog!$L$2:$L$37,Backlog!$F$2:$F$37,"SP-16",Backlog!$C$2:$C$37,"Notification") -> 0 | F28: =SUMIFS(Backlog!$L$2:$L$37,Backlog!$F$2:$F$37,"SP-16",Backlog!$C$2:$C$37,"Platform admin") -> 13 | G28: =SUMIFS(Backlog!$L$2:$L$37,Backlog!$F$2:$F$37,"SP-16",Backlog!$C$2:$C$37,"PlatformBilling") -> 0 | H28: =SUMIFS(Backlog!$L$2:$L$37,Backlog!$F$2:$F$37,"SP-16",Backlog!$C$2:$C$37,"Rep app") -> 0 | I28: =SUMIFS(Backlog!$L$2:$L$37,Backlog!$F$2:$F$37,"SP-16",Backlog!$C$2:$C$37,"Reporting") -> 5 | J28: =SUMIFS(Backlog!$L$2:$L$37,Backlog!$F$2:$F$37,"SP-16",Backlog!$C$2:$C$37,"Retailer app") -> 0 | K28: =SUMIFS(Backlog!$L$2:$L$37,Backlog!$F$2:$F$37,"SP-16",Backlog!$C$2:$C$37,"Support") -> 13 | L28: =SUM(B28:K28) -> 31
A29: SP-17 | B29: =SUMIFS(Backlog!$L$2:$L$37,Backlog!$F$2:$F$37,"SP-17",Backlog!$C$2:$C$37,"Channel dashboard") -> 0 | C29: =SUMIFS(Backlog!$L$2:$L$37,Backlog!$F$2:$F$37,"SP-17",Backlog!$C$2:$C$37,"Content") -> 0 | D29: =SUMIFS(Backlog!$L$2:$L$37,Backlog!$F$2:$F$37,"SP-17",Backlog!$C$2:$C$37,"Loyalty") -> 0 | E29: =SUMIFS(Backlog!$L$2:$L$37,Backlog!$F$2:$F$37,"SP-17",Backlog!$C$2:$C$37,"Notification") -> 0 | F29: =SUMIFS(Backlog!$L$2:$L$37,Backlog!$F$2:$F$37,"SP-17",Backlog!$C$2:$C$37,"Platform admin") -> 5 | G29: =SUMIFS(Backlog!$L$2:$L$37,Backlog!$F$2:$F$37,"SP-17",Backlog!$C$2:$C$37,"PlatformBilling") -> 18 | H29: =SUMIFS(Backlog!$L$2:$L$37,Backlog!$F$2:$F$37,"SP-17",Backlog!$C$2:$C$37,"Rep app") -> 0 | I29: =SUMIFS(Backlog!$L$2:$L$37,Backlog!$F$2:$F$37,"SP-17",Backlog!$C$2:$C$37,"Reporting") -> 0 | J29: =SUMIFS(Backlog!$L$2:$L$37,Backlog!$F$2:$F$37,"SP-17",Backlog!$C$2:$C$37,"Retailer app") -> 0 | K29: =SUMIFS(Backlog!$L$2:$L$37,Backlog!$F$2:$F$37,"SP-17",Backlog!$C$2:$C$37,"Support") -> 0 | L29: =SUM(B29:K29) -> 23
A30: SP-18 | B30: =SUMIFS(Backlog!$L$2:$L$37,Backlog!$F$2:$F$37,"SP-18",Backlog!$C$2:$C$37,"Channel dashboard") -> 0 | C30: =SUMIFS(Backlog!$L$2:$L$37,Backlog!$F$2:$F$37,"SP-18",Backlog!$C$2:$C$37,"Content") -> 0 | D30: =SUMIFS(Backlog!$L$2:$L$37,Backlog!$F$2:$F$37,"SP-18",Backlog!$C$2:$C$37,"Loyalty") -> 0 | E30: =SUMIFS(Backlog!$L$2:$L$37,Backlog!$F$2:$F$37,"SP-18",Backlog!$C$2:$C$37,"Notification") -> 0 | F30: =SUMIFS(Backlog!$L$2:$L$37,Backlog!$F$2:$F$37,"SP-18",Backlog!$C$2:$C$37,"Platform admin") -> 0 | G30: =SUMIFS(Backlog!$L$2:$L$37,Backlog!$F$2:$F$37,"SP-18",Backlog!$C$2:$C$37,"PlatformBilling") -> 0 | H30: =SUMIFS(Backlog!$L$2:$L$37,Backlog!$F$2:$F$37,"SP-18",Backlog!$C$2:$C$37,"Rep app") -> 0 | I30: =SUMIFS(Backlog!$L$2:$L$37,Backlog!$F$2:$F$37,"SP-18",Backlog!$C$2:$C$37,"Reporting") -> 0 | J30: =SUMIFS(Backlog!$L$2:$L$37,Backlog!$F$2:$F$37,"SP-18",Backlog!$C$2:$C$37,"Retailer app") -> 0 | K30: =SUMIFS(Backlog!$L$2:$L$37,Backlog!$F$2:$F$37,"SP-18",Backlog!$C$2:$C$37,"Support") -> 0 | L30: =SUM(B30:K30) -> 0
A31: Total | B31: =SUM(B26:B30) -> 24 | C31: =SUM(C26:C30) -> 19 | D31: =SUM(D26:D30) -> 10 | E31: =SUM(E26:E30) -> 15 | F31: =SUM(F26:F30) -> 18 | G31: =SUM(G26:G30) -> 18 | H31: =SUM(H26:H30) -> 8 | I31: =SUM(I26:I30) -> 26 | ... L31: =SUM(L26:L30) -> 161

Sheet Dependencies
A1: Blocker | B1: Blocker title | C1: Blocker layer | D1: Blocker sprint | E1: Blocked | F1: Blocked title | G1: Blocked sprint | H1: From earlier layer
A2: BE-A07 | B2: Bulk role assignment | C2: L1 | D2: SP-02 | E2: BE4-BIL03 | F2: Platform team management | G2: SP-17 | H2: Yes
A3: BE-A16 | B3: Two-level authorisation enforcement | C3: L1 | D3: SP-02 | E3: BE4-SUP01 | F3: Tickets and unified search | G3: SP-16 | H3: Yes
A4: BE-C02 | B4: Error handler and HTTP status map | C4: L1 | D4: SP-00 | E4: BE4-CNT04 | F4: App version gating | G4: SP-14 | H4: Yes
A5: BE-C04 | B5: Immutable audit log | C5: L1 | D5: SP-00 | E5: BE4-SUP02 | F5: Impersonation with guardrails | G5: SP-16 | H5: Yes
A6: BE-C05 | B6: Generic dual-approval mechanism | C6: L1 | D6: SP-00 | E6: BE4-SUP02 | F6: Impersonation with guardrails | G6: SP-16 | H6: Yes
A7: BE-F07 | B7: Queues and Horizon | C7: L1 | D7: SP-00 | E7: BE4-SUP03 | F7: System health view | G7: SP-16 | H7: Yes
A8: BE-Q04 | B8: Authorisation bypass test suite | C8: L1 | D8: SP-02 | E8: BE4-HRD02 | F8: Security hardening and penetration pass | G8: SP-16 | H8: Yes
A9: BE-T02 | B9: Tenant isolation: trait, scope and 404 policy | C9: L1 | D9: SP-04 | E9: BE4-NTF01 | F9: Notification model and targeting | G9: SP-14 | H9: Yes
A10: BE-T03 | B10: Tenant isolation test suite | C10: L1 | D10: SP-04 | E10: BE4-HRD02 | F10: Security hardening and penetration pass | G10: SP-16 | H10: Yes
A11: BE-T04 | B11: Create channel | C11: L1 | D11: SP-04 | E11: BE4-CNT01 | F11: Intro and legal pages | G11: SP-14 | H11: Yes
A12: BE-T12 | B12: Limits, overrides and plan enforcement | C12: L1 | D12: SP-04 | E12: BE4-BIL01 | F12: Plans and subscriptions | G12: SP-17 | H12: Yes
... A49: FE3-RT07 | B49: Offline engine in the rep app | C49: L3 | D49: SP-12 | E49: FE4-QA01 | F49: Field testing programme | G49: SP-17 | H49: Yes

Sheet Business Rules
A1: Rule | B1: Statement | C1: Owning module | D1: Enforcing issue | E1: In this layer
A2: BR-01 | B2: A multi-channel order is split automatically at submission into independent sub-orders, each with its own number, invoice, route and rep. | C2: Ordering | D2: BE2-ORD03 | E2: No
A3: BR-02 | B3: The supply channel name is not disclosed to the retailer before the sub-order is confirmed. | C3: Ordering / Core | D3: BE2-ORD08 · BE2-ORD02 | E3: No
A4: BR-03 | B4: The rep name and phone are not disclosed before the order reaches on_the_way. | C4: Delivery | D4: BE2-ORD08 · FE3-RT01 | E4: No
A5: BR-04 | B5: The price is frozen on the order at submission and is unaffected by any later price-list change. | C5: Pricing | D5: BE2-PRC05 | E5: No
A6: BR-05 | B6: Stock reservation starts at confirmation; the actual deduction happens at handover to the rep. | C6: Inventory | D6: BE3-INV02 | E6: No
A7: BR-06 | B7: Cancellation by the retailer is permitted in the pending state only. | C7: Ordering | D7: BE2-ORD04 | E7: No
A8: BR-07 | B8: The cart is emptied automatically after a successful submission and held locally before it. | C8: Ordering | D8: BE2-ORD01 · FE2-RT11 | E8: No
A9: BR-08 | B9: A composite offer is indivisible on add, remove and return. | C9: Promotion | D9: BE2-PRM04 | E9: No
A10: BR-09 | B10: An invoice discount applies only to the portion of the multi-channel order belonging to that channel. | C10: Promotion / Finance | D10: BE2-PRM01 | E10: No
A11: BR-10 | B11: A posted invoice cannot be edited; corrections are made by a linked credit or debit note. | C11: Finance | D11: BE3-FIN01 | E11: No
A12: BR-11 | B12: Every payment is documented by a unique receipt number shared between the rep and retailer apps to prevent double entry. | C12: Finance / Core | D12: BE3-FIN02 | E12: No
... A29: REQ-IN-08 | B29: The multi-channel split happens on the server at submission; the retailer sees one order and each channel sees only its part. | C29: Ordering | D29: BE2-ORD03 | E29: No

Sheet Acceptance Criteria
A1: Code | B1: Criterion | C1: How it is measured | D1: Satisfied by | E1: In this layer
A2: AC-01 | B2: A new user completes registration in under sixty seconds. | C2: Timed with five real users who have never seen the app. | D2: RT-18 · RP-10 (L1) · BE4-HRD03 | E2: Yes
A3: AC-02 | B3: A retailer submits an order in three to four taps. | C3: Tap count from home to the success screen. | D3: FE2-RT03 · FE2-RT11 · BE4-HRD03 | E3: Yes
A4: AC-03 | B4: A rep captures an order in under thirty seconds. | C4: Timed in the field with real reps inside real shops. | D4: FE3-RP02 · FE4-QA01 | E4: Yes
A5: AC-04 | B5: Value is understood within ten seconds. | C5: Ask a retailer what they understood from this screen. | D5: FE2-RT01 · FE4-QA01 | E5: Yes
A6: AC-05 | B6: Zero lost or duplicated operations after sync. | C6: A full working day offline with deliberate interruptions and resends. | D6: BE3-SYN01 · BE3-SYN03 · FE3-RT06 · FE3-RT07 | E6: No
A7: AC-06 | B7: The rep wallet equals collections minus settlements at any instant. | C7: Reconciliation against the wallet ledger. | D7: BE3-FIN04 · FE3-RP10 | E7: No
A8: AC-07 | B8: The retailer statement equals invoices minus payments minus returns. | C8: Reconciliation against the finance ledger. | D8: BE3-FIN03 · FE3-RT05 | E8: No
A9: AC-08 | B9: The channel identity cannot be revealed before confirmation, nor the rep before departure. | C9: Inspect the API responses directly, not the UI. | D9: BE2-ORD08 · BE4-HRD02 | E9: Yes
A10: AC-09 | B10: Conditional offers compute correctly. | C10: Every offer type tested in the cart and on the final invoice. | D10: BE2-PRM03 · FE2-CH06 | E10: No
A11: AC-10 | B11: Acceptable performance on a weak device. | C11: Startup and home load on 2GB RAM over 3G. | D11: BE2-CAT05 · BE4-HRD01 · FE4-QA01 | E11: Yes

Sheet Data Model
A1: Module | B1: Table | C1: Created by issue | D1: Sprint | E1: Side
A2: Content | B2: app_versions | C2: BE4-CNT04 | D2: SP-14 | E2: Backend
A3: Content | B3: banners | C3: BE4-CNT02 | D3: SP-14 | E3: Backend
A4: Content | B4: intros | C4: BE4-CNT01 | D4: SP-14 | E4: Backend
A5: Content | B5: legal_pages | C5: BE4-CNT01 | D5: SP-14 | E5: Backend
A6: Content | B6: slider_items | C6: BE4-CNT03 | D6: SP-14 | E6: Backend
A7: Content | B7: sliders | C7: BE4-CNT03 | D7: SP-14 | E7: Backend
A8: Loyalty | B8: loyalty_points | C8: BE4-LOY01 | D8: SP-15 | E8: Backend
A9: Loyalty | B9: loyalty_rules | C9: BE4-LOY01 | D9: SP-15 | E9: Backend
A10: Loyalty | B10: loyalty_tiers | C10: BE4-LOY02 | D10: SP-15 | E10: Backend
A11: Loyalty | B11: redemptions | C11: BE4-LOY02 | D11: SP-15 | E11: Backend
A12: Loyalty | B12: rewards | C12: BE4-LOY02 | D12: SP-15 | E12: Backend
... A26: Support | B26: tickets | C26: BE4-SUP01 | D26: SP-16 | E26: Backend

Sheet Events
A1: Event | B1: Emitted by | C1: Listened to by | D1: Effect | E1: Delivered in | F1: Issue
A2: ChannelStatusChanged | B2: Tenancy | C2: Ordering, Notification, Reporting | D2: Freezes new orders only (BR-AD-14) | E2: L1 | F2: BE-T01 (L1)
A3: ReferenceDisabled | B3: Reference | C3: Catalog, Tenancy, Ordering | D3: Blocks new use without touching existing records | E3: L1 | F3: BE-R01 (L1)
A4: OrderSubmitted | B4: Ordering | C4: Inventory, Notification, Reporting | D4: No reservation yet — channel notification only | E4: Layer 2 | F4: BE2-ORD03
A5: SubOrderConfirmed | B5: Ordering | C5: Inventory, Fulfillment, Notification | D5: Reserve stock and create the picking list (BR-05) | E5: Layer 2 | F5: BE2-ORD06
A6: HandoverCompleted | B6: Fulfillment | C6: Inventory, Ordering, Notification | D6: Actual stock deduction and the on_the_way state | E6: Layer 3 | F6: BE3-FUL04
A7: DeliveryCompleted | B7: Delivery | C7: Finance, Loyalty, Notification | D7: Generate the invoice, create the receivable, award points | E7: Layer 3 | F7: BE3-DLV03
A8: PaymentRecorded | B8: Finance | C8: Finance/Wallet, Notification, Reporting | D8: Increase the rep wallet and reduce the retailer receivable | E8: Layer 3 | F8: BE3-FIN02
A9: ReturnApproved | B9: Returns | C9: Finance, Inventory | D9: Credit note plus stock return according to condition | E9: Layer 3 | F9: BE3-RET02
A10: PriceListChanged | B10: Pricing | C10: Sync, Reporting | D10: Marks data for differential sync; never touches a live order | E10: Layer 2 | F10: BE2-PRC01

Sheet Risks
A1: # | B1: Risk | C1: Impact | D1: Consequence | E1: Mitigation | F1: Owning issue
A2: 1 | B2: Reps reject the app fearing it will replace them. | C2: Critical | D2: The whole system stops, because the rep is the only execution link. | E2: Involve real reps in design early and lead with what is theirs: wallet, points, ratings, less paperwork. | F2: FE3-RP10 · FE4-RP02
A3: 5 | B3: Incomplete catalog or stale prices at launch. | C3: High | D3: Retailer trust collapses on the first wrong price. | E3: Launch condition: a complete catalog with current prices for the pilot zone. | F3: BE4-HRD04
A4: 6 | B4: The order capture screen grows until it breaks the thirty-second rule. | C4: High | D4: The rep abandons the app and returns to paper. | E4: Measure the time every sprint, not at the end, and refuse any addition that increases it. | F4: FE3-RP02 · FE4-QA01
A5: 8 | B5: High battery consumption on the rep device. | C5: Medium | D5: The phone dies mid-round and the round is lost. | E5: Reduce location pings while stationary, batch uploads, measure consumption in field testing. | F5: BE3-DLV04 · FE4-QA01
A6: 11 | B6: Reporting aggregation slows the operational database. | C6: Medium | D6: Daily screens degrade because someone opened a report. | E6: Nightly snapshots on the reports queue; dashboards read snapshots, never live aggregates. | F6: BE4-RPT01
A7: 12 | B7: Issues start before their endpoints exist in the API catalog. | C7: High | D7: The exact failure Layer 1 was designed to prevent: screens built against invented contracts. | E7: The Contract column stays Proposed until the catalog is published; no issue is pulled while it reads Proposed. | F7: Every issue in this workbook

Sheet Jira Import
A1: Issue ID | B1: Issue Key | C1: Issue Type | D1: Summary | E1: Description | F1: Component/s | G1: Priority | H1: Story Points | I1: Epic Name | J1: Epic Link | K1: Sprint | L1: Fix Version/s | M1: Labels | N1: Blocked By
A2: 1 | B2: EP-L4-CNT | C2: Epic | D2: EP-L4-CNT — Content and marketing | E2: *Layer:* L4 *Covers:* Intro, banners, dynamic sliders, algorithms, legal pages *Volume:* 4 issues / 19 points | F2: l4 | G2: High | I2: EP-L4-CNT | L2: L4 | M2: l4 epic
A3: 2 | B3: EP-L4-NTF | C3: Epic | D3: EP-L4-NTF — Notifications and campaigns | E3: *Layer:* L4 *Covers:* Templates, targeting, scheduling, three channels, delivery log *Volume:* 3 issues / 15 points | F3: l4 | G3: High | I3: EP-L4-NTF | L3: L4 | M3: l4 epic
A4: 3 | B4: EP-L4-LOY | C4: Epic | D4: EP-L4-LOY — Loyalty | E4: *Layer:* L4 *Covers:* Point rules, tiers, rewards, redemption *Volume:* 2 issues / 10 points | F4: l4 | G4: High | I4: EP-L4-LOY | L4: L4 | M4: l4 epic
A5: 4 | B5: EP-L4-RPT | C5: Epic | D5: EP-L4-RPT — Reporting | E5: *Layer:* L4 *Covers:* Daily snapshots, dashboards, the nine report families, background export *Volume:* 4 issues / 26 points | F5: l4 | G5: High | I5: EP-L4-RPT | L5: L4 | M5: l4 epic
A6: 5 | B6: EP-L4-SUP | C6: Epic | D6: EP-L4-SUP — Support and platform ops | E6: *Layer:* L4 *Covers:* Tickets, unified search, 360 view, impersonation, system health *Volume:* 3 issues / 13 points | F6: l4 | G6: High | I6: EP-L4-SUP | L6: L4 | M6: l4 epic
A7: 6 | B7: EP-L4-BIL | C7: Epic | D7: EP-L4-BIL — Platform billing | E7: *Layer:* L4 *Covers:* Plans, subscriptions, platform invoices, dunning *Volume:* 3 issues / 18 points | F7: l4 | G7: High | I7: EP-L4-BIL | L7: L4 | M7: l4 epic
A8: 7 | B8: EP-L4-HRD | C8: Epic | D8: EP-L4-HRD — Hardening and launch | E8: *Layer:* L4 *Covers:* Performance, security, load, pilot, general release *Volume:* 6 issues / 45 points | F8: l4 | G8: High | I8: EP-L4-HRD | L8: L4 | M8: l4 epic
A9: 8 | B9: EP-L4-FE | C9: Epic | D9: EP-L4-FE — Layer 4 frontend | E9: *Layer:* L4 *Covers:* Growth screens across the five products *Volume:* 11 issues / 60 points | F9: l4 | G9: High | I9: EP-L4-FE | L9: L4 | M9: l4 epic
A10: 9 | B10: BE4-CNT01 | C10: Story | D10: BE4-CNT01 — Intro and legal pages | E10: *Side:* Backend *Unit:* Content *Sprint:* SP-14 *Contract status:* Proposed — endpoints must be fixed in the API catalog before this issue is pulled. *Tables:* intros, legal_pages h3. Requirements # Control the opening screen of both apps: enable, welcome text, logo, image or video, display duration. # Target a different intro per activity type or per zone. # Versioned terms and privacy policy with an acceptance record per user, required for store approval (NEED-C-08). h3. Acceptance criteria * (/) A terms change requires re-acceptance and the acceptance is recorded per version. * (/) Disabling the intro takes effect without an app release. h3. Definition of done * (/) Merged after peer review; Larastan level 6, Pint and Rector pass; Deptrac and the architecture suite pass. * (/) Unit and feature tests green: 90%+ on engines and money paths, 75%+ on endpoints, permissions and isolation. * (/) Every write carries X-Idempotency-Key unless it is on the documented exemption list. * (/) Every channel endpoint has an isolation test proving another channel receives 404. * (/) All amounts, limits and rates are integers; no float exists on any money path. * (/) Every state transition goes through the lifecycle service and is logged with actor and reason. * (/) Errors follow the unified envelope and the HTTP status map. * (/) Mobile work functions correctly with the network disconnected and syncs without loss or duplication. * (/) The OpenAPI document is regenerated and the typed client still builds. * (/) Deployed to the test environment and accepted by the product owner. | F10: Content | G10: Medium | H10: 3 | J10: EP-L4-CNT | K10: SP-14 | L10: L4 | M10: l4, backend, sp-14
A11: 10 | B11: BE4-CNT02 | C11: Story | D11: BE4-CNT02 — Banners | E11: *Side:* Backend *Unit:* Content *Sprint:* SP-14 *Contract status:* Proposed — endpoints must be fixed in the API catalog before this issue is pulled. *Tables:* banners h3. Requirements # Media type image, video or GIF; link internal, external or none. # Placements: home, root and sub categories, brand pages, offers page, product page. # Targeting by activity, zone, retailer group and app; a scheduled date window; order and random weight. # Measurement: impressions, clicks and click-through rate. h3. Acceptance criteria * (/) A banner outside its window is never served. * (/) Impression and click counts are server side and auditable. h3. Definition of done * (/) Merged after peer review; Larastan level 6, Pint and Rector pass; Deptrac and the architecture suite pass. * (/) Unit and feature tests green: 90%+ on engines and money paths, 75%+ on endpoints, permissions and isolation. * (/) Every write carries X-Idempotency-Key unless it is on the documented exemption list. * (/) Every channel endpoint has an isolation test proving another channel receives 404. * (/) All amounts, limits and rates are integers; no float exists on any money path. * (/) Every state transition goes through the lifecycle service and is logged with actor and reason. * (/) Errors follow the unified envelope and the HTTP status map. * (/) Mobile work functions correctly with the network disconnected and syncs without loss or duplication. * (/) The OpenAPI document is regenerated and the typed client still builds. * (/) Deployed to the test environment and accepted by the product owner. | F11: Content | G11: High | H11: 5 | J11: EP-L4-CNT | K11: SP-14 | L11: L4 | M11: l4, backend, sp-14 | N11: 9
A12: 11 | B12: BE4-CNT03 | C12: Story | D12: BE4-CNT03 — Dynamic sliders and algorithms | E12: *Side:* Backend *Unit:* Content *Sprint:* SP-14 *Contract status:* Proposed — endpoints must be fixed in the API catalog before this issue is pulled. *Tables:* sliders, slider_items h3. Requirements # Unlimited sliders with a name, order and placement. # Sources: manual selection, brand, category, offer set, or an algorithm. # Algorithms: newly arrived, best selling, most ordered by this retailer, suggested for you, similar products, same brand, also bought. # The same engine serves the rep app with its own sliders. h3. Acceptance criteria * (/) An algorithm slider is personalised per retailer and returns within the list budget. * (/) A slider with no eligible items is omitted rather than rendered empty. h3. Definition of done * (/) Merged after peer review; Larastan level 6, Pint and Rector pass; Deptrac and the architecture suite pass. * (/) Unit and feature tests green: 90%+ on engines and money paths, 75%+ on endpoints, permissions and isolation. * (/) Every write carries X-Idempotency-Key unless it is on the documented exemption list. * (/) Every channel endpoint has an isolation test proving another channel receives 404. * (/) All amounts, limits and rates are integers; no float exists on any money path. * (/) Every state transition goes through the lifecycle service and is logged with actor and reason. * (/) Errors follow the unified envelope and the HTTP status map. * (/) Mobile work functions correctly with the network disconnected and syncs without loss or duplication. * (/) The OpenAPI document is regenerated and the typed client still builds. * (/) Deployed to the test environment and accepted by the product owner. | F12: Content | G12: High | H12: 8 | J12: EP-L4-CNT | K12: SP-14 | L12: L4 | M12: l4, backend, sp-14 | N12: 10
A13: 12 | B13: BE4-CNT04 | C13: Story | D13: BE4-CNT04 — App version gating | E13: *Side:* Backend *Unit:* Content *Sprint:* SP-14 *Contract status:* Proposed — endpoints must be fixed in the API catalog before this issue is pulled. *Tables:* app_versions h3. Requirements # A minimum supported version per client; older builds receive 426 upgrade_required. # A soft-update notice above the minimum. h3. Acceptance criteria * (/) A build below the minimum cannot call any write endpoint. h3. Definition of done * (/) Merged after peer review; Larastan level 6, Pint and Rector pass; Deptrac and the architecture suite pass. * (/) Unit and feature tests green: 90%+ on engines and money paths, 75%+ on endpoints, permissions and isolation. * (/) Every write carries X-Idempotency-Key unless it is on the documented exemption list. * (/) Every channel endpoint has an isolation test proving another channel receives 404. * (/) All amounts, limits and rates are integers; no float exists on any money path. * (/) Every state transition goes through the lifecycle service and is logged with actor and reason. * (/) Errors follow the unified envelope and the HTTP status map. * (/) Mobile work functions correctly with the network disconnected and syncs without loss or duplication. * (/) The OpenAPI document is regenerated and the typed client still builds. * (/) Deployed to the test environment and accepted by the product owner. | F13: Content | G13: Medium | H13: 3 | J13: EP-L4-CNT | K13: SP-14 | L13: L4 | M13: l4, backend, sp-14
A14: 13 | B14: BE4-NTF01 | C14: Story | D14: BE4-NTF01 — Notification model and targeting | E14: *Side:* Backend *Unit:* Notification *Sprint:* SP-14 *Contract status:* Proposed — endpoints must be fixed in the API catalog before this issue is pulled. *Tables:* notifications, notification_targets h3. Requirements # Title, body, icon, optional image and a tap action opening a screen, product, offer or link. # Targeting: one user, several users, a retailer group, a zone, a city, an activity type, or everyone (REQ-CM-022). # Read notifications are hidden from the counter but never deleted from the log (BR-17). h3. Acceptance criteria * (/) A targeted notification reaches exactly the intended audience, verified by count. * (/) Marking as read changes the counter and preserves the record. h3. Definition of done * (/) Merged after peer review; Larastan level 6, Pint and Rector pass; Deptrac and the architecture suite pass. * (/) Unit and feature tests green: 90%+ on engines and money paths, 75%+ on endpoints, permissions and isolation. * (/) Every write carries X-Idempotency-Key unless it is on the documented exemption list. * (/) Every channel endpoint has an isolation test proving another channel receives 404. * (/) All amounts, limits and rates are integers; no float exists on any money path. * (/) Every state transition goes through the lifecycle service and is logged with actor and reason. * (/) Errors follow the unified envelope and the HTTP status map. * (/) Mobile work functions correctly with the network disconnected and syncs without loss or duplication. * (/) The OpenAPI document is regenerated and the typed client still builds. * (/) Deployed to the test environment and accepted by the product owner. | F14: Notification | G14: High | H14: 5 | J14: EP-L4-NTF | K14: SP-14 | L14: L4 | M14: l4, backend, sp-14
A15: 14 | B15: BE4-NTF02 | C15: Story | D15: BE4-NTF02 — Automatic event templates | E15: *Side:* Backend *Unit:* Notification *Sprint:* SP-14 *Contract status:* Proposed — endpoints must be fixed in the API catalog before this issue is pulled. *Tables:* notification_templates h3. Requirements # Templates bound to system events: order confirmed, rep on the way, delivered, postponed, an awaited product back in stock, a return decision, a payment falling due, a new offer matching the activity. # Send only on a change that matters to the user, without flooding (REQ-CM-023). h3. Acceptance criteria * (/) Every state transition that concerns a user produces exactly one notification. * (/) No event produces a notification that requires no action and carries no information. h3. Definition of done * (/) Merged after peer review; Larastan level 6, Pint and Rector pass; Deptrac and the architecture suite pass. * (/) Unit and feature tests green: 90%+ on engines and money paths, 75%+ on endpoints, permissions and isolation. * (/) Every write carries X-Idempotency-Key unless it is on the documented exemption list. * (/) Every channel endpoint has an isolation test proving another channel receives 404. * (/) All amounts, limits and rates are integers; no float exists on any money path. * (/) Every state transition goes through the lifecycle service and is logged with actor and reason. * (/) Errors follow the unified envelope and the HTTP status map. * (/) Mobile work functions correctly with the network disconnected and syncs without loss or duplication. * (/) The OpenAPI document is regenerated and the typed client still builds. * (/) Deployed to the test environment and accepted by the product owner. | F15: Notification | G15: High | H15: 5 | J15: EP-L4-NTF | K15: SP-14 | L15: L4 | M15: l4, backend, sp-14 | N15: 13
A16: 15 | B16: BE4-NTF03 | C16: Story | D16: BE4-NTF03 — Channels, scheduling and delivery log | E16: *Side:* Backend *Unit:* Notification *Sprint:* SP-14 *Contract status:* Proposed — endpoints must be fixed in the API catalog before this issue is pulled. *Tables:* delivery_log h3. Requirements # Three channels: in-app, push, and optionally WhatsApp for critical events. # Immediate or scheduled sending with quiet hours respected. # A delivery log per message: sent, delivered, read, failed. h3. Acceptance criteria * (/) A failed push is visible in the log and retried within policy. * (/) Quiet hours are honoured for non-critical messages. h3. Definition of done * (/) Merged after peer review; Larastan level 6, Pint and Rector pass; Deptrac and the architecture suite pass. * (/) Unit and feature tests green: 90%+ on engines and money paths, 75%+ on endpoints, permissions and isolation. * (/) Every write carries X-Idempotency-Key unless it is on the documented exemption list. * (/) Every channel endpoint has an isolation test proving another channel receives 404. * (/) All amounts, limits and rates are integers; no float exists on any money path. * (/) Every state transition goes through the lifecycle service and is logged with actor and reason. * (/) Errors follow the unified envelope and the HTTP status map. * (/) Mobile work functions correctly with the network disconnected and syncs without loss or duplication. * (/) The OpenAPI document is regenerated and the typed client still builds. * (/) Deployed to the test environment and accepted by the product owner. | F16: Notification | G16: Medium | H16: 5 | J16: EP-L4-NTF | K16: SP-14 | L16: L4 | M16: l4, backend, sp-14 | N16: 14
A17: 16 | B17: BE4-LOY01 | C17: Story | D17: BE4-LOY01 — Point rules | E17: *Side:* Backend *Unit:* Loyalty *Sprint:* SP-15 *Contract status:* Proposed — endpoints must be fixed in the API catalog before this issue is pulled. *Tables:* loyalty_rules, loyalty_points h3. Requirements # Retailer earning: purchase value, monthly continuity, on-time payment, rating a rep, trying a new product. # Rep earning: order count, on-time delivery rate, collection, new customers, retailer ratings. # Points carry an expiry date and every award is a ledger entry. h3. Acceptance criteria * (/) The points balance is recomputable from its ledger and always matches. * (/) A reversed order reverses its points. h3. Definition of done * (/) Merged after peer review; Larastan level 6, Pint and Rector pass; Deptrac and the architecture suite pass. * (/) Unit and feature tests green: 90%+ on engines and money paths, 75%+ on endpoints, permissions and isolation. * (/) Every write carries X-Idempotency-Key unless it is on the documented exemption list. * (/) Every channel endpoint has an isolation test proving another channel receives 404. * (/) All amounts, limits and rates are integers; no float exists on any money path. * (/) Every state transition goes through the lifecycle service and is logged with actor and reason. * (/) Errors follow the unified envelope and the HTTP status map. * (/) Mobile work functions correctly with the network disconnected and syncs without loss or duplication. * (/) The OpenAPI document is regenerated and the typed client still builds. * (/) Deployed to the test environment and accepted by the product owner. | F17: Loyalty | G17: Medium | H17: 5 | J17: EP-L4-LOY | K17: SP-15 | L17: L4 | M17: l4, backend, sp-15
A18: 17 | B18: BE4-LOY02 | C18: Story | D18: BE4-LOY02 — Tiers and rewards | E18: *Side:* Backend *Unit:* Loyalty *Sprint:* SP-15 *Contract status:* Proposed — endpoints must be fixed in the API catalog before this issue is pulled. *Tables:* loyalty_tiers, rewards, redemptions h3. Requirements # Bronze, silver and gold tiers with bound privileges: extra discount, delivery priority, exclusive offers. # A reward catalog with redemption and a complete history. h3. Acceptance criteria * (/) A tier change applies its privileges automatically. * (/) A redemption cannot exceed the available balance under concurrency. h3. Definition of done * (/) Merged after peer review; Larastan level 6, Pint and Rector pass; Deptrac and the architecture suite pass. * (/) Unit and feature tests green: 90%+ on engines and money paths, 75%+ on endpoints, permissions and isolation. * (/) Every write carries X-Idempotency-Key unless it is on the documented exemption list. * (/) Every channel endpoint has an isolation test proving another channel receives 404. * (/) All amounts, limits and rates are integers; no float exists on any money path. * (/) Every state transition goes through the lifecycle service and is logged with actor and reason. * (/) Errors follow the unified envelope and the HTTP status map. * (/) Mobile work functions correctly with the network disconnected and syncs without loss or duplication. * (/) The OpenAPI document is regenerated and the typed client still builds. * (/) Deployed to the test environment and accepted by the product owner. | F18: Loyalty | G18: Medium | H18: 5 | J18: EP-L4-LOY | K18: SP-15 | L18: L4 | M18: l4, backend, sp-15 | N18: 16
A19: 18 | B19: BE4-RPT01 | C19: Story | D19: BE4-RPT01 — Daily snapshots | E19: *Side:* Backend *Unit:* Reporting *Sprint:* SP-15 *Contract status:* Proposed — endpoints must be fixed in the API catalog before this issue is pulled. *Tables:* daily_snapshots h3. Requirements # A nightly job materialising the figures the dashboards read, so interactive screens never aggregate live. # Snapshots run on the reports queue and never contend with operational work. h3. Acceptance criteria * (/) A dashboard screen responds within the interactive budget at production volume. * (/) A snapshot failure is alerted and the previous snapshot is clearly dated. h3. Definition of done * (/) Merged after peer review; Larastan level 6, Pint and Rector pass; Deptrac and the architecture suite pass. * (/) Unit and feature tests green: 90%+ on engines and money paths, 75%+ on endpoints, permissions and isolation. * (/) Every write carries X-Idempotency-Key unless it is on the documented exemption list. * (/) Every channel endpoint has an isolation test proving another channel receives 404. * (/) All amounts, limits and rates are integers; no float exists on any money path. * (/) Every state transition goes through the lifecycle service and is logged with actor and reason. * (/) Errors follow the unified envelope and the HTTP status map. * (/) Mobile work functions correctly with the network disconnected and syncs without loss or duplication. * (/) The OpenAPI document is regenerated and the typed client still builds. * (/) Deployed to the test environment and accepted by the product owner. | F19: Reporting | G19: High | H19: 5 | J19: EP-L4-RPT | K19: SP-15 | L19: L4 | M19: l4, backend, sp-15
A20: 19 | B20: BE4-RPT02 | C20: Story | D20: BE4-RPT02 — Channel dashboard figures | E20: *Side:* Backend *Unit:* Reporting *Sprint:* SP-15 *Contract status:* Proposed — endpoints must be fixed in the API catalog before this issue is pulled. h3. Requirements # The indicator set from DOC-01 §4.1 with a selectable period and comparison to the previous period. # Actionable alerts: overdue pending orders, items at reorder point, returns awaiting decision, reps over their cash cap, retailers over their credit limit, offers expiring within 48 hours, unassigned scheduled orders. # Every card and chart column is drillable to its filtered list. h3. Acceptance criteria * (/) No figure exists without a route to its underlying documents. * (/) The alert list is actionable, with a bulk action attached to each type. h3. Definition of done * (/) Merged after peer review; Larastan level 6, Pint and Rector pass; Deptrac and the architecture suite pass. * (/) Unit and feature tests green: 90%+ on engines and money paths, 75%+ on endpoints, permissions and isolation. * (/) Every write carries X-Idempotency-Key unless it is on the documented exemption list. * (/) Every channel endpoint has an isolation test proving another channel receives 404. * (/) All amounts, limits and rates are integers; no float exists on any money path. * (/) Every state transition goes through the lifecycle service and is logged with actor and reason. * (/) Errors follow the unified envelope and the HTTP status map. * (/) Mobile work functions correctly with the network disconnected and syncs without loss or duplication. * (/) The OpenAPI document is regenerated and the typed client still builds. * (/) Deployed to the test environment and accepted by the product owner. | F20: Reporting | G20: High | H20: 8 | J20: EP-L4-RPT | K20: SP-15 | L20: L4 | M20: l4, backend, sp-15 | N20: 18
A21: 20 | B21: BE4-RPT03 | C21: Story | D21: BE4-RPT03 — The nine report families | E21: *Side:* Backend *Unit:* Reporting *Sprint:* SP-15 *Contract status:* Proposed — endpoints must be fixed in the API catalog before this issue is pulled. h3. Requirements # Sales, products, retailers, reps, zones, inventory, finance, offers and operations. # Every report filters, sorts, exports to Excel and PDF, and prints. # Heavy reports are generated in the background and delivered by notification. h3. Acceptance criteria * (/) Any figure in any report traces back to its originating document (DOC-01 §7). * (/) No report blocks an HTTP request. h3. Definition of done * (/) Merged after peer review; Larastan level 6, Pint and Rector pass; Deptrac and the architecture suite pass. * (/) Unit and feature tests green: 90%+ on engines and money paths, 75%+ on endpoints, permissions and isolation. * (/) Every write carries X-Idempotency-Key unless it is on the documented exemption list. * (/) Every channel endpoint has an isolation test proving another channel receives 404. * (/) All amounts, limits and rates are integers; no float exists on any money path. * (/) Every state transition goes through the lifecycle service and is logged with actor and reason. * (/) Errors follow the unified envelope and the HTTP status map. * (/) Mobile work functions correctly with the network disconnected and syncs without loss or duplication. * (/) The OpenAPI document is regenerated and the typed client still builds. * (/) Deployed to the test environment and accepted by the product owner. | F21: Reporting | G21: Medium | H21: 8 | J21: EP-L4-RPT | K21: SP-15 | L21: L4 | M21: l4, backend, sp-15 | N21: 18
A22: 21 | B22: BE4-RPT04 | C22: Story | D22: BE4-RPT04 — Platform-level reporting | E22: *Side:* Backend *Unit:* Reporting *Sprint:* SP-16 *Contract status:* Proposed — endpoints must be fixed in the API catalog before this issue is pulled. *Tables:* report_jobs, report_exports h3. Requirements # Cross-channel platform figures for the super admin, respecting isolation: aggregates only, never another channel detail. # Background export with job status. h3. Acceptance criteria * (/) A platform aggregate never exposes a single channel commercial detail to another channel. h3. Definition of done * (/) Merged after peer review; Larastan level 6, Pint and Rector pass; Deptrac and the architecture suite pass. * (/) Unit and feature tests green: 90%+ on engines and money paths, 75%+ on endpoints, permissions and isolation. * (/) Every write carries X-Idempotency-Key unless it is on the documented exemption list. * (/) Every channel endpoint has an isolation test proving another channel receives 404. * (/) All amounts, limits and rates are integers; no float exists on any money path. * (/) Every state transition goes through the lifecycle service and is logged with actor and reason. * (/) Errors follow the unified envelope and the HTTP status map. * (/) Mobile work functions correctly with the network disconnected and syncs without loss or duplication. * (/) The OpenAPI document is regenerated and the typed client still builds. * (/) Deployed to the test environment and accepted by the product owner. | F22: Reporting | G22: Medium | H22: 5 | J22: EP-L4-RPT | K22: SP-16 | L22: L4 | M22: l4, backend, sp-16 | N22: 18
A23: 22 | B23: BE4-SUP01 | C23: Story | D23: BE4-SUP01 — Tickets and unified search | E23: *Side:* Backend *Unit:* Support *Sprint:* SP-16 *Contract status:* Proposed — endpoints must be fixed in the API catalog before this issue is pulled. *Tables:* tickets, ticket_events h3. Requirements # A ticket with a subject, a linked entity, a state machine and an event log. # Unified search across retailers, reps, channels, orders and invoices from one field. h3. Acceptance criteria * (/) A support agent finds any entity by number or phone in one search. * (/) Every ticket action is audited. h3. Definition of done * (/) Merged after peer review; Larastan level 6, Pint and Rector pass; Deptrac and the architecture suite pass. * (/) Unit and feature tests green: 90%+ on engines and money paths, 75%+ on endpoints, permissions and isolation. * (/) Every write carries X-Idempotency-Key unless it is on the documented exemption list. * (/) Every channel endpoint has an isolation test proving another channel receives 404. * (/) All amounts, limits and rates are integers; no float exists on any money path. * (/) Every state transition goes through the lifecycle service and is logged with actor and reason. * (/) Errors follow the unified envelope and the HTTP status map. * (/) Mobile work functions correctly with the network disconnected and syncs without loss or duplication. * (/) The OpenAPI document is regenerated and the typed client still builds. * (/) Deployed to the test environment and accepted by the product owner. | F23: Support | G23: Medium | H23: 5 | J23: EP-L4-SUP | K23: SP-16 | L23: L4 | M23: l4, backend, sp-16
A24: 23 | B24: BE4-SUP02 | C24: Story | D24: BE4-SUP02 — Impersonation with guardrails | E24: *Side:* Backend *Unit:* Support *Sprint:* SP-16 *Contract status:* Proposed — endpoints must be fixed in the API catalog before this issue is pulled. *Tables:* impersonation_grants h3. Requirements # Impersonation requires an explicit grant with a reason, a time limit and a second approver. # Every request made while impersonating is flagged in the audit log. # Write actions can be restricted while impersonating. h3. Acceptance criteria * (/) No impersonation exists without a grant and a reason. * (/) The audit log distinguishes an impersonated action from a genuine one. h3. Definition of done * (/) Merged after peer review; Larastan level 6, Pint and Rector pass; Deptrac and the architecture suite pass. * (/) Unit and feature tests green: 90%+ on engines and money paths, 75%+ on endpoints, permissions and isolation. * (/) Every write carries X-Idempotency-Key unless it is on the documented exemption list. * (/) Every channel endpoint has an isolation test proving another channel receives 404. * (/) All amounts, limits and rates are integers; no float exists on any money path. * (/) Every state transition goes through the lifecycle service and is logged with actor and reason. * (/) Errors follow the unified envelope and the HTTP status map. * (/) Mobile work functions correctly with the network disconnected and syncs without loss or duplication. * (/) The OpenAPI document is regenerated and the typed client still builds. * (/) Deployed to the test environment and accepted by the product owner. | F24: Support | G24: High | H24: 5 | J24: EP-L4-SUP | K24: SP-16 | L24: L4 | M24: l4, backend, sp-16
A25: 24 | B25: BE4-SUP03 | C25: Story | D25: BE4-SUP03 — System health view | E25: *Side:* Backend *Unit:* Support *Sprint:* SP-16 *Contract status:* Proposed — endpoints must be fixed in the API catalog before this issue is pulled. h3. Requirements # Queue depth, job failure rate, integration provider health and the last snapshot time. h3. Acceptance criteria * (/) A degraded provider is visible before users report it. h3. Definition of done * (/) Merged after peer review; Larastan level 6, Pint and Rector pass; Deptrac and the architecture suite pass. * (/) Unit and feature tests green: 90%+ on engines and money paths, 75%+ on endpoints, permissions and isolation. * (/) Every write carries X-Idempotency-Key unless it is on the documented exemption list. * (/) Every channel endpoint has an isolation test proving another channel receives 404. * (/) All amounts, limits and rates are integers; no float exists on any money path. * (/) Every state transition goes through the lifecycle service and is logged with actor and reason. * (/) Errors follow the unified envelope and the HTTP status map. * (/) Mobile work functions correctly with the network disconnected and syncs without loss or duplication. * (/) The OpenAPI document is regenerated and the typed client still builds. * (/) Deployed to the test environment and accepted by the product owner. | F25: Support | G25: Medium | H25: 3 | J25: EP-L4-SUP | K25: SP-16 | L25: L4 | M25: l4, backend, sp-16
A26: 25 | B26: BE4-BIL01 | C26: Story | D26: BE4-BIL01 — Plans and subscriptions | E26: *Side:* Backend *Unit:* PlatformBilling *Sprint:* SP-17 *Contract status:* Proposed — endpoints must be fixed in the API catalog before this issue is pulled. *Tables:* plans, subscriptions h3. Requirements # Plan definitions with limits and features that feed the channel limit and feature resolution. # Subscription lifecycle with trial, active, past due and cancelled states. # A plan change reuses the existing preview and apply path. h3. Acceptance criteria * (/) A plan limit change propagates to channel enforcement without a code change. * (/) A trial expiry moves the subscription automatically. h3. Definition of done * (/) Merged after peer review; Larastan level 6, Pint and Rector pass; Deptrac and the architecture suite pass. * (/) Unit and feature tests green: 90%+ on engines and money paths, 75%+ on endpoints, permissions and isolation. * (/) Every write carries X-Idempotency-Key unless it is on the documented exemption list. * (/) Every channel endpoint has an isolation test proving another channel receives 404. * (/) All amounts, limits and rates are integers; no float exists on any money path. * (/) Every state transition goes through the lifecycle service and is logged with actor and reason. * (/) Errors follow the unified envelope and the HTTP status map. * (/) Mobile work functions correctly with the network disconnected and syncs without loss or duplication. * (/) The OpenAPI document is regenerated and the typed client still builds. * (/) Deployed to the test environment and accepted by the product owner. | F26: PlatformBilling | G26: Medium | H26: 8 | J26: EP-L4-BIL | K26: SP-17 | L26: L4 | M26: l4, backend, sp-17
A27: 26 | B27: BE4-BIL02 | C27: Story | D27: BE4-BIL02 — Platform invoices and dunning | E27: *Side:* Backend *Unit:* PlatformBilling *Sprint:* SP-17 *Contract status:* Proposed — endpoints must be fixed in the API catalog before this issue is pulled. *Tables:* platform_invoices, dunning_events h3. Requirements # Generate platform invoices per billing cycle and record payment. # A dunning sequence on failure with an escalation to suspension, which freezes new orders only. h3. Acceptance criteria * (/) Suspension for non-payment does not disturb orders already in flight (BR-AD-14). h3. Definition of done * (/) Merged after peer review; Larastan level 6, Pint and Rector pass; Deptrac and the architecture suite pass. * (/) Unit and feature tests green: 90%+ on engines and money paths, 75%+ on endpoints, permissions and isolation. * (/) Every write carries X-Idempotency-Key unless it is on the documented exemption list. * (/) Every channel endpoint has an isolation test proving another channel receives 404. * (/) All amounts, limits and rates are integers; no float exists on any money path. * (/) Every state transition goes through the lifecycle service and is logged with actor and reason. * (/) Errors follow the unified envelope and the HTTP status map. * (/) Mobile work functions correctly with the network disconnected and syncs without loss or duplication. * (/) The OpenAPI document is regenerated and the typed client still builds. * (/) Deployed to the test environment and accepted by the product owner. | F27: PlatformBilling | G27: Medium | H27: 5 | J27: EP-L4-BIL | K27: SP-17 | L27: L4 | M27: l4, backend, sp-17 | N27: 25
A28: 27 | B28: BE4-BIL03 | C28: Story | D28: BE4-BIL03 — Platform team management | E28: *Side:* Backend *Unit:* PlatformBilling *Sprint:* SP-17 *Contract status:* Proposed — endpoints must be fixed in the API catalog before this issue is pulled. h3. Requirements # Full CRUD for platform staff with role assignment through the existing IAM paths. # Deactivation transfers open approvals rather than orphaning them. h3. Acceptance criteria * (/) A deactivated admin leaves no approval request without an approver. h3. Definition of done * (/) Merged after peer review; Larastan level 6, Pint and Rector pass; Deptrac and the architecture suite pass. * (/) Unit and feature tests green: 90%+ on engines and money paths, 75%+ on endpoints, permissions and isolation. * (/) Every write carries X-Idempotency-Key unless it is on the documented exemption list. * (/) Every channel endpoint has an isolation test proving another channel receives 404. * (/) All amounts, limits and rates are integers; no float exists on any money path. * (/) Every state transition goes through the lifecycle service and is logged with actor and reason. * (/) Errors follow the unified envelope and the HTTP status map. * (/) Mobile work functions correctly with the network disconnected and syncs without loss or duplication. * (/) The OpenAPI document is regenerated and the typed client still builds. * (/) Deployed to the test environment and accepted by the product owner. | F28: PlatformBilling | G28: Medium | H28: 5 | J28: EP-L4-BIL | K28: SP-17 | L28: L4 | M28: l4, backend, sp-17
A29: 28 | B29: BE4-HRD01 | C29: Story | D29: BE4-HRD01 — Performance hardening | E29: *Side:* Backend *Unit:* — *Sprint:* SP-16 *Contract status:* Proposed — endpoints must be fixed in the API catalog before this issue is pulled. h3. Requirements # Meet the DOC-01 §7 targets: under one second for daily operational screens, under three seconds for interactive reports. # Sustain a catalog of 100,000 items, 10,000 active retailers and 5,000 orders per day per channel without noticeable degradation. # Index review on every hot query path; eliminate every N+1 on list screens. h3. Acceptance criteria * (/) A k6 run at one thousand concurrent users on list and submission paths holds the budget. * (/) No list endpoint issues a per-row query. h3. Definition of done * (/) Merged after peer review; Larastan level 6, Pint and Rector pass; Deptrac and the architecture suite pass. * (/) Unit and feature tests green: 90%+ on engines and money paths, 75%+ on endpoints, permissions and isolation. * (/) Every write carries X-Idempotency-Key unless it is on the documented exemption list. * (/) Every channel endpoint has an isolation test proving another channel receives 404. * (/) All amounts, limits and rates are integers; no float exists on any money path. * (/) Every state transition goes through the lifecycle service and is logged with actor and reason. * (/) Errors follow the unified envelope and the HTTP status map. * (/) Mobile work functions correctly with the network disconnected and syncs without loss or duplication. * (/) The OpenAPI document is regenerated and the typed client still builds. * (/) Deployed to the test environment and accepted by the product owner. | F29: platform | G29: Highest | H29: 8 | J29: EP-L4-HRD | K29: SP-16 | L29: L4 | M29: l4, backend, sp-16 | N29: 18
A30: 29 | B30: BE4-HRD02 | C30: Story | D30: BE4-HRD02 — Security hardening and penetration pass | E30: *Side:* Backend *Unit:* — *Sprint:* SP-16 *Contract status:* Proposed — endpoints must be fixed in the API catalog before this issue is pulled. h3. Requirements # A deliberate attempt to reach another channel data across every endpoint, expected to fail. # Verification that the channel identity and the rep identity cannot be obtained early through any API path (AC-08). # File upload, rate limit, session and token handling review. # Encrypted daily off-server backup with a documented restore, and a recovery-time objective under four hours. h3. Acceptance criteria * (/) The isolation attempt fails on every endpoint without exception. * (/) A restore is executed and timed against the four-hour objective. h3. Definition of done * (/) Merged after peer review; Larastan level 6, Pint and Rector pass; Deptrac and the architecture suite pass. * (/) Unit and feature tests green: 90%+ on engines and money paths, 75%+ on endpoints, permissions and isolation. * (/) Every write carries X-Idempotency-Key unless it is on the documented exemption list. * (/) Every channel endpoint has an isolation test proving another channel receives 404. * (/) All amounts, limits and rates are integers; no float exists on any money path. * (/) Every state transition goes through the lifecycle service and is logged with actor and reason. * (/) Errors follow the unified envelope and the HTTP status map. * (/) Mobile work functions correctly with the network disconnected and syncs without loss or duplication. * (/) The OpenAPI document is regenerated and the typed client still builds. * (/) Deployed to the test environment and accepted by the product owner. | F30: platform | G30: Highest | H30: 8 | J30: EP-L4-HRD | K30: SP-16 | L30: L4 | M30: l4, backend, sp-16
A31: 30 | B31: BE4-HRD03 | C31: Story | D31: BE4-HRD03 — Field acceptance criteria verification | E31: *Side:* Backend *Unit:* — *Sprint:* SP-17 *Contract status:* Proposed — endpoints must be fixed in the API catalog before this issue is pulled. h3. Requirements # Verify AC-01 through AC-10 from DOC-06 §9.1 with real users, not in a meeting room. # Registration under sixty seconds, retailer order in three to four taps, rep order under thirty seconds, value understood in ten seconds. # Zero lost or duplicated operations after a full day offline with deliberate interruptions. # Wallet, statement and stock all reconcile exactly. h3. Acceptance criteria * (/) Every one of the ten criteria is measured and recorded with real participants. * (/) A failure on any criterion blocks the pilot rather than being noted for later. h3. Definition of done * (/) Merged after peer review; Larastan level 6, Pint and Rector pass; Deptrac and the architecture suite pass. * (/) Unit and feature tests green: 90%+ on engines and money paths, 75%+ on endpoints, permissions and isolation. * (/) Every write carries X-Idempotency-Key unless it is on the documented exemption list. * (/) Every channel endpoint has an isolation test proving another channel receives 404. * (/) All amounts, limits and rates are integers; no float exists on any money path. * (/) Every state transition goes through the lifecycle service and is logged with actor and reason. * (/) Errors follow the unified envelope and the HTTP status map. * (/) Mobile work functions correctly with the network disconnected and syncs without loss or duplication. * (/) The OpenAPI document is regenerated and the typed client still builds. * (/) Deployed to the test environment and accepted by the product owner. | F31: platform | G31: Highest | H31: 8 | J31: EP-L4-HRD | K31: SP-17 | L31: L4 | M31: l4, backend, sp-17
A32: 31 | B32: BE4-HRD04 | C32: Story | D32: BE4-HRD04 — Pilot launch | E32: *Side:* Backend *Unit:* — *Sprint:* SP-17 *Contract status:* Proposed — endpoints must be fixed in the API catalog before this issue is pulled. h3. Requirements # One channel, a limited zone set, real retailers and real reps. # Launch condition: a complete catalog with current prices for the pilot zone (DOC-06 §10.2). # A daily observation log of every stumble, with a named owner per issue. h3. Acceptance criteria * (/) A complete cycle runs with real users and no financial discrepancy. * (/) Manual intervention falls to a minimum before the general release. h3. Definition of done * (/) Merged after peer review; Larastan level 6, Pint and Rector pass; Deptrac and the architecture suite pass. * (/) Unit and feature tests green: 90%+ on engines and money paths, 75%+ on endpoints, permissions and isolation. * (/) Every write carries X-Idempotency-Key unless it is on the documented exemption list. * (/) Every channel endpoint has an isolation test proving another channel receives 404. * (/) All amounts, limits and rates are integers; no float exists on any money path. * (/) Every state transition goes through the lifecycle service and is logged with actor and reason. * (/) Errors follow the unified envelope and the HTTP status map. * (/) Mobile work functions correctly with the network disconnected and syncs without loss or duplication. * (/) The OpenAPI document is regenerated and the typed client still builds. * (/) Deployed to the test environment and accepted by the product owner. | F32: platform | G32: Highest | H32: 8 | J32: EP-L4-HRD | K32: SP-17 | L32: L4 | M32: l4, backend, sp-17 | N32: 30
A33: 32 | B33: BE4-HRD05 | C33: Story | D33: BE4-HRD05 — General release readiness | E33: *Side:* Backend *Unit:* — *Sprint:* SP-18 *Contract status:* Proposed — endpoints must be fixed in the API catalog before this issue is pulled. h3. Requirements # Store submissions with terms, privacy policy and support material in place. # Runbooks for operations, monitoring dashboards and an on-call rotation. # A documented rollback plan for the first weeks. h3. Acceptance criteria * (/) Every release-readiness criterion in DOC-02 §25 is met and signed off. h3. Definition of done * (/) Merged after peer review; Larastan level 6, Pint and Rector pass; Deptrac and the architecture suite pass. * (/) Unit and feature tests green: 90%+ on engines and money paths, 75%+ on endpoints, permissions and isolation. * (/) Every write carries X-Idempotency-Key unless it is on the documented exemption list. * (/) Every channel endpoint has an isolation test proving another channel receives 404. * (/) All amounts, limits and rates are integers; no float exists on any money path. * (/) Every state transition goes through the lifecycle service and is logged with actor and reason. * (/) Errors follow the unified envelope and the HTTP status map. * (/) Mobile work functions correctly with the network disconnected and syncs without loss or duplication. * (/) The OpenAPI document is regenerated and the typed client still builds. * (/) Deployed to the test environment and accepted by the product owner. | F33: platform | G33: Highest | H33: 5 | J33: EP-L4-HRD | K33: SP-18 | L33: L4 | M33: l4, backend, sp-18 | N33: 31
A34: 33 | B34: FE4-RT01 | C34: Story | D34: FE4-RT01 — Retailer favourites, rating and notifications | E34: *Side:* Frontend *Unit:* Retailer app *Sprint:* SP-14 *Contract status:* Proposed — endpoints must be fixed in the API catalog before this issue is pulled. h3. Requirements # Favourites with individual and bulk add to cart and an empty-state message. # Rep rating appearing automatically after delivery, five stars with quick tags, skippable. # Notification list newest first with mark all read and clear all. h3. Acceptance criteria * (/) A read notification leaves the counter but stays in the log (BR-17). * (/) The rating screen never blocks the flow. h3. Definition of done * (/) Merged after peer review; Larastan level 6, Pint and Rector pass; Deptrac and the architecture suite pass. * (/) Unit and feature tests green: 90%+ on engines and money paths, 75%+ on endpoints, permissions and isolation. * (/) Every write carries X-Idempotency-Key unless it is on the documented exemption list. * (/) Every channel endpoint has an isolation test proving another channel receives 404. * (/) All amounts, limits and rates are integers; no float exists on any money path. * (/) Every state transition goes through the lifecycle service and is logged with actor and reason. * (/) Errors follow the unified envelope and the HTTP status map. * (/) Mobile work functions correctly with the network disconnected and syncs without loss or duplication. * (/) The OpenAPI document is regenerated and the typed client still builds. * (/) Deployed to the test environment and accepted by the product owner. | F34: Retailer app | G34: Medium | H34: 5 | J34: EP-L4-FE | K34: SP-14 | L34: L4 | M34: l4, frontend, sp-14 | N34: 13
A35: 34 | B35: FE4-RT02 | C35: Story | D35: FE4-RT02 — Retailer growth features | E35: *Side:* Frontend *Unit:* Retailer app *Sprint:* SP-15 *Contract status:* Proposed — endpoints must be fixed in the API catalog before this issue is pulled. h3. Requirements # Points and rewards bar, algorithm sliders, price comparison, voice search. # These are phase-three features and must not slow the core order path. h3. Acceptance criteria * (/) Home load time does not regress against the phase-one measurement. h3. Definition of done * (/) Merged after peer review; Larastan level 6, Pint and Rector pass; Deptrac and the architecture suite pass. * (/) Unit and feature tests green: 90%+ on engines and money paths, 75%+ on endpoints, permissions and isolation. * (/) Every write carries X-Idempotency-Key unless it is on the documented exemption list. * (/) Every channel endpoint has an isolation test proving another channel receives 404. * (/) All amounts, limits and rates are integers; no float exists on any money path. * (/) Every state transition goes through the lifecycle service and is logged with actor and reason. * (/) Errors follow the unified envelope and the HTTP status map. * (/) Mobile work functions correctly with the network disconnected and syncs without loss or duplication. * (/) The OpenAPI document is regenerated and the typed client still builds. * (/) Deployed to the test environment and accepted by the product owner. | F35: Retailer app | G35: Medium | H35: 5 | J35: EP-L4-FE | K35: SP-15 | L35: L4 | M35: l4, frontend, sp-15 | N35: 11 17
A36: 35 | B36: FE4-RP01 | C36: Story | D36: FE4-RP01 — Rep account, statistics and notifications | E36: *Side:* Frontend *Unit:* Rep app *Sprint:* SP-14 *Contract status:* Proposed — endpoints must be fixed in the API catalog before this issue is pulled. h3. Requirements # Monthly statistics card with executed orders, new customers, fulfilment rate and points. # Settings and information lists, work-zone editing, sign out. # Notification list with the same rules as the retailer app. h3. Acceptance criteria * (/) Editing work zones takes effect after channel approval, not immediately. h3. Definition of done * (/) Merged after peer review; Larastan level 6, Pint and Rector pass; Deptrac and the architecture suite pass. * (/) Unit and feature tests green: 90%+ on engines and money paths, 75%+ on endpoints, permissions and isolation. * (/) Every write carries X-Idempotency-Key unless it is on the documented exemption list. * (/) Every channel endpoint has an isolation test proving another channel receives 404. * (/) All amounts, limits and rates are integers; no float exists on any money path. * (/) Every state transition goes through the lifecycle service and is logged with actor and reason. * (/) Errors follow the unified envelope and the HTTP status map. * (/) Mobile work functions correctly with the network disconnected and syncs without loss or duplication. * (/) The OpenAPI document is regenerated and the typed client still builds. * (/) Deployed to the test environment and accepted by the product owner. | F36: Rep app | G36: Medium | H36: 5 | J36: EP-L4-FE | K36: SP-14 | L36: L4 | M36: l4, frontend, sp-14 | N36: 13
A37: 36 | B37: FE4-RP02 | C37: Story | D37: FE4-RP02 — Rep growth features | E37: *Side:* Frontend *Unit:* Rep app *Sprint:* SP-15 *Contract status:* Proposed — endpoints must be fixed in the API catalog before this issue is pulled. h3. Requirements # Points and rewards, custom sliders, personal performance analytics. # Presented as enablement, never as surveillance, because a rep who feels watched will resist the app (DOC-05 §2.1). h3. Acceptance criteria * (/) The rep sees their own wallet, points and ratings before they see any monitoring figure. h3. Definition of done * (/) Merged after peer review; Larastan level 6, Pint and Rector pass; Deptrac and the architecture suite pass. * (/) Unit and feature tests green: 90%+ on engines and money paths, 75%+ on endpoints, permissions and isolation. * (/) Every write carries X-Idempotency-Key unless it is on the documented exemption list. * (/) Every channel endpoint has an isolation test proving another channel receives 404. * (/) All amounts, limits and rates are integers; no float exists on any money path. * (/) Every state transition goes through the lifecycle service and is logged with actor and reason. * (/) Errors follow the unified envelope and the HTTP status map. * (/) Mobile work functions correctly with the network disconnected and syncs without loss or duplication. * (/) The OpenAPI document is regenerated and the typed client still builds. * (/) Deployed to the test environment and accepted by the product owner. | F37: Rep app | G37: Low | H37: 3 | J37: EP-L4-FE | K37: SP-15 | L37: L4 | M37: l4, frontend, sp-15 | N37: 16
A38: 37 | B38: FE4-CH01 | C38: Story | D38: FE4-CH01 — Content and marketing console | E38: *Side:* Frontend *Unit:* Channel dashboard *Sprint:* SP-14 *Contract status:* Proposed — endpoints must be fixed in the API catalog before this issue is pulled. h3. Requirements # Intro control, banner builder with placement, targeting, window and measurement. # Slider builder with source selection including algorithms and per-activity customisation. # Brand page composition. h3. Acceptance criteria * (/) A banner cannot be published without a placement and a window. * (/) Click-through rate is visible per banner. h3. Definition of done * (/) Merged after peer review; Larastan level 6, Pint and Rector pass; Deptrac and the architecture suite pass. * (/) Unit and feature tests green: 90%+ on engines and money paths, 75%+ on endpoints, permissions and isolation. * (/) Every write carries X-Idempotency-Key unless it is on the documented exemption list. * (/) Every channel endpoint has an isolation test proving another channel receives 404. * (/) All amounts, limits and rates are integers; no float exists on any money path. * (/) Every state transition goes through the lifecycle service and is logged with actor and reason. * (/) Errors follow the unified envelope and the HTTP status map. * (/) Mobile work functions correctly with the network disconnected and syncs without loss or duplication. * (/) The OpenAPI document is regenerated and the typed client still builds. * (/) Deployed to the test environment and accepted by the product owner. | F38: Channel dashboard | G38: High | H38: 8 | J38: EP-L4-FE | K38: SP-14 | L38: L4 | M38: l4, frontend, sp-14 | N38: 10 11
A39: 38 | B39: FE4-CH02 | C39: Story | D39: FE4-CH02 — Notification and campaign console | E39: *Side:* Frontend *Unit:* Channel dashboard *Sprint:* SP-14 *Contract status:* Proposed — endpoints must be fixed in the API catalog before this issue is pulled. h3. Requirements # Compose, target, schedule and review the delivery log. # Automatic template management bound to system events. h3. Acceptance criteria * (/) An audience count is shown before sending, not after. h3. Definition of done * (/) Merged after peer review; Larastan level 6, Pint and Rector pass; Deptrac and the architecture suite pass. * (/) Unit and feature tests green: 90%+ on engines and money paths, 75%+ on endpoints, permissions and isolation. * (/) Every write carries X-Idempotency-Key unless it is on the documented exemption list. * (/) Every channel endpoint has an isolation test proving another channel receives 404. * (/) All amounts, limits and rates are integers; no float exists on any money path. * (/) Every state transition goes through the lifecycle service and is logged with actor and reason. * (/) Errors follow the unified envelope and the HTTP status map. * (/) Mobile work functions correctly with the network disconnected and syncs without loss or duplication. * (/) The OpenAPI document is regenerated and the typed client still builds. * (/) Deployed to the test environment and accepted by the product owner. | F39: Channel dashboard | G39: High | H39: 5 | J39: EP-L4-FE | K39: SP-14 | L39: L4 | M39: l4, frontend, sp-14 | N39: 15
A40: 39 | B40: FE4-CH03 | C40: Story | D40: FE4-CH03 — Reports console | E40: *Side:* Frontend *Unit:* Channel dashboard *Sprint:* SP-15 *Contract status:* Proposed — endpoints must be fixed in the API catalog before this issue is pulled. h3. Requirements # The nine report families with saved filters, export and print. # A heavy report runs in the background and arrives by notification. h3. Acceptance criteria * (/) Every figure drills down to its source document. * (/) No report freezes the page. h3. Definition of done * (/) Merged after peer review; Larastan level 6, Pint and Rector pass; Deptrac and the architecture suite pass. * (/) Unit and feature tests green: 90%+ on engines and money paths, 75%+ on endpoints, permissions and isolation. * (/) Every write carries X-Idempotency-Key unless it is on the documented exemption list. * (/) Every channel endpoint has an isolation test proving another channel receives 404. * (/) All amounts, limits and rates are integers; no float exists on any money path. * (/) Every state transition goes through the lifecycle service and is logged with actor and reason. * (/) Errors follow the unified envelope and the HTTP status map. * (/) Mobile work functions correctly with the network disconnected and syncs without loss or duplication. * (/) The OpenAPI document is regenerated and the typed client still builds. * (/) Deployed to the test environment and accepted by the product owner. | F40: Channel dashboard | G40: High | H40: 8 | J40: EP-L4-FE | K40: SP-15 | L40: L4 | M40: l4, frontend, sp-15 | N40: 20
A41: 40 | B41: FE4-CH04 | C41: Story | D41: FE4-CH04 — Loyalty console | E41: *Side:* Frontend *Unit:* Channel dashboard *Sprint:* SP-15 *Contract status:* Proposed — endpoints must be fixed in the API catalog before this issue is pulled. h3. Requirements # Point rules, tiers, reward catalog and redemption history. h3. Acceptance criteria * (/) A rule change is previewed against a sample before publishing. h3. Definition of done * (/) Merged after peer review; Larastan level 6, Pint and Rector pass; Deptrac and the architecture suite pass. * (/) Unit and feature tests green: 90%+ on engines and money paths, 75%+ on endpoints, permissions and isolation. * (/) Every write carries X-Idempotency-Key unless it is on the documented exemption list. * (/) Every channel endpoint has an isolation test proving another channel receives 404. * (/) All amounts, limits and rates are integers; no float exists on any money path. * (/) Every state transition goes through the lifecycle service and is logged with actor and reason. * (/) Errors follow the unified envelope and the HTTP status map. * (/) Mobile work functions correctly with the network disconnected and syncs without loss or duplication. * (/) The OpenAPI document is regenerated and the typed client still builds. * (/) Deployed to the test environment and accepted by the product owner. | F41: Channel dashboard | G41: Low | H41: 3 | J41: EP-L4-FE | K41: SP-15 | L41: L4 | M41: l4, frontend, sp-15 | N41: 17
A42: 41 | B42: FE4-AD01 | C42: Story | D42: FE4-AD01 — Platform operations dashboard | E42: *Side:* Frontend *Unit:* Platform admin *Sprint:* SP-16 *Contract status:* Proposed — endpoints must be fixed in the API catalog before this issue is pulled. h3. Requirements # The live platform view deferred from Layer 1: cross-channel aggregates, growth and health. # Explicitly out of scope in L1 and only now permitted, because the underlying figures finally exist. h3. Acceptance criteria * (/) No aggregate exposes one channel commercial detail to another. * (/) The screen reads snapshots, never live aggregation. h3. Definition of done * (/) Merged after peer review; Larastan level 6, Pint and Rector pass; Deptrac and the architecture suite pass. * (/) Unit and feature tests green: 90%+ on engines and money paths, 75%+ on endpoints, permissions and isolation. * (/) Every write carries X-Idempotency-Key unless it is on the documented exemption list. * (/) Every channel endpoint has an isolation test proving another channel receives 404. * (/) All amounts, limits and rates are integers; no float exists on any money path. * (/) Every state transition goes through the lifecycle service and is logged with actor and reason. * (/) Errors follow the unified envelope and the HTTP status map. * (/) Mobile work functions correctly with the network disconnected and syncs without loss or duplication. * (/) The OpenAPI document is regenerated and the typed client still builds. * (/) Deployed to the test environment and accepted by the product owner. | F42: Platform admin | G42: High | H42: 8 | J42: EP-L4-FE | K42: SP-16 | L42: L4 | M42: l4, frontend, sp-16 | N42: 21
A43: 42 | B43: FE4-AD02 | C43: Story | D43: FE4-AD02 — Support console and impersonation | E43: *Side:* Frontend *Unit:* Platform admin *Sprint:* SP-16 *Contract status:* Proposed — endpoints must be fixed in the API catalog before this issue is pulled. h3. Requirements # Ticket queue, unified search, the 360 view of any entity. # Impersonation behind a grant, a reason and a visible banner throughout the session. h3. Acceptance criteria * (/) The impersonation banner is impossible to dismiss while the session is active. h3. Definition of done * (/) Merged after peer review; Larastan level 6, Pint and Rector pass; Deptrac and the architecture suite pass. * (/) Unit and feature tests green: 90%+ on engines and money paths, 75%+ on endpoints, permissions and isolation. * (/) Every write carries X-Idempotency-Key unless it is on the documented exemption list. * (/) Every channel endpoint has an isolation test proving another channel receives 404. * (/) All amounts, limits and rates are integers; no float exists on any money path. * (/) Every state transition goes through the lifecycle service and is logged with actor and reason. * (/) Errors follow the unified envelope and the HTTP status map. * (/) Mobile work functions correctly with the network disconnected and syncs without loss or duplication. * (/) The OpenAPI document is regenerated and the typed client still builds. * (/) Deployed to the test environment and accepted by the product owner. | F43: Platform admin | G43: Medium | H43: 5 | J43: EP-L4-FE | K43: SP-16 | L43: L4 | M43: l4, frontend, sp-16 | N43: 22 23
A44: 43 | B44: FE4-AD03 | C44: Story | D44: FE4-AD03 — Billing and platform team console | E44: *Side:* Frontend *Unit:* Platform admin *Sprint:* SP-17 *Contract status:* Proposed — endpoints must be fixed in the API catalog before this issue is pulled. h3. Requirements # Plan catalog, channel subscriptions, platform invoices and the dunning view. # Full platform team CRUD, deferred from Layer 1. h3. Acceptance criteria * (/) A suspension for non-payment shows exactly what it freezes and what it leaves running. h3. Definition of done * (/) Merged after peer review; Larastan level 6, Pint and Rector pass; Deptrac and the architecture suite pass. * (/) Unit and feature tests green: 90%+ on engines and money paths, 75%+ on endpoints, permissions and isolation. * (/) Every write carries X-Idempotency-Key unless it is on the documented exemption list. * (/) Every channel endpoint has an isolation test proving another channel receives 404. * (/) All amounts, limits and rates are integers; no float exists on any money path. * (/) Every state transition goes through the lifecycle service and is logged with actor and reason. * (/) Errors follow the unified envelope and the HTTP status map. * (/) Mobile work functions correctly with the network disconnected and syncs without loss or duplication. * (/) The OpenAPI document is regenerated and the typed client still builds. * (/) Deployed to the test environment and accepted by the product owner. | F44: Platform admin | G44: Medium | H44: 5 | J44: EP-L4-FE | K44: SP-17 | L44: L4 | M44: l4, frontend, sp-17 | N44: 25 27
A45: 44 | B45: FE4-QA01 | C45: Story | D45: FE4-QA01 — Field testing programme | E45: *Side:* Frontend *Unit:* — *Sprint:* SP-17 *Contract status:* Proposed — endpoints must be fixed in the API catalog before this issue is pulled. h3. Requirements # Test in the street, in sunlight, while moving, one handed — desk testing does not surface these failures (DOC-06 §9.2). # Deliberate connectivity cuts in the middle of financial operations. # At least three devices including one low specification; a full working day with a real rep and an observer. # A retailer who has never used a similar app, with no prior explanation. # Battery and data consumption measured across a full working day. h3. Acceptance criteria * (/) Every one of the ten acceptance criteria is measured in the field, not in the office. * (/) The observation log names an owner for every stumble recorded. h3. Definition of done * (/) Merged after peer review; Larastan level 6, Pint and Rector pass; Deptrac and the architecture suite pass. * (/) Unit and feature tests green: 90%+ on engines and money paths, 75%+ on endpoints, permissions and isolation. * (/) Every write carries X-Idempotency-Key unless it is on the documented exemption list. * (/) Every channel endpoint has an isolation test proving another channel receives 404. * (/) All amounts, limits and rates are integers; no float exists on any money path. * (/) Every state transition goes through the lifecycle service and is logged with actor and reason. * (/) Errors follow the unified envelope and the HTTP status map. * (/) Mobile work functions correctly with the network disconnected and syncs without loss or duplication. * (/) The OpenAPI document is regenerated and the typed client still builds. * (/) Deployed to the test environment and accepted by the product owner. | F45: platform | G45: Highest | H45: 8 | J45: EP-L4-HRD | K45: SP-17 | L45: L4 | M45: l4, frontend, sp-17
